Workbook

Sheet Sheet
A1: SUBSISTEMA DE CONTABILIDAD
A2: TRANSAMBIENTAL S.A.S.
A3: CONSULTA DE MOVIMIENTO POR FUENTES A 26.AGO./2025
A4: PERIODO COMPRENDIDO ENTRE 01.ENE./2025 Y 31.JUL./2025 | I4: =SUBTOTAL(9,I7:I521) -> 109263756 | J4: =SUBTOTAL(9,J7:J521) -> 96904517 | K4: =+I4-J4 -> 12359239
A6: Codigo Cuenta | B6: Nombre Cuenta | C6: Fecha Documento | D6: Fuente | E6: Nombre Fuente | F6: Prefijo Documento | G6: Numero Documento | H6: Detalle del Registro | I6: Valor Debito | J6: Valor Credito | K6: Tipo Anexo | L6: Id.Tercero | M6: Nombre Tercero | N6: Codigo Costo | O6: Nombre Costo | P6: Codigo Retencion | Q6: Concepto Retencion | R6: Base Retencion | S6: Tipo Libro | T6: Asiento Cierre | U6: Documento Referencia | V6: Numero Cheque | W6: Codigo Operacion | X6: Fecha Operacion | Y6: Programa | Z6: Estacion | AA6: Empresa | AB6: Fecha Version | AC6: Estado Reg.
A7: 138020001 | B7: REINTEGRO DE INCAPACIDADES | C7: 45681 | D7: 15 | E7: CONSIGNACIONES BANCO | G7: 000000701 | H7: SALUD TOTAL S.A. EPS ARS:REINTEGRO INCAPACIDAD000000701 | I7: 0 | J7: 433330 | K7: 1 | L7: 800130907 | M7: SALUD TOTAL S.A. EPS ARS | R7: 0 | S7: CONTABLE | T7: N | U7: 000000701 | V7: 0 | W7: TACOTESO | X7: Feb 6 2025 2:03PM | Y7: frmBAN607 | Z7: TA-COOR-TESO | AA7: TAMBIENTAL | AB7: Feb 6 2025 2:03PM
A8: 138020001 | B8: REINTEGRO DE INCAPACIDADES | C8: 45679 | D8: 15 | E8: CONSIGNACIONES BANCO | G8: 000000702 | H8: E.P.S. SANITAS S.A.:REINTEGRO INCAPACIDAD000000702 | I8: 0 | J8: 718378 | K8: 1 | L8: 800251440 | M8: E.P.S. SANITAS S.A. | R8: 0 | S8: CONTABLE | T8: N | U8: 000000702 | V8: 0 | W8: TACOTESO | X8: Feb 6 2025 2:04PM | Y8: frmBAN607 | Z8: TA-COOR-TESO | AA8: TAMBIENTAL | AB8: Feb 6 2025 2:04PM
A9: 138020001 | B9: REINTEGRO DE INCAPACIDADES | C9: 45674 | D9: 15 | E9: CONSIGNACIONES BANCO | G9: 000000703 | H9: E.P.S. SANITAS S.A.:REINTEGRO INCAPACIDAD000000703 | I9: 0 | J9: 2463437 | K9: 1 | L9: 800251440 | M9: E.P.S. SANITAS S.A. | R9: 0 | S9: CONTABLE | T9: N | U9: 000000703 | V9: 0 | W9: TACOTESO | X9: Feb 6 2025 2:05PM | Y9: frmBAN607 | Z9: TA-COOR-TESO | AA9: TAMBIENTAL | AB9: Feb 6 2025 2:05PM
A10: 138020001 | B10: REINTEGRO DE INCAPACIDADES | C10: 45671 | D10: 15 | E10: CONSIGNACIONES BANCO | G10: 000000704 | H10: EPS SURA COMPAÑIA SURAMERICANA SERVICIOS DE SALUD:REINTEGRO INCAPACIDAD000000704 | I10: 0 | J10: 2165553 | K10: 1 | L10: 800088702 | M10: EPS SURA COMPAÑIA SURAMERICANA SERVICIOS DE SALUD | R10: 0 | S10: CONTABLE | T10: N | U10: 000000704 | V10: 0 | W10: TACOTESO | X10: Feb 6 2025 2:06PM | Y10: frmBAN607 | Z10: TA-COOR-TESO | AA10: TAMBIENTAL | AB10: Feb 6 2025 2:06PM
A11: 138020001 | B11: REINTEGRO DE INCAPACIDADES | C11: 45667 | D11: 15 | E11: CONSIGNACIONES BANCO | G11: 000000706 | H11: NUEVA EMPRESA PROMOTORA DE SALUD:REINTEGRO INCAPACIDAD000000706 | I11: 0 | J11: 780001 | K11: 1 | L11: 900156264 | M11: NUEVA EMPRESA PROMOTORA DE SALUD | R11: 0 | S11: CONTABLE | T11: N | U11: 000000706 | V11: 0 | W11: TACOTESO | X11: Feb 6 2025 2:08PM | Y11: frmBAN607 | Z11: TA-COOR-TESO | AA11: TAMBIENTAL | AB11: Feb 6 2025 2:08PM
A12: 138020001 | B12: REINTEGRO DE INCAPACIDADES | C12: 45667 | D12: 15 | E12: CONSIGNACIONES BANCO | G12: 000000705 | H12: SALUD TOTAL S.A. EPS ARS:REINTEGRO INCAPACIDAD000000705 | I12: 0 | J12: 942452 | K12: 1 | L12: 800130907 | M12: SALUD TOTAL S.A. EPS ARS | R12: 0 | S12: CONTABLE | T12: N | U12: 000000705 | V12: 0 | W12: TACOTESO | X12: Feb 6 2025 2:07PM | Y12: frmBAN607 | Z12: TA-COOR-TESO | AA12: TAMBIENTAL | AB12: Feb 6 2025 2:07PM
A13: 138020001 | B13: REINTEGRO DE INCAPACIDADES | C13: 45688 | D13: 21 | E13: NOMINA NOVASOFT | G13: 000000043 | H13: GASTOS REEMBOLSABLES | I13: 711750 | J13: 0 | K13: 1 | L13: 73169783 | M13: VERGARA ORTEGA BERCELIO | N13: 10030400 | O13: OPERADORES | R13: 0 | S13: CONTABLE | T13: N | U13: 000000043 | V13: 0 | W13: TAAUXAREA | X13: Feb 18 2025 9:10AM | Y13: frmCON6093 | Z13: TA-ANA-CONT | AA13: TAMBIENTAL | AB13: Feb 18 2025 9:10AM
A14: 138020001 | B14: REINTEGRO DE INCAPACIDADES | C14: 45688 | D14: 21 | E14: NOMINA NOVASOFT | G14: 000000043 | H14: GASTOS REEMBOLSABLES | I14: 711750 | J14: 0 | K14: 1 | L14: 73169783 | M14: VERGARA ORTEGA BERCELIO | N14: 10030400 | O14: OPERADORES | R14: 0 | S14: CONTABLE | T14: N | U14: 000000043 | V14: 0 | W14: TAAUXAREA | X14: Feb 18 2025 9:10AM | Y14: frmCON6093 | Z14: TA-ANA-CONT | AA14: TAMBIENTAL | AB14: Feb 18 2025 9:10AM
A15: 138020001 | B15: REINTEGRO DE INCAPACIDADES | C15: 45688 | D15: 21 | E15: NOMINA NOVASOFT | G15: 000000043 | H15: GASTOS REEMBOLSABLES | I15: 49214 | J15: 0 | K15: 1 | L15: 73579382 | M15: HENRRY VARGAS CHICO | N15: 10030400 | O15: OPERADORES | R15: 0 | S15: CONTABLE | T15: N | U15: 000000043 | V15: 0 | W15: TAAUXAREA | X15: Feb 18 2025 9:10AM | Y15: frmCON6093 | Z15: TA-ANA-CONT | AA15: TAMBIENTAL | AB15: Feb 18 2025 9:10AM
A16: 138020001 | B16: REINTEGRO DE INCAPACIDADES | C16: 45688 | D16: 21 | E16: NOMINA NOVASOFT | G16: 000000043 | H16: GASTOS REEMBOLSABLES | I16: 449970 | J16: 0 | K16: 1 | L16: 72195323 | M16: LUIS ALFONSO UPARELA LARA | N16: 10020200 | O16: EJECUCIÓN | R16: 0 | S16: CONTABLE | T16: N | U16: 000000043 | V16: 0 | W16: TAAUXAREA | X16: Feb 18 2025 9:10AM | Y16: frmCON6093 | Z16: TA-ANA-CONT | AA16: TAMBIENTAL | AB16: Feb 18 2025 9:10AM
A17: 138020001 | B17: REINTEGRO DE INCAPACIDADES | C17: 45688 | D17: 21 | E17: NOMINA NOVASOFT | G17: 000000043 | H17: GASTOS REEMBOLSABLES | I17: 47450 | J17: 0 | K17: 1 | L17: 1002059942 | M17: WILSON RAFAEL SIMANCAS MARTINEZ | N17: 10030400 | O17: OPERADORES | R17: 0 | S17: CONTABLE | T17: N | U17: 000000043 | V17: 0 | W17: TAAUXAREA | X17: Feb 18 2025 9:10AM | Y17: frmCON6093 | Z17: TA-ANA-CONT | AA17: TAMBIENTAL | AB17: Feb 18 2025 9:10AM
A18: 138020001 | B18: REINTEGRO DE INCAPACIDADES | C18: 45688 | D18: 21 | E18: NOMINA NOVASOFT | G18: 000000043 | H18: GASTOS REEMBOLSABLES | I18: 152520 | J18: 0 | K18: 1 | L18: 1050959328 | M18: WILMER ANTONIO SILVA VARGAS | N18: 10030400 | O18: OPERADORES | R18: 0 | S18: CONTABLE | T18: N | U18: 000000043 | V18: 0 | W18: TAAUXAREA | X18: Feb 18 2025 9:10AM | Y18: frmCON6093 | Z18: TA-ANA-CONT | AA18: TAMBIENTAL | AB18: Feb 18 2025 9:10AM
A19: 138020001 | B19: REINTEGRO DE INCAPACIDADES | C19: 45688 | D19: 21 | E19: NOMINA NOVASOFT | G19: 000000043 | H19: GASTOS REEMBOLSABLES | I19: 142350 | J19: 0 | K19: 1 | L19: 73211365 | M19: SIERRA PAYARES RAFAEL | N19: 10030400 | O19: OPERADORES | R19: 0 | S19: CONTABLE | T19: N | U19: 000000043 | V19: 0 | W19: TAAUXAREA | X19: Feb 18 2025 9:10AM | Y19: frmCON6093 | Z19: TA-ANA-CONT | AA19: TAMBIENTAL | AB19: Feb 18 2025 9:10AM
A20: 138020001 | B20: REINTEGRO DE INCAPACIDADES | C20: 45688 | D20: 21 | E20: NOMINA NOVASOFT | G20: 000000043 | H20: GASTOS REEMBOLSABLES | I20: 47450 | J20: 0 | K20: 1 | L20: 9103870 | M20: SALAS LLERENA OSVALDO | N20: 10030400 | O20: OPERADORES | R20: 0 | S20: CONTABLE | T20: N | U20: 000000043 | V20: 0 | W20: TAAUXAREA | X20: Feb 18 2025 9:10AM | Y20: frmCON6093 | Z20: TA-ANA-CONT | AA20: TAMBIENTAL | AB20: Feb 18 2025 9:10AM
A21: 138020001 | B21: REINTEGRO DE INCAPACIDADES | C21: 45688 | D21: 21 | E21: NOMINA NOVASOFT | G21: 000000043 | H21: GASTOS REEMBOLSABLES | I21: 379600 | J21: 0 | K21: 1 | L21: 1047463607 | M21: DUBAN JOSE RODRIGUEZ DIAZ | N21: 10030400 | O21: OPERADORES | R21: 0 | S21: CONTABLE | T21: N | U21: 000000043 | V21: 0 | W21: TAAUXAREA | X21: Feb 18 2025 9:10AM | Y21: frmCON6093 | Z21: TA-ANA-CONT | AA21: TAMBIENTAL | AB21: Feb 18 2025 9:10AM
A22: 138020001 | B22: REINTEGRO DE INCAPACIDADES | C22: 45688 | D22: 21 | E22: NOMINA NOVASOFT | G22: 000000043 | H22: GASTOS REEMBOLSABLES | I22: 94900 | J22: 0 | K22: 1 | L22: 94379411 | M22: RINCON SANCHEZ ANDERSON | N22: 10030400 | O22: OPERADORES | R22: 0 | S22: CONTABLE | T22: N | U22: 000000043 | V22: 0 | W22: TAAUXAREA | X22: Feb 18 2025 9:10AM | Y22: frmCON6093 | Z22: TA-ANA-CONT | AA22: TAMBIENTAL | AB22: Feb 18 2025 9:10AM
A23: 138020001 | B23: REINTEGRO DE INCAPACIDADES | C23: 45688 | D23: 21 | E23: NOMINA NOVASOFT | G23: 000000043 | H23: GASTOS REEMBOLSABLES | I23: 47450 | J23: 0 | K23: 1 | L23: 7921809 | M23: NICOLAS REYES CASIANI | N23: 10030400 | O23: OPERADORES | R23: 0 | S23: CONTABLE | T23: N | U23: 000000043 | V23: 0 | W23: TAAUXAREA | X23: Feb 18 2025 9:10AM | Y23: frmCON6093 | Z23: TA-ANA-CONT | AA23: TAMBIENTAL | AB23: Feb 18 2025 9:10AM
A24: 138020001 | B24: REINTEGRO DE INCAPACIDADES | C24: 45688 | D24: 21 | E24: NOMINA NOVASOFT | G24: 000000043 | H24: GASTOS REEMBOLSABLES | I24: 664300 | J24: 0 | K24: 1 | L24: 3883113 | M24: LUIS FERNANDO PIMIENTEL SANTANA | N24: 10030400 | O24: OPERADORES | R24: 0 | S24: CONTABLE | T24: N | U24: 000000043 | V24: 0 | W24: TAAUXAREA | X24: Feb 18 2025 9:10AM | Y24: frmCON6093 | Z24: TA-ANA-CONT | AA24: TAMBIENTAL | AB24: Feb 18 2025 9:10AM
... A77: 138020001 | B77: REINTEGRO DE INCAPACIDADES | C77: 45716 | D77: 21 | E77: NOMINA NOVASOFT | G77: 000000044 | H77: GASTOS REEMBOLSABLES | I77: 142350 | J77: 0 | K77: 1 | L77: 1237441830 | M77: ABRAM GARRIDO BARACALDO | N77: 10030400 | O77: OPERADORES | R77: 0 | S77: CONTABLE | T77: N | U77: 000000044 | V77: 0 | W77: TAAUXAREA | X77: Mar 20 2025 5:19PM | Y77: frmCON6093 | Z77: TA-AUX-CONTA1 | AA77: TAMBIENTAL | AB77: Mar 20 2025 5:19PM
A78: 138020001 | B78: REINTEGRO DE INCAPACIDADES | C78: 45713 | D78: 15 | E78: CONSIGNACIONES BANCO | G78: 000000745 | H78: E.P.S. SANITAS S.A.:REINTEGRO INCAPACIDADES000000745 | I78: 0 | J78: 130000 | K78: 1 | L78: 73211365 | M78: SIERRA PAYARES RAFAEL | R78: 0 | S78: CONTABLE | T78: N | U78: 000000745 | V78: 0 | W78: TACOTESO | X78: Mar 14 2025 5:22PM | Y78: frmBAN607 | Z78: TA-COOR-TESO | AA78: TAMBIENTAL | AB78: Mar 14 2025 5:22PM
A79: 138020001 | B79: REINTEGRO DE INCAPACIDADES | C79: 45713 | D79: 15 | E79: CONSIGNACIONES BANCO | G79: 000000744 | H79: EPS SURA COMPAÑIA SURAMERICANA SERVICIOS DE SALUD:REINTEGRO INCAPACIDADES000000744 | I79: 0 | J79: 596267 | K79: 1 | L79: 3883113 | M79: LUIS FERNANDO PIMIENTEL SANTANA | R79: 0 | S79: CONTABLE | T79: N | U79: 000000744 | V79: 0 | W79: TACOTESO | X79: Mar 14 2025 5:19PM | Y79: frmBAN607 | Z79: TA-COOR-TESO | AA79: TAMBIENTAL | AB79: Mar 14 2025 5:19PM
A80: 138020001 | B80: REINTEGRO DE INCAPACIDADES | C80: 45712 | D80: 15 | E80: CONSIGNACIONES BANCO | G80: 000000743 | H80: E.P.S. SANITAS S.A.:REINTEGRO INCAPACIDAD000000743 | I80: 0 | J80: 91488 | K80: 1 | L80: 1002248481 | M80: SERGIO LUIS HERNANDEZ GONZALEZ | R80: 0 | S80: CONTABLE | T80: N | U80: 000000743 | V80: 0 | W80: TACOTESO | X80: Mar 14 2025 5:17PM | Y80: frmBAN607 | Z80: TA-COOR-TESO | AA80: TAMBIENTAL | AB80: Mar 14 2025 5:17PM
A81: 138020001 | B81: REINTEGRO DE INCAPACIDADES | C81: 45709 | D81: 15 | E81: CONSIGNACIONES BANCO | G81: 000000742 | H81: COOSALUD ENTIDAD PROMOTORA DE SALUD S.A:REINTEGRO INCAPACIDADES000000742 | I81: 0 | J81: 44768 | K81: 1 | L81: 1047430645 | M81: LUIS MODESTO PALACIO URANGO | R81: 0 | S81: CONTABLE | T81: N | U81: 000000742 | V81: 0 | W81: TACOTESO | X81: Mar 14 2025 5:11PM | Y81: frmBAN607 | Z81: TA-COOR-TESO | AA81: TAMBIENTAL | AB81: Mar 14 2025 5:11PM
A82: 138020001 | B82: REINTEGRO DE INCAPACIDADES | C82: 45709 | D82: 15 | E82: CONSIGNACIONES BANCO | G82: 000000741 | H82: COOSALUD ENTIDAD PROMOTORA DE SALUD S.A:REINTEGRO INCAPACIDADES000000741 | I82: 0 | J82: 44768 | K82: 1 | L82: 1047430645 | M82: LUIS MODESTO PALACIO URANGO | R82: 0 | S82: CONTABLE | T82: N | U82: 000000741 | V82: 0 | W82: TACOTESO | X82: Mar 14 2025 5:10PM | Y82: frmBAN607 | Z82: TA-COOR-TESO | AA82: TAMBIENTAL | AB82: Mar 14 2025 5:10PM
A83: 138020001 | B83: REINTEGRO DE INCAPACIDADES | C83: 45709 | D83: 15 | E83: CONSIGNACIONES BANCO | G83: 000000740 | H83: COOSALUD ENTIDAD PROMOTORA DE SALUD S.A:REINTEGRO INCAPACIDADES000000740 | I83: 0 | J83: 47450 | K83: 1 | L83: 73117655 | M83: WILMAN HERRERA ARROYO | R83: 0 | S83: CONTABLE | T83: N | U83: 000000740 | V83: 0 | W83: TACOTESO | X83: Mar 14 2025 5:08PM | Y83: frmBAN607 | Z83: TA-COOR-TESO | AA83: TAMBIENTAL | AB83: Mar 14 2025 5:08PM
A84: 138020001 | B84: REINTEGRO DE INCAPACIDADES | C84: 45709 | D84: 15 | E84: CONSIGNACIONES BANCO | G84: 000000739 | H84: COOSALUD ENTIDAD PROMOTORA DE SALUD S.A:REINTEGRO INCAPACIDADES000000739 | I84: 0 | J84: 47450 | K84: 1 | L84: 73117655 | M84: WILMAN HERRERA ARROYO | R84: 0 | S84: CONTABLE | T84: N | U84: 000000739 | V84: 0 | W84: TACOTESO | X84: Mar 14 2025 5:06PM | Y84: frmBAN607 | Z84: TA-COOR-TESO | AA84: TAMBIENTAL | AB84: Mar 14 2025 5:06PM
A85: 138020001 | B85: REINTEGRO DE INCAPACIDADES | C85: 45709 | D85: 15 | E85: CONSIGNACIONES BANCO | G85: 000000738 | H85: Reintegro incapacidades | I85: 0 | J85: 43431 | K85: 1 | L85: 15031784 | M85: LOKY LUCIANO PEREZ CHICA | R85: 0 | S85: CONTABLE | T85: N | U85: 000000738 | V85: 0 | W85: TACOTESO | X85: Mar 14 2025 4:58PM | Y85: frmBAN607 | Z85: TA-COOR-TESO | AA85: TAMBIENTAL | AB85: Mar 14 2025 4:58PM
A86: 138020001 | B86: REINTEGRO DE INCAPACIDADES | C86: 45709 | D86: 15 | E86: CONSIGNACIONES BANCO | G86: 000000738 | H86: Reintegro incapacidades | I86: 0 | J86: 86667 | K86: 1 | L86: 1002059942 | M86: WILSON RAFAEL SIMANCAS MARTINEZ | R86: 0 | S86: CONTABLE | T86: N | U86: 000000738 | V86: 0 | W86: TACOTESO | X86: Mar 14 2025 4:58PM | Y86: frmBAN607 | Z86: TA-COOR-TESO | AA86: TAMBIENTAL | AB86: Mar 14 2025 4:58PM
A87: 138020001 | B87: REINTEGRO DE INCAPACIDADES | C87: 45709 | D87: 15 | E87: CONSIGNACIONES BANCO | G87: 000000738 | H87: Reintegro incapacidades | I87: 0 | J87: 1213333 | K87: 1 | L87: 12595533 | M87: LUIS ALFONSO MEDINA OCHOA | R87: 0 | S87: CONTABLE | T87: N | U87: 000000738 | V87: 0 | W87: TACOTESO | X87: Mar 14 2025 4:58PM | Y87: frmBAN607 | Z87: TA-COOR-TESO | AA87: TAMBIENTAL | AB87: Mar 14 2025 4:58PM
A88: 138020001 | B88: REINTEGRO DE INCAPACIDADES | C88: 45709 | D88: 15 | E88: CONSIGNACIONES BANCO | G88: 000000738 | H88: NUEVA EMPRESA PROMOTORA DE SALUD:Reintegro incapacidades000000738 | I88: 0 | J88: 1993333 | K88: 1 | L88: 73159298 | M88: MARQUEZ MERCADO ALEXANDER RAFAEL | R88: 0 | S88: CONTABLE | T88: N | U88: 000000738 | V88: 0 | W88: TACOTESO | X88: Mar 14 2025 4:58PM | Y88: frmBAN607 | Z88: TA-COOR-TESO | AA88: TAMBIENTAL | AB88: Mar 14 2025 4:58PM
A89: 138020001 | B89: REINTEGRO DE INCAPACIDADES | C89: 45706 | D89: 15 | E89: CONSIGNACIONES BANCO | G89: 000000737 | H89: E.P.S. SANITAS S.A.:REINTEGRO INCAPACIDAD000000737 | I89: 0 | J89: 50862 | K89: 1 | L89: 1002248481 | M89: SERGIO LUIS HERNANDEZ GONZALEZ | R89: 0 | S89: CONTABLE | T89: N | U89: 000000737 | V89: 0 | W89: TACOTESO | X89: Mar 14 2025 3:20PM | Y89: frmBAN607 | Z89: TA-COOR-TESO | AA89: TAMBIENTAL | AB89: Mar 14 2025 3:20PM
... A94: 138020001 | B94: REINTEGRO DE INCAPACIDADES | C94: 45720 | D94: 15 | E94: CONSIGNACIONES BANCO | G94: 000000764 | H94: ASOCIACION MUTUAL SER EMPRESA SOLIDARIA:REINTEGRO INCAPACIDAD000000764 | I94: 0 | J94: 133690 | K94: 1 | L94: 806008394 | M94: ASOCIACION MUTUAL SER EMPRESA SOLIDARIA | R94: 0 | S94: CONTABLE | T94: N | U94: 000000764 | V94: 0 | W94: TACOTESO | X94: Abr 8 2025 5:08PM | Y94: frmBAN607 | Z94: TA-COOR-TESO | AA94: TAMBIENTAL | AB94: Abr 8 2025 5:08PM
A95: 138020001 | B95: REINTEGRO DE INCAPACIDADES | C95: 45747 | D95: 21 | E95: NOMINA NOVASOFT | G95: 000000045 | H95: GASTOS REEMBOLSABLES | I95: 521950 | J95: 0 | K95: 1 | L95: 73159298 | M95: MARQUEZ MERCADO ALEXANDER RAFAEL | N95: 10030400 | O95: OPERADORES | R95: 0 | S95: CONTABLE | T95: N | U95: 000000045 | V95: 0 | W95: TAAUXAREA | X95: Abr 22 2025 12:04PM | Y95: frmCON6093 | Z95: TA-ANA-CONTB | AA95: TAMBIENTAL | AB95: Abr 22 2025 12:04PM
A96: 138020001 | B96: REINTEGRO DE INCAPACIDADES | C96: 45747 | D96: 21 | E96: NOMINA NOVASOFT | G96: 000000045 | H96: GASTOS REEMBOLSABLES | I96: 94900 | J96: 0 | K96: 1 | L96: 30873721 | M96: ROSANA JIMENEZ LLANOS | N96: 10030400 | O96: OPERADORES | R96: 0 | S96: CONTABLE | T96: N | U96: 000000045 | V96: 0 | W96: TAAUXAREA | X96: Abr 22 2025 12:04PM | Y96: frmCON6093 | Z96: TA-ANA-CONTB | AA96: TAMBIENTAL | AB96: Abr 22 2025 12:04PM
A97: 138020001 | B97: REINTEGRO DE INCAPACIDADES | C97: 45747 | D97: 21 | E97: NOMINA NOVASOFT | G97: 000000045 | H97: GASTOS REEMBOLSABLES | I97: 759200 | J97: 0 | K97: 1 | L97: 73109356 | M97: WILLIAN ANTONIO MARTINEZ OLAVE | N97: 10030400 | O97: OPERADORES | R97: 0 | S97: CONTABLE | T97: N | U97: 000000045 | V97: 0 | W97: TAAUXAREA | X97: Abr 22 2025 12:04PM | Y97: frmCON6093 | Z97: TA-ANA-CONTB | AA97: TAMBIENTAL | AB97: Abr 22 2025 12:04PM
A98: 138020001 | B98: REINTEGRO DE INCAPACIDADES | C98: 45747 | D98: 21 | E98: NOMINA NOVASOFT | G98: 000000045 | H98: GASTOS REEMBOLSABLES | I98: 47450 | J98: 0 | K98: 1 | L98: 73154547 | M98: JORGE ELIECER JIMENEZ PEREZ | N98: 10030400 | O98: OPERADORES | R98: 0 | S98: CONTABLE | T98: N | U98: 000000045 | V98: 0 | W98: TAAUXAREA | X98: Abr 22 2025 12:04PM | Y98: frmCON6093 | Z98: TA-ANA-CONTB | AA98: TAMBIENTAL | AB98: Abr 22 2025 12:04PM
A99: 138020001 | B99: REINTEGRO DE INCAPACIDADES | C99: 45747 | D99: 21 | E99: NOMINA NOVASOFT | G99: 000000045 | H99: GASTOS REEMBOLSABLES | I99: 47450 | J99: 0 | K99: 1 | L99: 9146382 | M99: LUIS MIGUEL PADILLA HERNANDEZ | N99: 10030400 | O99: OPERADORES | R99: 0 | S99: CONTABLE | T99: N | U99: 000000045 | V99: 0 | W99: TAAUXAREA | X99: Abr 22 2025 12:04PM | Y99: frmCON6093 | Z99: TA-ANA-CONTB | AA99: TAMBIENTAL | AB99: Abr 22 2025 12:04PM
A100: 138020001 | B100: REINTEGRO DE INCAPACIDADES | C100: 45747 | D100: 21 | E100: NOMINA NOVASOFT | G100: 000000045 | H100: GASTOS REEMBOLSABLES | I100: 47450 | J100: 0 | K100: 1 | L100: 1047440584 | M100: ALVAREZ PIMIENTA WILL ALFONSO | N100: 10030400 | O100: OPERADORES | R100: 0 | S100: CONTABLE | T100: N | U100: 000000045 | V100: 0 | W100: TAAUXAREA | X100: Abr 22 2025 12:04PM | Y100: frmCON6093 | Z100: TA-ANA-CONTB | AA100: TAMBIENTAL | AB100: Abr 22 2025 12:04PM
A101: 138020001 | B101: REINTEGRO DE INCAPACIDADES | C101: 45747 | D101: 21 | E101: NOMINA NOVASOFT | G101: 000000045 | H101: GASTOS REEMBOLSABLES | I101: 142350 | J101: 0 | K101: 1 | L101: 1065650246 | M101: ACOSTA MUÑOZ RAFAEL ENRIQUE | N101: 10030400 | O101: OPERADORES | R101: 0 | S101: CONTABLE | T101: N | U101: 000000045 | V101: 0 | W101: TAAUXAREA | X101: Abr 22 2025 12:04PM | Y101: frmCON6093 | Z101: TA-ANA-CONTB | AA101: TAMBIENTAL | AB101: Abr 22 2025 12:04PM
A102: 138020001 | B102: REINTEGRO DE INCAPACIDADES | C102: 45747 | D102: 21 | E102: NOMINA NOVASOFT | G102: 000000045 | H102: GASTOS REEMBOLSABLES | I102: 47450 | J102: 0 | K102: 1 | L102: 1006877412 | M102: CARVAJAL RAMOS DANIEL ANDRES | N102: 10030400 | O102: OPERADORES | R102: 0 | S102: CONTABLE | T102: N | U102: 000000045 | V102: 0 | W102: TAAUXAREA | X102: Abr 22 2025 12:04PM | Y102: frmCON6093 | Z102: TA-ANA-CONTB | AA102: TAMBIENTAL | AB102: Abr 22 2025 12:04PM
A103: 138020001 | B103: REINTEGRO DE INCAPACIDADES | C103: 45747 | D103: 21 | E103: NOMINA NOVASOFT | G103: 000000045 | H103: GASTOS REEMBOLSABLES | I103: 53738 | J103: 0 | K103: 1 | L103: 1002248080 | M103: JOSE FILOT PEREZ | N103: 10030400 | O103: OPERADORES | R103: 0 | S103: CONTABLE | T103: N | U103: 000000045 | V103: 0 | W103: TAAUXAREA | X103: Abr 22 2025 12:04PM | Y103: frmCON6093 | Z103: TA-ANA-CONTB | AA103: TAMBIENTAL | AB103: Abr 22 2025 12:04PM
A104: 138020001 | B104: REINTEGRO DE INCAPACIDADES | C104: 45747 | D104: 21 | E104: NOMINA NOVASOFT | G104: 000000045 | H104: GASTOS REEMBOLSABLES | I104: 142350 | J104: 0 | K104: 1 | L104: 73195999 | M104: HENRY GUERRERO LOPEZ | N104: 10030400 | O104: OPERADORES | R104: 0 | S104: CONTABLE | T104: N | U104: 000000045 | V104: 0 | W104: TAAUXAREA | X104: Abr 22 2025 12:04PM | Y104: frmCON6093 | Z104: TA-ANA-CONTB | AA104: TAMBIENTAL | AB104: Abr 22 2025 12:04PM
A105: 138020001 | B105: REINTEGRO DE INCAPACIDADES | C105: 45747 | D105: 21 | E105: NOMINA NOVASOFT | G105: 000000045 | H105: GASTOS REEMBOLSABLES | I105: 142350 | J105: 0 | K105: 1 | L105: 12595533 | M105: LUIS ALFONSO MEDINA OCHOA | N105: 10030400 | O105: OPERADORES | R105: 0 | S105: CONTABLE | T105: N | U105: 000000045 | V105: 0 | W105: TAAUXAREA | X105: Abr 22 2025 12:04PM | Y105: frmCON6093 | Z105: TA-ANA-CONTB | AA105: TAMBIENTAL | AB105: Abr 22 2025 12:04PM
A106: 138020001 | B106: REINTEGRO DE INCAPACIDADES | C106: 45747 | D106: 21 | E106: NOMINA NOVASOFT | G106: 000000045 | H106: GASTOS REEMBOLSABLES | I106: 54913 | J106: 0 | K106: 1 | L106: 9147614 | M106: PEDRO PABLO MARTINEZ RODRIGUEZ | N106: 10030400 | O106: OPERADORES | R106: 0 | S106: CONTABLE | T106: N | U106: 000000045 | V106: 0 | W106: TAAUXAREA | X106: Abr 22 2025 12:04PM | Y106: frmCON6093 | Z106: TA-ANA-CONTB | AA106: TAMBIENTAL | AB106: Abr 22 2025 12:04PM
... A121: 138020001 | B121: REINTEGRO DE INCAPACIDADES | C121: 45747 | D121: 21 | E121: NOMINA NOVASOFT | G121: 000000045 | H121: GASTOS REEMBOLSABLES | I121: 379600 | J121: 0 | K121: 1 | L121: 3883113 | M121: LUIS FERNANDO PIMIENTEL SANTANA | N121: 10030400 | O121: OPERADORES | R121: 0 | S121: CONTABLE | T121: N | U121: 000000045 | V121: 0 | W121: TAAUXAREA | X121: Abr 22 2025 12:04PM | Y121: frmCON6093 | Z121: TA-ANA-CONTB | AA121: TAMBIENTAL | AB121: Abr 22 2025 12:04PM
A122: 138020001 | B122: REINTEGRO DE INCAPACIDADES | C122: 45728 | D122: 24 | E122: ASIENTOS DE CONTABILIDAD | G122: 000001667 | H122: RECLASIFICACION DE INCAPACIDADES | I122: 0 | J122: 2165553 | K122: 1 | L122: 92545434 | M122: ACOSTA BALDOVINO LUIS CARLOS | R122: 0 | S122: CONTABLE | T122: N | U122: 000001667 | V122: 0 | W122: TAAUXAREA | X122: Mar 12 2025 4:12PM | Y122: frmCON607 | Z122: TA-ANA-CONT | AA122: TAMBIENTAL | AB122: Mar 12 2025 4:12PM
A123: 138020001 | B123: REINTEGRO DE INCAPACIDADES | C123: 45728 | D123: 24 | E123: ASIENTOS DE CONTABILIDAD | G123: 000001667 | H123: RECLASIFICACION DE INCAPACIDADES | I123: 2165553 | J123: 0 | K123: 1 | L123: 800088702 | M123: EPS SURA COMPAÑIA SURAMERICANA SERVICIOS DE SALUD | R123: 0 | S123: CONTABLE | T123: N | U123: 000001667 | V123: 0 | W123: TAAUXAREA | X123: Mar 12 2025 4:12PM | Y123: frmCON607 | Z123: TA-ANA-CONT | AA123: TAMBIENTAL | AB123: Mar 12 2025 4:12PM
A124: 138020001 | B124: REINTEGRO DE INCAPACIDADES | C124: 45728 | D124: 24 | E124: ASIENTOS DE CONTABILIDAD | G124: 000001667 | H124: RECLASIFICACION DE INCAPACIDADES | I124: 0 | J124: 43333 | K124: 1 | L124: 9236697 | M124: OSMAR ALBERTO POVEDA GIL | R124: 0 | S124: CONTABLE | T124: N | U124: 000001667 | V124: 0 | W124: TAAUXAREA | X124: Mar 12 2025 4:12PM | Y124: frmCON607 | Z124: TA-ANA-CONT | AA124: TAMBIENTAL | AB124: Mar 12 2025 4:12PM
A125: 138020001 | B125: REINTEGRO DE INCAPACIDADES | C125: 45728 | D125: 24 | E125: ASIENTOS DE CONTABILIDAD | G125: 000001667 | H125: RECLASIFICACION DE INCAPACIDADES | I125: 43333 | J125: 0 | K125: 1 | L125: 800088702 | M125: EPS SURA COMPAÑIA SURAMERICANA SERVICIOS DE SALUD | R125: 0 | S125: CONTABLE | T125: N | U125: 000001667 | V125: 0 | W125: TAAUXAREA | X125: Mar 12 2025 4:12PM | Y125: frmCON607 | Z125: TA-ANA-CONT | AA125: TAMBIENTAL | AB125: Mar 12 2025 4:12PM
A126: 138020001 | B126: REINTEGRO DE INCAPACIDADES | C126: 45728 | D126: 24 | E126: ASIENTOS DE CONTABILIDAD | G126: 000001667 | H126: RECLASIFICACION DE INCAPACIDADES | I126: 0 | J126: 45076 | K126: 1 | L126: 3883113 | M126: LUIS FERNANDO PIMIENTEL SANTANA | R126: 0 | S126: CONTABLE | T126: N | U126: 000001667 | V126: 0 | W126: TAAUXAREA | X126: Mar 12 2025 4:12PM | Y126: frmCON607 | Z126: TA-ANA-CONT | AA126: TAMBIENTAL | AB126: Mar 12 2025 4:12PM
A127: 138020001 | B127: REINTEGRO DE INCAPACIDADES | C127: 45728 | D127: 24 | E127: ASIENTOS DE CONTABILIDAD | G127: 000001667 | H127: RECLASIFICACION DE INCAPACIDADES | I127: 45076 | J127: 0 | K127: 1 | L127: 800088702 | M127: EPS SURA COMPAÑIA SURAMERICANA SERVICIOS DE SALUD | R127: 0 | S127: CONTABLE | T127: N | U127: 000001667 | V127: 0 | W127: TAAUXAREA | X127: Mar 12 2025 4:12PM | Y127: frmCON607 | Z127: TA-ANA-CONT | AA127: TAMBIENTAL | AB127: Mar 12 2025 4:12PM
A128: 138020001 | B128: REINTEGRO DE INCAPACIDADES | C128: 45728 | D128: 24 | E128: ASIENTOS DE CONTABILIDAD | G128: 000001667 | H128: RECLASIFICACION DE INCAPACIDADES | I128: 0 | J128: 139300 | K128: 1 | L128: 73209469 | M128: RAMIREZ BRAVO RUBEN | R128: 0 | S128: CONTABLE | T128: N | U128: 000001667 | V128: 0 | W128: TAAUXAREA | X128: Mar 12 2025 4:12PM | Y128: frmCON607 | Z128: TA-ANA-CONT | AA128: TAMBIENTAL | AB128: Mar 12 2025 4:12PM
A129: 138020001 | B129: REINTEGRO DE INCAPACIDADES | C129: 45728 | D129: 24 | E129: ASIENTOS DE CONTABILIDAD | G129: 000001667 | H129: RECLASIFICACION DE INCAPACIDADES | I129: 0 | J129: 1213333 | K129: 1 | L129: 1128046710 | M129: IMANOL ENRIQUE CERDA SARA | R129: 0 | S129: CONTABLE | T129: N | U129: 000001667 | V129: 0 | W129: TAAUXAREA | X129: Mar 12 2025 4:12PM | Y129: frmCON607 | Z129: TA-ANA-CONT | AA129: TAMBIENTAL | AB129: Mar 12 2025 4:12PM
A130: 138020001 | B130: REINTEGRO DE INCAPACIDADES | C130: 45728 | D130: 24 | E130: ASIENTOS DE CONTABILIDAD | G130: 000001667 | H130: RECLASIFICACION DE INCAPACIDADES | I130: 1352633 | J130: 0 | K130: 1 | L130: 800088702 | M130: EPS SURA COMPAÑIA SURAMERICANA SERVICIOS DE SALUD | R130: 0 | S130: CONTABLE | T130: N | U130: 000001667 | V130: 0 | W130: TAAUXAREA | X130: Mar 12 2025 4:12PM | Y130: frmCON607 | Z130: TA-ANA-CONT | AA130: TAMBIENTAL | AB130: Mar 12 2025 4:12PM
A131: 138020001 | B131: REINTEGRO DE INCAPACIDADES | C131: 45728 | D131: 24 | E131: ASIENTOS DE CONTABILIDAD | G131: 000001667 | H131: RECLASIFICACION DE INCAPACIDADES | I131: 0 | J131: 216667 | K131: 1 | L131: 3883113 | M131: LUIS FERNANDO PIMIENTEL SANTANA | R131: 0 | S131: CONTABLE | T131: N | U131: 000001667 | V131: 0 | W131: TAAUXAREA | X131: Mar 12 2025 4:12PM | Y131: frmCON607 | Z131: TA-ANA-CONT | AA131: TAMBIENTAL | AB131: Mar 12 2025 4:12PM
A132: 138020001 | B132: REINTEGRO DE INCAPACIDADES | C132: 45728 | D132: 24 | E132: ASIENTOS DE CONTABILIDAD | G132: 000001667 | H132: RECLASIFICACION DE INCAPACIDADES | I132: 216667 | J132: 0 | K132: 1 | L132: 800088702 | M132: EPS SURA COMPAÑIA SURAMERICANA SERVICIOS DE SALUD | R132: 0 | S132: CONTABLE | T132: N | U132: 000001667 | V132: 0 | W132: TAAUXAREA | X132: Mar 12 2025 4:12PM | Y132: frmCON607 | Z132: TA-ANA-CONT | AA132: TAMBIENTAL | AB132: Mar 12 2025 4:12PM
A133: 138020001 | B133: REINTEGRO DE INCAPACIDADES | C133: 45728 | D133: 24 | E133: ASIENTOS DE CONTABILIDAD | G133: 000001667 | H133: RECLASIFICACION DE INCAPACIDADES | I133: 0 | J133: 130000 | K133: 1 | L133: 3883113 | M133: LUIS FERNANDO PIMIENTEL SANTANA | R133: 0 | S133: CONTABLE | T133: N | U133: 000001667 | V133: 0 | W133: TAAUXAREA | X133: Mar 12 2025 4:12PM | Y133: frmCON607 | Z133: TA-ANA-CONT | AA133: TAMBIENTAL | AB133: Mar 12 2025 4:12PM
... A148: 138020001 | B148: REINTEGRO DE INCAPACIDADES | C148: 45728 | D148: 24 | E148: ASIENTOS DE CONTABILIDAD | G148: 000001667 | H148: RECLASIFICACION DE INCAPACIDADES | I148: 2463259 | J148: 0 | K148: 1 | L148: 800088702 | M148: EPS SURA COMPAÑIA SURAMERICANA SERVICIOS DE SALUD | R148: 0 | S148: CONTABLE | T148: N | U148: 000001667 | V148: 0 | W148: TAAUXAREA | X148: Mar 12 2025 4:12PM | Y148: frmCON607 | Z148: TA-ANA-CONT | AA148: TAMBIENTAL | AB148: Mar 12 2025 4:12PM
A149: 138020001 | B149: REINTEGRO DE INCAPACIDADES | C149: 45747 | D149: 21 | E149: NOMINA NOVASOFT | G149: 000000045 | H149: GASTOS REEMBOLSABLES | I149: 95962 | J149: 0 | K149: 1 | L149: 1001974217 | M149: MORENO VICTOR MANUEL | N149: 10020200 | O149: EJECUCIÓN | R149: 0 | S149: CONTABLE | T149: N | U149: 000000045 | V149: 0 | W149: TAAUXAREA | X149: Abr 22 2025 12:04PM | Y149: frmCON6093 | Z149: TA-ANA-CONTB | AA149: TAMBIENTAL | AB149: Abr 22 2025 12:04PM
A150: 138020001 | B150: REINTEGRO DE INCAPACIDADES | C150: 45777 | D150: 21 | E150: NOMINA NOVASOFT | G150: 000000047 | H150: GASTOS REEMBOLSABLES | I150: 94900 | J150: 0 | K150: 1 | L150: 9148287 | M150: RAMOS GARCIA YEAM CARLOS | N150: 10030400 | O150: OPERADORES | R150: 0 | S150: CONTABLE | T150: N | U150: 000000047 | V150: 0 | W150: TAAUXAREA | X150: May 15 2025 5:35PM | Y150: frmCON6093 | Z150: TA-ANA-CONTB | AA150: TAMBIENTAL | AB150: May 15 2025 5:35PM
A151: 138020001 | B151: REINTEGRO DE INCAPACIDADES | C151: 45777 | D151: 21 | E151: NOMINA NOVASOFT | G151: 000000047 | H151: GASTOS REEMBOLSABLES | I151: 711750 | J151: 0 | K151: 1 | L151: 30873721 | M151: ROSANA JIMENEZ LLANOS | N151: 10030400 | O151: OPERADORES | R151: 0 | S151: CONTABLE | T151: N | U151: 000000047 | V151: 0 | W151: TAAUXAREA | X151: May 15 2025 5:35PM | Y151: frmCON6093 | Z151: TA-ANA-CONTB | AA151: TAMBIENTAL | AB151: May 15 2025 5:35PM
A152: 138020001 | B152: REINTEGRO DE INCAPACIDADES | C152: 45777 | D152: 21 | E152: NOMINA NOVASOFT | G152: 000000047 | H152: GASTOS REEMBOLSABLES | I152: 142350 | J152: 0 | K152: 1 | L152: 1007739448 | M152: LUIS SARMIENTO DE ARCO | N152: 10030400 | O152: OPERADORES | R152: 0 | S152: CONTABLE | T152: N | U152: 000000047 | V152: 0 | W152: TAAUXAREA | X152: May 15 2025 5:35PM | Y152: frmCON6093 | Z152: TA-ANA-CONTB | AA152: TAMBIENTAL | AB152: May 15 2025 5:35PM
A153: 138020001 | B153: REINTEGRO DE INCAPACIDADES | C153: 45777 | D153: 21 | E153: NOMINA NOVASOFT | G153: 000000047 | H153: GASTOS REEMBOLSABLES | I153: 711750 | J153: 0 | K153: 1 | L153: 73159298 | M153: MARQUEZ MERCADO ALEXANDER RAFAEL | N153: 10030400 | O153: OPERADORES | R153: 0 | S153: CONTABLE | T153: N | U153: 000000047 | V153: 0 | W153: TAAUXAREA | X153: May 15 2025 5:35PM | Y153: frmCON6093 | Z153: TA-ANA-CONTB | AA153: TAMBIENTAL | AB153: May 15 2025 5:35PM
A154: 138020001 | B154: REINTEGRO DE INCAPACIDADES | C154: 45777 | D154: 21 | E154: NOMINA NOVASOFT | G154: 000000047 | H154: GASTOS REEMBOLSABLES | I154: 94900 | J154: 0 | K154: 1 | L154: 12595533 | M154: LUIS ALFONSO MEDINA OCHOA | N154: 10030400 | O154: OPERADORES | R154: 0 | S154: CONTABLE | T154: N | U154: 000000047 | V154: 0 | W154: TAAUXAREA | X154: May 15 2025 5:35PM | Y154: frmCON6093 | Z154: TA-ANA-CONTB | AA154: TAMBIENTAL | AB154: May 15 2025 5:35PM
A155: 138020001 | B155: REINTEGRO DE INCAPACIDADES | C155: 45777 | D155: 21 | E155: NOMINA NOVASOFT | G155: 000000047 | H155: GASTOS REEMBOLSABLES | I155: 616850 | J155: 0 | K155: 1 | L155: 73109356 | M155: WILLIAN ANTONIO MARTINEZ OLAVE | N155: 10030400 | O155: OPERADORES | R155: 0 | S155: CONTABLE | T155: N | U155: 000000047 | V155: 0 | W155: TAAUXAREA | X155: May 15 2025 5:35PM | Y155: frmCON6093 | Z155: TA-ANA-CONTB | AA155: TAMBIENTAL | AB155: May 15 2025 5:35PM
A156: 138020001 | B156: REINTEGRO DE INCAPACIDADES | C156: 45777 | D156: 21 | E156: NOMINA NOVASOFT | G156: 000000047 | H156: GASTOS REEMBOLSABLES | I156: 47450 | J156: 0 | K156: 1 | L156: 1002059942 | M156: WILSON RAFAEL SIMANCAS MARTINEZ | N156: 10030400 | O156: OPERADORES | R156: 0 | S156: CONTABLE | T156: N | U156: 000000047 | V156: 0 | W156: TAAUXAREA | X156: May 15 2025 5:35PM | Y156: frmCON6093 | Z156: TA-ANA-CONTB | AA156: TAMBIENTAL | AB156: May 15 2025 5:35PM
A157: 138020001 | B157: REINTEGRO DE INCAPACIDADES | C157: 45776 | D157: 15 | E157: CONSIGNACIONES BANCO | G157: 000000772 | H157: COLMENA SEGUROS RIESGOS LABORALES S.A., RIESGOS LABORALES COLMENA S.A. COMPAÑIA DE SEGUROS DE VIDA:Reintegro Incapacidades000000772 | I157: 0 | J157: 3090938 | K157: 1 | L157: 800226175 | M157: COLMENA SEGUROS RIESGOS LABORALES S.A., RIESGOS LABORALES COLMENA S.A. COMPAÑIA DE SEGUROS DE VIDA | R157: 0 | S157: CONTABLE | T157: N | U157: 000000772 | V157: 0 | W157: TACOTESO | X157: May 8 2025 5:17PM | Y157: frmBAN607 | Z157: TA-COOR-TESO | AA157: TAMBIENTAL | AB157: May 8 2025 5:17PM
A158: 138020001 | B158: REINTEGRO DE INCAPACIDADES | C158: 45769 | D158: 15 | E158: CONSIGNACIONES BANCO | G158: 000000773 | H158: E.P.S. SANITAS S.A.:Reintegro incapacidades000000773 | I158: 0 | J158: 47450 | K158: 1 | L158: 800251440 | M158: E.P.S. SANITAS S.A. | R158: 0 | S158: CONTABLE | T158: N | U158: 000000773 | V158: 0 | W158: TACOTESO | X158: May 8 2025 5:19PM | Y158: frmBAN607 | Z158: TA-COOR-TESO | AA158: TAMBIENTAL | AB158: May 8 2025 5:19PM
A159: 138020001 | B159: REINTEGRO DE INCAPACIDADES | C159: 45768 | D159: 15 | E159: CONSIGNACIONES BANCO | G159: 000000774 | H159: E.P.S. SANITAS S.A.:Reintegro incapacidades000000774 | I159: 0 | J159: 255603 | K159: 1 | L159: 800251440 | M159: E.P.S. SANITAS S.A. | R159: 0 | S159: CONTABLE | T159: N | U159: 000000774 | V159: 0 | W159: TACOTESO | X159: May 8 2025 5:20PM | Y159: frmBAN607 | Z159: TA-COOR-TESO | AA159: TAMBIENTAL | AB159: May 8 2025 5:20PM
A160: 138020001 | B160: REINTEGRO DE INCAPACIDADES | C160: 45763 | D160: 15 | E160: CONSIGNACIONES BANCO | G160: 000000776 | H160: EPS SURA COMPAÑIA SURAMERICANA SERVICIOS DE SALUD:Reintegro incapacidad000000776 | I160: 0 | J160: 2562300 | K160: 1 | L160: 800088702 | M160: EPS SURA COMPAÑIA SURAMERICANA SERVICIOS DE SALUD | R160: 0 | S160: CONTABLE | T160: N | U160: 000000776 | V160: 0 | W160: TACOTESO | X160: May 8 2025 5:22PM | Y160: frmBAN607 | Z160: TA-COOR-TESO | AA160: TAMBIENTAL | AB160: May 8 2025 5:22PM
A161: 138020001 | B161: REINTEGRO DE INCAPACIDADES | C161: 45763 | D161: 15 | E161: CONSIGNACIONES BANCO | G161: 000000775 | H161: E.P.S. SANITAS S.A.:Reintegro incapacidades000000775 | I161: 0 | J161: 86667 | K161: 1 | L161: 800251440 | M161: E.P.S. SANITAS S.A. | R161: 0 | S161: CONTABLE | T161: N | U161: 000000775 | V161: 0 | W161: TACOTESO | X161: May 8 2025 5:21PM | Y161: frmBAN607 | Z161: TA-COOR-TESO | AA161: TAMBIENTAL | AB161: May 8 2025 5:21PM
A162: 138020001 | B162: REINTEGRO DE INCAPACIDADES | C162: 45777 | D162: 21 | E162: NOMINA NOVASOFT | G162: 000000047 | H162: GASTOS REEMBOLSABLES | I162: 171590 | J162: 0 | K162: 1 | L162: 73188537 | M162: LAGUNA URUETA ALVARO DE JESUS | N162: 10030400 | O162: OPERADORES | R162: 0 | S162: CONTABLE | T162: N | U162: 000000047 | V162: 0 | W162: TAAUXAREA | X162: May 15 2025 5:35PM | Y162: frmCON6093 | Z162: TA-ANA-CONTB | AA162: TAMBIENTAL | AB162: May 15 2025 5:35PM
A163: 138020001 | B163: REINTEGRO DE INCAPACIDADES | C163: 45777 | D163: 21 | E163: NOMINA NOVASOFT | G163: 000000047 | H163: GASTOS REEMBOLSABLES | I163: 284700 | J163: 0 | K163: 1 | L163: 1237441830 | M163: ABRAM GARRIDO BARACALDO | N163: 10020200 | O163: EJECUCIÓN | R163: 0 | S163: CONTABLE | T163: N | U163: 000000047 | V163: 0 | W163: TAAUXAREA | X163: May 15 2025 5:35PM | Y163: frmCON6093 | Z163: TA-ANA-CONTB | AA163: TAMBIENTAL | AB163: May 15 2025 5:35PM
A164: 138020001 | B164: REINTEGRO DE INCAPACIDADES | C164: 45777 | D164: 21 | E164: NOMINA NOVASOFT | G164: 000000047 | H164: GASTOS REEMBOLSABLES | I164: 523716 | J164: 0 | K164: 1 | L164: 1002057942 | M164: ANDRES SOLANA CASTILLA | N164: 10020200 | O164: EJECUCIÓN | R164: 0 | S164: CONTABLE | T164: N | U164: 000000047 | V164: 0 | W164: TAAUXAREA | X164: May 15 2025 5:35PM | Y164: frmCON6093 | Z164: TA-ANA-CONTB | AA164: TAMBIENTAL | AB164: May 15 2025 5:35PM
A165: 138020001 | B165: REINTEGRO DE INCAPACIDADES | C165: 45777 | D165: 21 | E165: NOMINA NOVASOFT | G165: 000000047 | H165: GASTOS REEMBOLSABLES | I165: 142350 | J165: 0 | K165: 1 | L165: 9236697 | M165: OSMAR ALBERTO POVEDA GIL | N165: 10030400 | O165: OPERADORES | R165: 0 | S165: CONTABLE | T165: N | U165: 000000047 | V165: 0 | W165: TAAUXAREA | X165: May 15 2025 5:35PM | Y165: frmCON6093 | Z165: TA-ANA-CONTB | AA165: TAMBIENTAL | AB165: May 15 2025 5:35PM
A166: 138020001 | B166: REINTEGRO DE INCAPACIDADES | C166: 45777 | D166: 21 | E166: NOMINA NOVASOFT | G166: 000000047 | H166: GASTOS REEMBOLSABLES | I166: 616850 | J166: 0 | K166: 1 | L166: 30873721 | M166: ROSANA JIMENEZ LLANOS | N166: 10030400 | O166: OPERADORES | R166: 0 | S166: CONTABLE | T166: N | U166: 000000047 | V166: 0 | W166: TAAUXAREA | X166: May 15 2025 5:35PM | Y166: frmCON6093 | Z166: TA-ANA-CONTB | AA166: TAMBIENTAL | AB166: May 15 2025 5:35PM
A167: 138020001 | B167: REINTEGRO DE INCAPACIDADES | C167: 45777 | D167: 21 | E167: NOMINA NOVASOFT | G167: 000000047 | H167: GASTOS REEMBOLSABLES | I167: 148176 | J167: 0 | K167: 1 | L167: 9147614 | M167: PEDRO PABLO MARTINEZ RODRIGUEZ | N167: 10030400 | O167: OPERADORES | R167: 0 | S167: CONTABLE | T167: N | U167: 000000047 | V167: 0 | W167: TAAUXAREA | X167: May 15 2025 5:35PM | Y167: frmCON6093 | Z167: TA-ANA-CONTB | AA167: TAMBIENTAL | AB167: May 15 2025 5:35PM
A168: 138020001 | B168: REINTEGRO DE INCAPACIDADES | C168: 45777 | D168: 21 | E168: NOMINA NOVASOFT | G168: 000000047 | H168: GASTOS REEMBOLSABLES | I168: 616850 | J168: 0 | K168: 1 | L168: 1143339994 | M168: JESUS RAFAEL OSORIO CASTILLO | N168: 10030400 | O168: OPERADORES | R168: 0 | S168: CONTABLE | T168: N | U168: 000000047 | V168: 0 | W168: TAAUXAREA | X168: May 15 2025 5:35PM | Y168: frmCON6093 | Z168: TA-ANA-CONTB | AA168: TAMBIENTAL | AB168: May 15 2025 5:35PM
A169: 138020001 | B169: REINTEGRO DE INCAPACIDADES | C169: 45777 | D169: 21 | E169: NOMINA NOVASOFT | G169: 000000047 | H169: GASTOS REEMBOLSABLES | I169: 664300 | J169: 0 | K169: 1 | L169: 3883113 | M169: LUIS FERNANDO PIMIENTEL SANTANA | N169: 10030400 | O169: OPERADORES | R169: 0 | S169: CONTABLE | T169: N | U169: 000000047 | V169: 0 | W169: TAAUXAREA | X169: May 15 2025 5:35PM | Y169: frmCON6093 | Z169: TA-ANA-CONTB | AA169: TAMBIENTAL | AB169: May 15 2025 5:35PM
A170: 138020001 | B170: REINTEGRO DE INCAPACIDADES | C170: 45777 | D170: 21 | E170: NOMINA NOVASOFT | G170: 000000047 | H170: GASTOS REEMBOLSABLES | I170: 711750 | J170: 0 | K170: 1 | L170: 1237441830 | M170: ABRAM GARRIDO BARACALDO | N170: 10020200 | O170: EJECUCIÓN | R170: 0 | S170: CONTABLE | T170: N | U170: 000000047 | V170: 0 | W170: TAAUXAREA | X170: May 15 2025 5:35PM | Y170: frmCON6093 | Z170: TA-ANA-CONTB | AA170: TAMBIENTAL | AB170: May 15 2025 5:35PM
A171: 138020001 | B171: REINTEGRO DE INCAPACIDADES | C171: 45777 | D171: 21 | E171: NOMINA NOVASOFT | G171: 000000047 | H171: GASTOS REEMBOLSABLES | I171: 47450 | J171: 0 | K171: 1 | L171: 73117655 | M171: WILMAN HERRERA ARROYO | N171: 10030400 | O171: OPERADORES | R171: 0 | S171: CONTABLE | T171: N | U171: 000000047 | V171: 0 | W171: TAAUXAREA | X171: May 15 2025 5:35PM | Y171: frmCON6093 | Z171: TA-ANA-CONTB | AA171: TAMBIENTAL | AB171: May 15 2025 5:35PM
A172: 138020001 | B172: REINTEGRO DE INCAPACIDADES | C172: 45777 | D172: 21 | E172: NOMINA NOVASOFT | G172: 000000047 | H172: GASTOS REEMBOLSABLES | I172: 47450 | J172: 0 | K172: 1 | L172: 1143411950 | M172: BANQUEZ SAYAS LACIDES | N172: 10030400 | O172: OPERADORES | R172: 0 | S172: CONTABLE | T172: N | U172: 000000047 | V172: 0 | W172: TAAUXAREA | X172: May 15 2025 5:35PM | Y172: frmCON6093 | Z172: TA-ANA-CONTB | AA172: TAMBIENTAL | AB172: May 15 2025 5:35PM
A173: 138020001 | B173: REINTEGRO DE INCAPACIDADES | C173: 45777 | D173: 21 | E173: NOMINA NOVASOFT | G173: 000000047 | H173: GASTOS REEMBOLSABLES | I173: 94900 | J173: 0 | K173: 1 | L173: 73159298 | M173: MARQUEZ MERCADO ALEXANDER RAFAEL | N173: 10030400 | O173: OPERADORES | R173: 0 | S173: CONTABLE | T173: N | U173: 000000047 | V173: 0 | W173: TAAUXAREA | X173: May 15 2025 5:35PM | Y173: frmCON6093 | Z173: TA-ANA-CONTB | AA173: TAMBIENTAL | AB173: May 15 2025 5:35PM
... A214: 138020001 | B214: REINTEGRO DE INCAPACIDADES | C214: 45808 | D214: 21 | E214: NOMINA NOVASOFT | G214: 000000048 | H214: GASTOS REEMBOLSABLES | I214: 785573 | J214: 0 | K214: 1 | L214: 1002057942 | M214: ANDRES SOLANA CASTILLA | N214: 10020200 | O214: EJECUCIÓN | R214: 0 | S214: CONTABLE | T214: N | U214: 000000048 | V214: 0 | W214: TAAUXAREA | X214: Jun 17 2025 6:37PM | Y214: frmCON6093 | Z214: TA-ANA-CONTB | AA214: TAMBIENTAL | AB214: Jun 17 2025 6:37PM
A215: 138020001 | B215: REINTEGRO DE INCAPACIDADES | C215: 45804 | D215: 15 | E215: CONSIGNACIONES BANCO | G215: 000000817 | H215: EPS SURA COMPAÑIA SURAMERICANA SERVICIOS DE SALUD:REINTEGRO INCAPACIDADES000000817 | I215: 0 | J215: 142350 | K215: 1 | L215: 800088702 | M215: EPS SURA COMPAÑIA SURAMERICANA SERVICIOS DE SALUD | R215: 0 | S215: CONTABLE | T215: N | U215: 000000817 | V215: 0 | W215: TACOTESO | X215: Jun 12 2025 9:02AM | Y215: frmBAN607 | Z215: TA-COOR-TESO | AA215: TAMBIENTAL | AB215: Jun 12 2025 9:02AM
A216: 138020001 | B216: REINTEGRO DE INCAPACIDADES | C216: 45798 | D216: 15 | E216: CONSIGNACIONES BANCO | G216: 000000816 | H216: COLMENA SEGUROS RIESGOS LABORALES S.A., RIESGOS LABORALES COLMENA S.A. COMPAÑIA DE SEGUROS DE VIDA:REINTEGRO INCAPACIDADES000000816 | I216: 0 | J216: 128121 | K216: 1 | L216: 800226175 | M216: COLMENA SEGUROS RIESGOS LABORALES S.A., RIESGOS LABORALES COLMENA S.A. COMPAÑIA DE SEGUROS DE VIDA | R216: 0 | S216: CONTABLE | T216: N | U216: 000000816 | V216: 0 | W216: TACOTESO | X216: Jun 12 2025 9:01AM | Y216: frmBAN607 | Z216: TA-COOR-TESO | AA216: TAMBIENTAL | AB216: Jun 12 2025 9:01AM
A217: 138020001 | B217: REINTEGRO DE INCAPACIDADES | C217: 45798 | D217: 15 | E217: CONSIGNACIONES BANCO | G217: 000000815 | H217: EPS SURA COMPAÑIA SURAMERICANA SERVICIOS DE SALUD:REINTEGRO INCAPACIDADES000000815 | I217: 0 | J217: 1198257 | K217: 1 | L217: 800088702 | M217: EPS SURA COMPAÑIA SURAMERICANA SERVICIOS DE SALUD | R217: 0 | S217: CONTABLE | T217: N | U217: 000000815 | V217: 0 | W217: TACOTESO | X217: Jun 12 2025 9:00AM | Y217: frmBAN607 | Z217: TA-COOR-TESO | AA217: TAMBIENTAL | AB217: Jun 12 2025 9:00AM
A218: 138020001 | B218: REINTEGRO DE INCAPACIDADES | C218: 45786 | D218: 15 | E218: CONSIGNACIONES BANCO | G218: 000000814 | H218: COLMENA SEGUROS RIESGOS LABORALES S.A., RIESGOS LABORALES COLMENA S.A. COMPAÑIA DE SEGUROS DE VIDA:REINTEGRO INCAPACIDADES000000814 | I218: 0 | J218: 919887 | K218: 1 | L218: 800226175 | M218: COLMENA SEGUROS RIESGOS LABORALES S.A., RIESGOS LABORALES COLMENA S.A. COMPAÑIA DE SEGUROS DE VIDA | R218: 0 | S218: CONTABLE | T218: N | U218: 000000814 | V218: 0 | W218: TACOTESO | X218: Jun 12 2025 8:59AM | Y218: frmBAN607 | Z218: TA-COOR-TESO | AA218: TAMBIENTAL | AB218: Jun 12 2025 8:59AM
A219: 138020001 | B219: REINTEGRO DE INCAPACIDADES | C219: 45785 | D219: 15 | E219: CONSIGNACIONES BANCO | G219: 000000813 | H219: ASOCIACION MUTUAL SER EMPRESA SOLIDARIA:REINTEGRO INCAPACIDADES000000813 | I219: 0 | J219: 47450 | K219: 1 | L219: 806008394 | M219: ASOCIACION MUTUAL SER EMPRESA SOLIDARIA | R219: 0 | S219: CONTABLE | T219: N | U219: 000000813 | V219: 0 | W219: TACOTESO | X219: Jun 12 2025 8:58AM | Y219: frmBAN607 | Z219: TA-COOR-TESO | AA219: TAMBIENTAL | AB219: Jun 12 2025 8:58AM
A220: 138020001 | B220: REINTEGRO DE INCAPACIDADES | C220: 45785 | D220: 15 | E220: CONSIGNACIONES BANCO | G220: 000000812 | H220: ASOCIACION MUTUAL SER EMPRESA SOLIDARIA:REINTEGRO INCAPACIDADES000000812 | I220: 0 | J220: 720066 | K220: 1 | L220: 806008394 | M220: ASOCIACION MUTUAL SER EMPRESA SOLIDARIA | R220: 0 | S220: CONTABLE | T220: N | U220: 000000812 | V220: 0 | W220: TACOTESO | X220: Jun 12 2025 8:57AM | Y220: frmBAN607 | Z220: TA-COOR-TESO | AA220: TAMBIENTAL | AB220: Jun 12 2025 8:57AM
A221: 138020001 | B221: REINTEGRO DE INCAPACIDADES | C221: 45784 | D221: 15 | E221: CONSIGNACIONES BANCO | G221: 000000811 | H221: ASOCIACION MUTUAL SER EMPRESA SOLIDARIA:REINTEGRO INCAPACIDADES000000811 | I221: 0 | J221: 380155 | K221: 1 | L221: 806008394 | M221: ASOCIACION MUTUAL SER EMPRESA SOLIDARIA | R221: 0 | S221: CONTABLE | T221: N | U221: 000000811 | V221: 0 | W221: TACOTESO | X221: Jun 12 2025 8:56AM | Y221: frmBAN607 | Z221: TA-COOR-TESO | AA221: TAMBIENTAL | AB221: Jun 12 2025 8:56AM
A222: 138020001 | B222: REINTEGRO DE INCAPACIDADES | C222: 45784 | D222: 15 | E222: CONSIGNACIONES BANCO | G222: 000000810 | H222: EPS SURA COMPAÑIA SURAMERICANA SERVICIOS DE SALUD:REINTEGRO INCAPACIDADES000000810 | I222: 0 | J222: 142350 | K222: 1 | L222: 800088702 | M222: EPS SURA COMPAÑIA SURAMERICANA SERVICIOS DE SALUD | R222: 0 | S222: CONTABLE | T222: N | U222: 000000810 | V222: 0 | W222: TACOTESO | X222: Jun 12 2025 8:55AM | Y222: frmBAN607 | Z222: TA-COOR-TESO | AA222: TAMBIENTAL | AB222: Jun 12 2025 8:55AM
A223: 138020001 | B223: REINTEGRO DE INCAPACIDADES | C223: 45782 | D223: 15 | E223: CONSIGNACIONES BANCO | G223: 000000809 | H223: E.P.S. SANITAS S.A.:REINTEGRO INCAPACIDADES000000809 | I223: 0 | J223: 142350 | K223: 1 | L223: 800251440 | M223: E.P.S. SANITAS S.A. | R223: 0 | S223: CONTABLE | T223: N | U223: 000000809 | V223: 0 | W223: TACOTESO | X223: Jun 12 2025 8:51AM | Y223: frmBAN607 | Z223: TA-COOR-TESO | AA223: TAMBIENTAL | AB223: Jun 12 2025 8:51AM
A224: 138020001 | B224: REINTEGRO DE INCAPACIDADES | C224: 45779 | D224: 15 | E224: CONSIGNACIONES BANCO | G224: 000000808 | H224: COOSALUD ENTIDAD PROMOTORA DE SALUD S.A:REINTEGRO INCAPACIDADES000000808 | I224: 0 | J224: 143578 | K224: 1 | L224: 900226715 | M224: COOSALUD ENTIDAD PROMOTORA DE SALUD S.A | R224: 0 | S224: CONTABLE | T224: N | U224: 000000808 | V224: 0 | W224: TACOTESO | X224: Jun 12 2025 8:42AM | Y224: frmBAN607 | Z224: TA-COOR-TESO | AA224: TAMBIENTAL | AB224: Jun 12 2025 8:42AM
A225: 138020001 | B225: REINTEGRO DE INCAPACIDADES | C225: 45779 | D225: 15 | E225: CONSIGNACIONES BANCO | G225: 000000807 | H225: COOSALUD ENTIDAD PROMOTORA DE SALUD S.A:REINTEGRO INCAPACIDADES000000807 | I225: 0 | J225: 47860 | K225: 1 | L225: 900226715 | M225: COOSALUD ENTIDAD PROMOTORA DE SALUD S.A | R225: 0 | S225: CONTABLE | T225: N | U225: 000000807 | V225: 0 | W225: TACOTESO | X225: Jun 12 2025 8:41AM | Y225: frmBAN607 | Z225: TA-COOR-TESO | AA225: TAMBIENTAL | AB225: Jun 12 2025 8:41AM
...

Sheet Comportamiento
B2: COMPORTAMIENTO DE INCAPACIDADES 2021 - 2026
F4: 2021 | I4: 2022 | L4: 2023 | O4: 2024 | R4: 2025 | U4: 2026
B5: Tem_Cuenta | C5: Tem_Nom Cta | D5: Generado | E5: Recuperado | F5: Sal Act 2021 | G5: Generado | H5: Recuperado | I5: Sal Act 2022 | J5: Generado | K5: Recuperado | L5: Sal Act 2023 | M5: Generado | N5: Recuperado | O5: Sal Act 2024 | P5: Generado | Q5: Recuperado | R5: Sal Act 2025 | S5: Generado | T5: Recuperado | U5: Sal Act 2026
B6: 138020001 | C6: REINTEGRO DE INCAPACIDADES | D6: =SUMIF('BD sin reclasif'!$D$7:$D$10000,Comportamiento!F4,'BD sin reclasif'!$J$7:$J$10000) -> 42950760 | E6: =SUMIF('BD sin reclasif'!$D$7:$D$10000,Comportamiento!F4,'BD sin reclasif'!$K$7:$K$10000) -> 3940992 | F6: =+D6-E6 -> 39009768 | G6: =SUMIF('BD sin reclasif'!$D$7:$D$10000,Comportamiento!I4,'BD sin reclasif'!$J$7:$J$10000) -> 66175156 | H6: =SUMIF('BD sin reclasif'!$D$7:$D$10000,Comportamiento!I4,'BD sin reclasif'!$K$7:$K$10000) -> 44088544 | I6: =+F6+G6-H6 -> 61096380 | J6: =SUMIF('BD sin reclasif'!$D$7:$D$10000,Comportamiento!L4,'BD sin reclasif'!$J$7:$J$10000) -> 129358157 | K6: =SUMIF('BD sin reclasif'!$D$7:$D$10000,Comportamiento!L4,'BD sin reclasif'!$K$7:$K$10000) -> 24346262 | L6: =+I6+J6-K6 -> 1.6610828e+08 | M6: =SUMIF('BD sin reclasif'!$D$7:$D$10000,Comportamiento!O4,'BD sin reclasif'!$J$7:$J$10000) -> 189024323 | N6: =SUMIF('BD sin reclasif'!$D$7:$D$9442,Comportamiento!O4,'BD sin reclasif'!$K$7:$K$9442) -> 178759490 | O6: =+L6+M6-N6 -> 1.7637311e+08 | P6: =SUMIF('BD sin reclasif'!$D$7:$D$10000,Comportamiento!R4,'BD sin reclasif'!$J$7:$J$10000) -> 91449382 | Q6: =SUMIF('BD sin reclasif'!$D$7:$D$9442,Comportamiento!R4,'BD sin reclasif'!$K$7:$K$9442) -> 88178930 | R6: =+O6+P6-Q6 -> 1.7964356e+08 | S6: =SUMIF('BD sin reclasif'!$D$7:$D$10000,Comportamiento!U4,'BD sin reclasif'!$J$7:$J$10000) -> 13425056 | T6: =SUMIF('BD sin reclasif'!$D$7:$D$9442,Comportamiento!U4,'BD sin reclasif'!$K$7:$K$9442) -> 10261364 | U6: =+R6+S6-T6 -> 1.8280725e+08
F8: 2021 | I8: 2022 | L8: 2023 | O8: 2024 | R8: 2025 | U8: 2026 | W8: Comentarios
C9: Saldo Inicial | F9: 0 | I9: =+F13 -> 39009768 | L9: =+I13 -> 61096380 | O9: =+L13 -> 1.6610828e+08 | R9: =+O13 -> 1.7637311e+08 | U9: =+R13 -> 1.7964356e+08
C10: (+) Generado | F10: =+D6 -> 42950760 | I10: =+G6 -> 66175156 | L10: =+J6 -> 129358157 | O10: =+M6 -> 189024323 | R10: =+P6 -> 91449382 | U10: =+S6 -> 13425056
C11: (-) Recuperado | F11: =-E6 -> -3940992 | I11: =-H6 -> -44088544 | L11: =-K6 -> -24346262 | O11: =-N6 -> -178759490 | R11: =-Q6 -> -88178930 | U11: =-T6 -> -10261364
C12: (-) Incobrable | F12: 0 | I12: 0 | L12: 0 | O12: 0 | R12: 0 | U12: 0
C13: Saldo Final | F13: =SUM(F9:F12) -> 39009768 | I13: =SUM(I9:I12) -> 61096380 | L13: =SUM(L9:L12) -> 1.6610828e+08 | O13: =SUM(O9:O12) -> 1.7637311e+08 | R13: =SUM(R9:R12) -> 1.7964356e+08 | U13: =SUM(U9:U12) -> 1.8280725e+08
B28: *Cifras en miles de peso

Sheet Detalle Gerencia
A1: EPS | B1: 2021 | C1: 2022 | D1: 2023 | E1: 2024 | F1: 2025 | G1: 2026 | H1: Total general | I1: %
A2: TRANSAMBIENTAL SAS | B2: 38623261 | G2: =+SUMIFS('BD sin reclasif'!$J:$J,'BD sin reclasif'!$AH:$AH,'Detalle Gerencia'!A2,'BD sin reclasif'!$AF:$AF,'Detalle Gerencia'!$G$1) -> 0 | H2: =SUM(B2:G2) -> 38623261 | I2: =+H2/$H$15 -> 0.19457405
A3: SALUD TOTAL E.P.S. | B3: 0 | C3: 2882465 | D3: =4667958+7496555 -> 12164513 | E3: =12135741-2000000 -> 10135741 | F3: =14144951-2000000 -> 12144951 | G3: =+SUMIFS('BD sin reclasif'!$J:$J,'BD sin reclasif'!$AH:$AH,'Detalle Gerencia'!A3,'BD sin reclasif'!$AF:$AF,'Detalle Gerencia'!$G$1) -> 4902540 | H3: =SUM(B3:G3) -> 42230210 | I3: =+H3/$H$15 -> 0.21274493
A4: SANITAS E.P.S | B4: 0 | C4: 2310456 | D4: =16952990-1000000-480533 -> 15472457 | E4: =6188650-2000000 -> 4188650 | F4: =5165577+5285863 -> 10451440 | G4: =+SUMIFS('BD sin reclasif'!$J:$J,'BD sin reclasif'!$AH:$AH,'Detalle Gerencia'!A4,'BD sin reclasif'!$AF:$AF,'Detalle Gerencia'!$G$1) -> 233455 | H4: =SUM(B4:G4) -> 32656458 | I4: =+H4/$H$15 -> 0.16451483
A5: EPS MUTUAL SER | B5: 0 | C5: 6782337 | D5: 6521414 | E5: 5476679 | F5: =6484188+8000000-1444921 -> 13039267 | G5: =+SUMIFS('BD sin reclasif'!$J:$J,'BD sin reclasif'!$AH:$AH,'Detalle Gerencia'!A5,'BD sin reclasif'!$AF:$AF,'Detalle Gerencia'!$G$1) -> 1623876 | H5: =SUM(B5:G5) -> 33443573 | I5: =+H5/$H$15 -> 0.16848011
A6: FAMISANAR E.P.S | B6: 0 | C6: 1328674 | D6: =7161414-4293000 -> 2868414 | E6: 1280000 | F6: =2485000+2000000 -> 4485000 | G6: =+SUMIFS('BD sin reclasif'!$J:$J,'BD sin reclasif'!$AH:$AH,'Detalle Gerencia'!A6,'BD sin reclasif'!$AF:$AF,'Detalle Gerencia'!$G$1) -> 1925997 | H6: =SUM(B6:G6) -> 11888085 | I6: =+H6/$H$15 -> 0.059889112
A7: SURA E.P.S. | B7: 0 | C7: 1810983 | D7: 3047344 | E7: =2991428+242467 -> 3233895 | F7: =2658540+4000000+1000000 -> 7658540 | G7: =+SUMIFS('BD sin reclasif'!$J:$J,'BD sin reclasif'!$AH:$AH,'Detalle Gerencia'!A7,'BD sin reclasif'!$AF:$AF,'Detalle Gerencia'!$G$1) -> 2626360 | H7: =SUM(B7:G7) -> 18377122 | I7: =+H7/$H$15 -> 0.092579209
A8: COOSALUD ESS EPS -S | B8: 0 | C8: 710325 | D8: 3407896 | E8: 966867 | F8: 3661949 | G8: =+SUMIFS('BD sin reclasif'!$J:$J,'BD sin reclasif'!$AH:$AH,'Detalle Gerencia'!A8,'BD sin reclasif'!$AF:$AF,'Detalle Gerencia'!$G$1) -> 0 | H8: =SUM(B8:G8) -> 8747037 | I8: =+H8/$H$15 -> 0.04406532
A9: NUEVA E.P.S | B9: 0 | C9: 0 | D9: 999324 | E9: 0 | F9: =2416853+1829196 -> 4246049 | G9: =+SUMIFS('BD sin reclasif'!$J:$J,'BD sin reclasif'!$AH:$AH,'Detalle Gerencia'!A9,'BD sin reclasif'!$AF:$AF,'Detalle Gerencia'!$G$1) -> 1176111 | H9: =SUM(B9:G9) -> 6421484 | I9: =+H9/$H$15 -> 0.032349783
A10: EPS-S CAJACOPI | B10: 0 | D10: 270668 | E10: 86667 | F10: 2229713 | G10: =+SUMIFS('BD sin reclasif'!$J:$J,'BD sin reclasif'!$AH:$AH,'Detalle Gerencia'!A10,'BD sin reclasif'!$AF:$AF,'Detalle Gerencia'!$G$1) -> 758728 | H10: =SUM(B10:G10) -> 3345776 | I10: =+H10/$H$15 -> 0.016855158
A11: FONDO DE SOLIDARIDAD Y GARANTÍA FOSYGA | C11: 972655 | D11: 685000 | E11: 563334 | F11: 0 | G11: =+SUMIFS('BD sin reclasif'!$J:$J,'BD sin reclasif'!$AH:$AH,'Detalle Gerencia'!A11,'BD sin reclasif'!$AF:$AF,'Detalle Gerencia'!$G$1) -> 0 | H11: =SUM(B11:G11) -> 2220989 | I11: =+H11/$H$15 -> 0.011188771
A12: COOMEVA E.P.S | B12: 0 | C12: 327939 | D12: 0 | G12: =+SUMIFS('BD sin reclasif'!$J:$J,'BD sin reclasif'!$AH:$AH,'Detalle Gerencia'!A12,'BD sin reclasif'!$AF:$AF,'Detalle Gerencia'!$G$1) -> 0 | H12: =SUM(B12:G12) -> 327939 | I12: =+H12/$H$15 -> 0.0016520723
A13: (en blanco) | C13: 41686 | G13: =+SUMIFS('BD sin reclasif'!$J:$J,'BD sin reclasif'!$AH:$AH,'Detalle Gerencia'!A13,'BD sin reclasif'!$AF:$AF,'Detalle Gerencia'!$G$1) -> 0 | H13: =SUM(B13:G13) -> 41686 | I13: =+H13/$H$15 -> 0.00021000334
A14: AMBUQ | G14: =+SUMIFS('BD sin reclasif'!$J:$J,'BD sin reclasif'!$AH:$AH,'Detalle Gerencia'!A14,'BD sin reclasif'!$AF:$AF,'Detalle Gerencia'!$G$1) -> 177989 | H14: =SUM(B14:G14) -> 177989
A15: Incapacidades a 2026 * EPS | B15: =SUM(B2:B13) -> 38623261 | C15: =SUM(C2:C13) -> 17167520 | D15: =SUM(D2:D13) -> 45437030 | E15: =SUM(E2:E13) -> 25931833 | F15: =SUM(F2:F13) -> 57916909 | G15: =SUM(G2:G14) -> 13425056 | H15: =SUM(H2:H14) -> 1.9850161e+08
A22: Generado | B22: =+Comportamiento!F10 -> 42950760 | C22: =+Comportamiento!I10 -> 66175156 | D22: =+Comportamiento!L10 -> 129358157 | E22: =+Comportamiento!O10 -> 189024323 | F22: =+Comportamiento!R10 -> 91449382 | G22: =+Comportamiento!S6 -> 13425056 | H22: =SUM(B22:G22) -> 5.3238283e+08
A23: Recaudado | B23: =+Comportamiento!F11*-1 -> 3940992 | C23: =+Comportamiento!I11*-1 -> 44088544 | D23: =+Comportamiento!L11*-1 -> 24346262 | E23: =+Comportamiento!O11*-1 -> 178759490 | F23: =+Comportamiento!R11*-1 -> 88178930 | G23: =+Comportamiento!T6 -> 10261364 | H23: =SUM(B23:G23) -> 349575582 | I23: =+H22-H23 -> 1.8280725e+08
A24: 2021 | B24: =3398127+542865 -> 3940992 | C24: =5546000+223908 -> 5769908 | D24: 0 | E24: 0 | F24: 49592 | H24: =SUM(B24:G24) -> 9760492 | I24: =+I23-Comportamiento!U6 -> 0
A25: 2022 | B25: 0 | C25: =22905000+15413636 -> 38318636 | D25: 4104000 | E25: 3992000 | F25: 2593000 | H25: =SUM(B25:G25) -> 49007636
A26: 2023 | B26: 0 | C26: 0 | D26: =+D23-D25 -> 20242262 | E26: =47423000+500000 -> 47923000 | F26: =3462865+8000000+4293000 -> 15755865 | G26: =1953742+1845170 -> 3798912 | H26: =SUM(B26:G26) -> 87720039
A27: 2024 | B27: 0 | C27: 0 | E27: 126844490 | F27: 36248000 | G27: 2181242 | H27: =SUM(B27:G27) -> 165273732
A28: 2025 | B28: 0 | C28: 0 | E28: 0 | F28: =45825473-8000000-4293000 -> 33532473 | G28: =2491485+1789725 -> 4281210 | H28: =SUM(B28:G28) -> 37813683
A29: 2026 | B29: 0 | C29: 0 | D29: 0 | E29: 0 | F29: 0 | G29: 0 | H29: =SUM(B29:G29) -> 0
A30: Incapacidades recaudadas | B30: =SUM(B24:B29) -> 3940992 | C30: =SUM(C24:C29) -> 44088544 | D30: =SUM(D24:D29) -> 24346262 | E30: =SUM(E24:E29) -> 178759490 | F30: =SUM(F24:F29) -> 88178930 | G30: =SUM(G24:G29) -> 10261364 | H30: =SUM(H24:H29) -> 349575582
B31: =B23=B30 -> TRUE | C31: =C23=C30 -> TRUE | D31: =D23=D30 -> TRUE | E31: =E23=E30 -> TRUE | F31: =F23=F30 -> TRUE | G31: =G23=G30 -> TRUE | H31: =H23=H30 -> TRUE
F32: =+F30-F23 -> 0 | G32: =+G23-G30 -> 0 | H32: =+H23-H30 -> 0
A34: Año | B34: Generado | C34: Recaudado | D34: Cartera Pte x recaudar
A35: 2021 | B35: =+B22 -> 42950760 | C35: =+H24 -> 9760492 | D35: =+B35-C35 -> 33190268
A36: 2022 | B36: =+C22 -> 66175156 | C36: =+H25 -> 49007636 | D36: =+B36-C36 -> 17167520
A37: 2023 | B37: =+D22 -> 129358157 | C37: =+H26 -> 87720039 | D37: =+B37-C37 -> 41638118
A38: 2024 | B38: =+E22 -> 189024323 | C38: =+H27 -> 165273732 | D38: =+B38-C38 -> 23750591
A39: 2025 | B39: =+F22 -> 91449382 | C39: =+H28 -> 37813683 | D39: =+B39-C39 -> 53635699
A40: 2026 | B40: =+G22 -> 13425056 | C40: =+G30 -> 10261364 | D40: =+B40-C40 -> 3163692
B41: =SUM(B35:B40) -> 5.3238283e+08 | C41: =SUM(C35:C40) -> 359836946 | D41: =SUM(D35:D40) -> 1.7254589e+08

Sheet Saldos X Terceros X Año
A4: Suma de Saldo | B4: AÑO
A5: TERCERO | B5: 2021 | C5: 2022 | D5: 2023 | E5: 2024 | F5: 2025 | G5: 2026 | H5: Total general
A6: ABDIEL ANTONIO SANJUR CORREA | C6: 82769 | D6: 464002 | E6: 23334 | H6: 570105
A7: ABRAM GARRIDO BARACALDO | F7: 2467400 | H7: 2467400
A8: ACOSTA MUÑOZ RAFAEL ENRIQUE | F8: 189800 | H8: 189800
A9: ACOSTA BALDOVINO LUIS CARLOS | E9: 1514488 | H9: 1514488
A10: ACOSTA FONTALVO JAIR ALFONSO | C10: 503875 | D10: 541334 | E10: -38667 | H10: 1006542
A11: ACOSTA FONTALVO WLADIMIR | D11: 43817 | E11: 43334 | H11: 87151
A12: ADALBERTO MANUEL OTERO MARTINEZ | C12: 1000001 | D12: 812001 | E12: 260000 | H12: 2072002
A13: AGAMEZ BELTRAN JAVIER ALFONZO | F13: 521950 | H13: 521950
A14: ALBEIRO SEGURA BOLAÑOS | C14: 162171 | H14: 162171
A15: ALCALA BARBOZA YENIS PATRICIA | C15: 666668 | D15: 889334 | E15: 86667 | F15: -47450 | H15: 1595219
A16: ALEJANDRO LUIS MARIN ROMERO | C16: 103721 | D16: 341332 | F16: 54371 | H16: 499424
A17: ALEJANDRO LUIS PEREZ PEDROZA | C17: 37832 | F17: 48077 | H17: 85909
A18: ALEXANDER LARA OROZCO | D18: 1317230 | E18: 767046 | H18: 2084276
A19: ALFONSO PATIÑO PUPO | C19: 103272 | D19: 43311 | H19: 146583
A20: ALFONSO JULIO CORREA | D20: 309335 | H20: 309335
A21: ALFONSO PESTANA GUETTE | E21: 433334 | H21: 433334
A22: ALVAREZ CASTRO KEIVIS MANUEL | C22: 33334 | H22: 33334
A23: ALVAREZ PIMIENTA WILL ALFONSO | E23: 698257 | F23: 759200 | H23: 1457457
A24: ALVAREZ QUIROZ DIEGO ARMANDO | E24: 46681 | H24: 46681
A25: ALVARO RAUL GOMEZ SANCHEZ | C25: 33334 | H25: 33334
A26: ANDRES SOLANA CASTILLA | F26: 790138 | H26: 790138
A27: ANDRES ENRIQUE ACEVEDO VILLADIEGO | C27: 33334 | H27: 33334
A28: ANDRES FELIPE TORRES PITALUA | E28: 346667 | F28: -129999 | H28: 216668
A29: ANDRES LAMBIS SALCEDO | F29: -47450 | H29: -47450
A30: ANGEL ENRIQUE PEREA SOLIPA | C30: 266667 | D30: 1 | F30: -266668 | H30: 0
A31: ANGULO PICOT JHONATAN | C31: 115442 | D31: 47691 | E31: 419904 | H31: 583037
A32: ANIBANIEL ARTEAGA ALTAMIRANDA | C32: 493876 | D32: 127151 | E32: 49997 | H32: 671024
A33: ANTONIO ANDRES ARRIETA ARROYO | C33: 37172 | H33: 37172
A34: ANTONIO BLANCO SIERRA | C34: 139328 | D34: 47209 | H34: 186537
A35: ANTONIO MANUEL DEL TORO GORDON | C35: 39976 | D35: 58969 | E35: 138057 | H35: 237002
A36: ARELLANO CAUSIL YEISSON | E36: 407720 | H36: 407720
A37: ARELLANO NEGRETE HERLING DAVID | D37: 184792 | E37: -134937 | H37: 49855
A38: ARGEMIRO AGRESOTH PADILLA | C38: 66668 | H38: 66668
A39: ARGEMIRO GUZMAN SANCHEZ | C39: 222227 | H39: 222227
A40: ARGUMEDO PACHECO RAMIRO ANTONIO | D40: 125809 | E40: 6702 | F40: -49031 | G40: 175246 | H40: 258726
A41: ARIAS ARRIETA JOSE ALFREDO | D41: 38667 | E41: 86668 | H41: 125335
A42: ARMANDO CASTELLANO ESPINOSA | E42: 475752 | H42: 475752
A43: ARNULFO HERNANDEZ MERCADO | C43: 357925 | D43: 850668 | E43: 2734311 | F43: 65049 | G43: 58364 | H43: 4066317
A44: ARP SURA | B44: 458350 | C44: 446824 | H44: 905174
A45: ASOCIACION MUTUAL SER EMPRESA SOLIDARIA | B45: -484 | C45: -518613 | D45: -812001 | E45: -8417349 | F45: -12685039 | G45: -2047468 | H45: -24480954
A46: ATENCIO TURIZO CARLOS MAURO | D46: 941132 | E46: 173334 | H46: 1114466
A47: AVILA JHONATAN ALZUZAR DE | C47: 33334 | H47: 33334
A48: BANCOLOMBIA | C48: -301002 | H48: -301002
A49: BANQUEZ SAYAS LACIDES | F49: 569400 | H49: 569400
A50: BARRAGAN GOMEZ ALEXANDER | C50: 766668 | E50: 43334 | H50: 810002
A51: BARRIOS CONTRERAS LEYSON JAVIER | C51: 3944291 | D51: 980112 | H51: 4924403
A52: BARRIOS CORREA DANIEL | C52: 233334 | D52: 344429 | E52: -43333 | H52: 534430
A53: BELTRAN HERRERA MICHEL | E53: 430218 | F53: -220961 | H53: 209257
A54: BENTA BERTEL YEFER ANTONIO | F54: 153230 | H54: 153230
A55: BERNAL PAYARES JORGE | C55: 33334 | E55: -476666 | H55: -443332
A56: BERRIO CONTRERAS MOISES FERNANDO | D56: 270667 | E56: 1300001 | H56: 1570668
A57: BERRIO DEL TORO HECTOR ANDRES | E57: 46773 | H57: 46773
A58: BRAYAN JOSE PIÑA PAJARO | D58: 43924 | H58: 43924
A59: BRAYHAN DAVID BORGE MATOS | C59: 133334 | H59: 133334
A60: BRITO TORRES GERMAN ENRIQUE | D60: 579340 | H60: 579340
A61: CABARCAS MEDRANO HEYSER | D61: 78255 | H61: 78255
A62: CALIXTO ANTONIO JIMENEZ TAPIA | C62: 915917 | D62: 348003 | E62: -470423 | F62: 379600 | H62: 1173097
A63: CAMACHO BELEÑO ERIK ALEXI | D63: 309334 | F63: 806933 | H63: 1116267
A64: CAMILO REALES BALLESTAS | F64: 47450 | H64: 47450
A65: CARLOS CANTILLO MUÑIZ | D65: 166141 | H65: 166141
A66: CARLOS EDUARDO CARDONA TORRES | D66: 77334 | H66: 77334
A67: CARLOS ENRIQUE SALAS CONTRERAS | C67: 40542 | D67: 865069 | E67: 310058 | H67: 1215669
A68: CARVAJAL BERROCAL JESUS | E68: 86668 | G68: 58364 | H68: 145032
A69: CARVAJAL RAMOS DANIEL ANDRES | F69: 142350 | H69: 142350
A70: CASTAÑO OROZCO CESAR HUMBERTO | D70: 1986969 | H70: 1986969
A71: CASTILLA PARDO AMAURY JOSE | D71: 38667 | E71: 130002 | H71: 168669
A72: CASTILLO DE LA OSSA JESUS EDUARDO | E72: 130000 | H72: 130000
A73: CASTILLO PEREZ ANDERSON | E73: 650002 | G73: 1634178 | H73: 2284180
A74: Castro Julio Tayler Enrique | D74: 39600 | H74: 39600
A75: CASTRO SIMARRA RAFAEL | F75: 72063 | H75: 72063
A76: CESAR DAVID IBAÑEZ MAGALLANES | E76: 43334 | H76: 43334
A77: CESAR ENRIQUE GALVIZ CASTILLA | E77: 43765 | G77: 58364 | H77: 102129
A78: CESAR GONZALEZ AVILA | E78: 93008 | H78: 93008
A79: CESPEDES RODRIGUEZ ANGEL ANTONIO | E79: 47394 | H79: 47394
A80: CIFUENTESMARTINEZ YAIR | D80: 623905 | H80: 623905
A81: COLMENA SEGUROS RIESGOS LABORALES S.A., RIESGOS LABORALES COLMENA S.A. COMPAÑIA DE SEGUROS DE VIDA | F81: -5729366 | G81: -382648 | H81: -6112014
A82: CONDE MENDOZA ALEJANDRA PAOLA | C82: 40853 | H82: 40853
A83: CONEO GAMARRA JOSE ANTONIO | D83: 38667 | E83: 311 | F83: 146362 | H83: 185340
A84: CONEO GOMEZ LUIS DANIEL | E84: 100310 | F84: -97095 | H84: 3215
A85: CONTRERAS JAIRO VANEGAS | D85: 541334 | E85: 55768 | F85: -52113 | H85: 544989
A86: COOSALUD ENTIDAD PROMOTORA DE SALUD S.A | B86: 33291 | C86: -1849319 | D86: -854152 | E86: -173334 | F86: -855607 | H86: -3699121
A87: COOSALUD ESS ENTIDAD PROMOTORA DE SALUD | D87: -151421 | H87: -151421
A88: CORTINA AGAMEZ CESAR AUGUSTO | E88: 43334 | H88: 43334
A89: COTA HERNANDEZ ALEJANDRO | D89: 130584 | E89: -124000 | H89: 6584
A90: CRISTIAN CAMILO ALVAREZ RICARDO | E90: 43334 | H90: 43334
A91: CUELLO MAESTRE YOEL JOSE | D91: 38667 | G91: 58364 | H91: 97031
A92: CUESTA CARLOS IVAN | D92: 348001 | H92: 348001
A93: DAIRIS P. VEGA HERNANDEZ | F93: -43333 | H93: -43333
A94: DAIRO CASTRO CASTRO | D94: 38667 | H94: 38667
A95: DANIEL GONZALEZ PADILLA | E95: 1168306 | H95: 1168306
A96: DANIEL ISAAC GONZALEZ SUAREZ | D96: 77334 | E96: -82276 | H96: -4942
A97: DANIEL SALINAS MUENTES | E97: 173334 | H97: 173334
A98: DE LAS AGUAS TEHERAN JADER | D98: 154667 | E98: 4927050 | H98: 5081717
A99: DECHAMPS MORALES MANUEL CARMELO | C99: 887849 | D99: 1237334 | E99: 1820001 | F99: 1328600 | H99: 5273784
A100: DEIVI LUIS MARTELO CORTINA | C100: 35339 | H100: 35339
A101: DEIVIS GARCIA LICONA | C101: 584877 | H101: 584877
A102: DIANER DAVILA SANES | E102: 351144 | F102: -346664 | H102: 4480
A103: DIAZ DORADO MIGUEL ENRIQUE | E103: -983136 | H103: -983136
...

Sheet BD sin reclasif
A1: SUBSISTEMA DE CONTABILIDAD
A2: TRANSAMBIENTAL S.A.S.
A3: CONSULTA DE MOVIMIENTO POR FUENTES A 24.MAR./2026 | I3: Saldo a 2025
A4: PERIODO COMPRENDIDO ENTRE 01.ENE./2021 Y 28.FEB./2026 | I4: 1.7970636e+08 | J4: =SUBTOTAL(9,J7:J10000) -> 13425056 | K4: =SUBTOTAL(9,K7:K10000) -> 0 | L4: =+J4-K4 -> 13425056
A6: Codigo Cuenta | B6: Nombre Cuenta | C6: Fecha Documento | D6: Año | E6: Fuente | F6: Nombre Fuente | G6: Prefijo Documento | H6: Numero Documento | I6: Detalle del Registro | J6: Generado | K6: Reintegrado | L6: Saldo | M6: Tipo Anexo | N6: Id.Tercero | O6: Nombre Tercero | P6: Codigo Costo | Q6: Nombre Costo | R6: Codigo Retencion | S6: Concepto Retencion | T6: Base Retencion | U6: Tipo Libro | V6: Asiento Cierre | W6: Documento Referencia | X6: Numero Cheque | Y6: Codigo Operacion | Z6: Fecha Operacion | AA6: Programa | AB6: Estacion | AC6: Empresa | AD6: Fecha Version | AE6: Estado Reg. | AF6: Año 2 | AG6: Mes | AH6: eps
A7: 138020001 | B7: REINTEGRO DE INCAPACIDADES | C7: 44530 | D7: =TEXT(C7,"yyyy") -> 2021 | E7: 99 | F7: SALDOS INICIALES | H7: 000000001 | I7: REINTEGRO DE INCAPACIDADES | J7: 38623261 | K7: 0 | L7: =+J7-K7 -> 38623261 | M7: 1 | N7: 900771273 | O7: TRANSAMBIENTAL | T7: 0 | U7: CONTABLE | V7: N | W7: 000000001 | X7: 0 | Y7: TACOSITI | Z7: Feb 8 2022 4:17AM | AA7: frmCON6093 | AB7: DESKTOP-5900GRN | AC7: TAMBIENTAL | AD7: Feb 8 2022 4:17AM | AF7: =YEAR(C7) -> 2021 | AG7: =TEXT(C7,"mmm") -> nov | AH7: TRANSAMBIENTAL | AI7: #N/A
A8: 138020001 | B8: REINTEGRO DE INCAPACIDADES | C8: 44532 | D8: =TEXT(C8,"yyyy") -> 2021 | E8: 15 | F8: CONSIGNACIONES BANCO | H8: 000000010 | I8: EPS SURA COMPAÑIA SURAMERICANA SERVICIOS DE SALUD:REINTEGRO INCAPACIDAD SURAMERICANA000000010 | J8: 0 | K8: 262479 | L8: =+J8-K8 -> -262479 | M8: 1 | N8: 800088702 | O8: EPS SURA COMPAÑIA SURAMERICANA SERVICIOS DE SALUD | T8: 0 | U8: CONTABLE | V8: N | W8: 000000010 | X8: 0 | Y8: TACOTESO | Z8: Ene 14 2022 5:20PM | AA8: frmBAN607 | AB8: DESKTOP-O60S49G | AC8: TAMBIENTAL | AD8: Ene 14 2022 5:20PM | AF8: =YEAR(C8) -> 2021 | AG8: =TEXT(C8,"mmm") -> dic | AH8: EPS SURA COMPAÑIA SURAMERICANA SERVICIOS DE SALUD | AI8: #N/A
A9: 138020001 | B9: REINTEGRO DE INCAPACIDADES | C9: 44532 | D9: =TEXT(C9,"yyyy") -> 2021 | E9: 15 | F9: CONSIGNACIONES BANCO | H9: 000000011 | I9: SALUD TOTAL S.A. EPS ARS:REINTEGRO INCAPACIDAD SALUD TOTAL000000011 | J9: 0 | K9: 428175 | L9: =+J9-K9 -> -428175 | M9: 1 | N9: 800130907 | O9: SALUD TOTAL S.A. EPS ARS | T9: 0 | U9: CONTABLE | V9: N | W9: 000000011 | X9: 0 | Y9: TACOTESO | Z9: Ene 14 2022 5:27PM | AA9: frmBAN607 | AB9: DESKTOP-O60S49G | AC9: TAMBIENTAL | AD9: Ene 14 2022 5:27PM | AF9: =YEAR(C9) -> 2021 | AG9: =TEXT(C9,"mmm") -> dic | AH9: SALUD TOTAL S.A. EPS ARS | AI9: #N/A
A10: 138020001 | B10: REINTEGRO DE INCAPACIDADES | C10: 44540 | D10: =TEXT(C10,"yyyy") -> 2021 | E10: 15 | F10: CONSIGNACIONES BANCO | H10: 000000007 | I10: SALUD TOTAL S.A. EPS ARS:REINTEGRO INCAPACIDAD SALUD TOTAL000000007 | J10: 0 | K10: 1535787 | L10: =+J10-K10 -> -1535787 | M10: 1 | N10: 800130907 | O10: SALUD TOTAL S.A. EPS ARS | T10: 0 | U10: CONTABLE | V10: N | W10: 000000007 | X10: 0 | Y10: TACOTESO | Z10: Ene 14 2022 4:39PM | AA10: frmBAN607 | AB10: DESKTOP-O60S49G | AC10: TAMBIENTAL | AD10: Ene 14 2022 4:39PM | AF10: =YEAR(C10) -> 2021 | AG10: =TEXT(C10,"mmm") -> dic | AH10: SALUD TOTAL S.A. EPS ARS | AI10: #N/A
A11: 138020001 | B11: REINTEGRO DE INCAPACIDADES | C11: 44540 | D11: =TEXT(C11,"yyyy") -> 2021 | E11: 15 | F11: CONSIGNACIONES BANCO | H11: 000000008 | I11: NUEVA EMPRESA PROMOTORA DE SALUD:REINTEGRO INCAPACIDAD NUEVA EPS000000008 | J11: 0 | K11: 195079 | L11: =+J11-K11 -> -195079 | M11: 1 | N11: 900156264 | O11: NUEVA EMPRESA PROMOTORA DE SALUD | T11: 0 | U11: CONTABLE | V11: N | W11: 000000008 | X11: 0 | Y11: TACOTESO | Z11: Ene 14 2022 4:41PM | AA11: frmBAN607 | AB11: DESKTOP-O60S49G | AC11: TAMBIENTAL | AD11: Ene 14 2022 4:41PM | AF11: =YEAR(C11) -> 2021 | AG11: =TEXT(C11,"mmm") -> dic | AH11: NUEVA EMPRESA PROMOTORA DE SALUD | AI11: #N/A
A12: 138020001 | B12: REINTEGRO DE INCAPACIDADES | C12: 44545 | D12: =TEXT(C12,"yyyy") -> 2021 | E12: 21 | F12: NOMINA NOVASOFT | H12: 000000001 | I12: GASTOS REEMBOLSABLES | J12: 42866 | K12: 0 | L12: =+J12-K12 -> 42866 | M12: 1 | N12: 800088702 | O12: EPS SURA COMPAÑIA SURAMERICANA SERVICIOS DE SALUD | P12: 10010200 | Q12: COMPRAS Y ABASTESIMIENTO | T12: 0 | U12: CONTABLE | V12: N | W12: 000000001 | X12: 0 | Y12: TACOSITI | Z12: Feb 8 2022 5:24PM | AA12: frmCON6093 | AB12: DESKTOP-5900GRN | AC12: TAMBIENTAL | AD12: Feb 8 2022 5:24PM | AF12: =YEAR(C12) -> 2021 | AG12: =TEXT(C12,"mmm") -> dic | AH12: EPS SURA COMPAÑIA SURAMERICANA SERVICIOS DE SALUD | AI12: #N/A
A13: 138020001 | B13: REINTEGRO DE INCAPACIDADES | C13: 44545 | D13: =TEXT(C13,"yyyy") -> 2021 | E13: 21 | F13: NOMINA NOVASOFT | H13: 000000001 | I13: GASTOS REEMBOLSABLES | J13: 30284 | K13: 0 | L13: =+J13-K13 -> 30284 | M13: 1 | N13: 800088702 | O13: EPS SURA COMPAÑIA SURAMERICANA SERVICIOS DE SALUD | P13: 10020200 | Q13: EJECUCIÓN | T13: 0 | U13: CONTABLE | V13: N | W13: 000000001 | X13: 0 | Y13: TACOSITI | Z13: Feb 8 2022 5:24PM | AA13: frmCON6093 | AB13: DESKTOP-5900GRN | AC13: TAMBIENTAL | AD13: Feb 8 2022 5:24PM | AF13: =YEAR(C13) -> 2021 | AG13: =TEXT(C13,"mmm") -> dic | AH13: EPS SURA COMPAÑIA SURAMERICANA SERVICIOS DE SALUD | AI13: #N/A
A14: 138020001 | B14: REINTEGRO DE INCAPACIDADES | C14: 44545 | D14: =TEXT(C14,"yyyy") -> 2021 | E14: 21 | F14: NOMINA NOVASOFT | H14: 000000001 | I14: GASTOS REEMBOLSABLES | J14: 77628 | K14: 0 | L14: =+J14-K14 -> 77628 | M14: 1 | N14: 800256161 | O14: ARP SURA | P14: 10020200 | Q14: EJECUCIÓN | T14: 0 | U14: CONTABLE | V14: N | W14: 000000001 | X14: 0 | Y14: TACOSITI | Z14: Feb 8 2022 5:24PM | AA14: frmCON6093 | AB14: DESKTOP-5900GRN | AC14: TAMBIENTAL | AD14: Feb 8 2022 5:24PM | AF14: =YEAR(C14) -> 2021 | AG14: =TEXT(C14,"mmm") -> dic | AH14: ARP SURA | AI14: #N/A
A15: 138020001 | B15: REINTEGRO DE INCAPACIDADES | C15: 44545 | D15: =TEXT(C15,"yyyy") -> 2021 | E15: 21 | F15: NOMINA NOVASOFT | H15: 000000001 | I15: GASTOS REEMBOLSABLES | J15: 60568 | K15: 0 | L15: =+J15-K15 -> 60568 | M15: 1 | N15: 800130907 | O15: SALUD TOTAL S.A. EPS ARS | P15: 10030200 | Q15: COORDINACIÓN DE OPERACIONES | T15: 0 | U15: CONTABLE | V15: N | W15: 000000001 | X15: 0 | Y15: TACOSITI | Z15: Feb 8 2022 5:24PM | AA15: frmCON6093 | AB15: DESKTOP-5900GRN | AC15: TAMBIENTAL | AD15: Feb 8 2022 5:24PM | AF15: =YEAR(C15) -> 2021 | AG15: =TEXT(C15,"mmm") -> dic | AH15: SALUD TOTAL S.A. EPS ARS | AI15: #N/A
A16: 138020001 | B16: REINTEGRO DE INCAPACIDADES | C16: 44545 | D16: =TEXT(C16,"yyyy") -> 2021 | E16: 21 | F16: NOMINA NOVASOFT | H16: 000000001 | I16: GASTOS REEMBOLSABLES | J16: 67244 | K16: 0 | L16: =+J16-K16 -> 67244 | M16: 1 | N16: 800088702 | O16: EPS SURA COMPAÑIA SURAMERICANA SERVICIOS DE SALUD | P16: 10030400 | Q16: OPERADORES | T16: 0 | U16: CONTABLE | V16: N | W16: 000000001 | X16: 0 | Y16: TACOSITI | Z16: Feb 8 2022 5:24PM | AA16: frmCON6093 | AB16: DESKTOP-5900GRN | AC16: TAMBIENTAL | AD16: Feb 8 2022 5:24PM | AF16: =YEAR(C16) -> 2021 | AG16: =TEXT(C16,"mmm") -> dic | AH16: EPS SURA COMPAÑIA SURAMERICANA SERVICIOS DE SALUD | AI16: #N/A
A17: 138020001 | B17: REINTEGRO DE INCAPACIDADES | C17: 44545 | D17: =TEXT(C17,"yyyy") -> 2021 | E17: 21 | F17: NOMINA NOVASOFT | H17: 000000001 | I17: GASTOS REEMBOLSABLES | J17: 454263 | K17: 0 | L17: =+J17-K17 -> 454263 | M17: 1 | N17: 800130907 | O17: SALUD TOTAL S.A. EPS ARS | P17: 10030400 | Q17: OPERADORES | T17: 0 | U17: CONTABLE | V17: N | W17: 000000001 | X17: 0 | Y17: TACOSITI | Z17: Feb 8 2022 5:24PM | AA17: frmCON6093 | AB17: DESKTOP-5900GRN | AC17: TAMBIENTAL | AD17: Feb 8 2022 5:24PM | AF17: =YEAR(C17) -> 2021 | AG17: =TEXT(C17,"mmm") -> dic | AH17: SALUD TOTAL S.A. EPS ARS | AI17: #N/A
A18: 138020001 | B18: REINTEGRO DE INCAPACIDADES | C18: 44545 | D18: =TEXT(C18,"yyyy") -> 2021 | E18: 21 | F18: NOMINA NOVASOFT | H18: 000000001 | I18: GASTOS REEMBOLSABLES | J18: 32965 | K18: 0 | L18: =+J18-K18 -> 32965 | M18: 1 | N18: 800130907 | O18: SALUD TOTAL S.A. EPS ARS | P18: 10030400 | Q18: OPERADORES | T18: 0 | U18: CONTABLE | V18: N | W18: 000000001 | X18: 0 | Y18: TACOSITI | Z18: Feb 8 2022 5:24PM | AA18: frmCON6093 | AB18: DESKTOP-5900GRN | AC18: TAMBIENTAL | AD18: Feb 8 2022 5:24PM | AF18: =YEAR(C18) -> 2021 | AG18: =TEXT(C18,"mmm") -> dic | AH18: SALUD TOTAL S.A. EPS ARS | AI18: #N/A
A19: 138020001 | B19: REINTEGRO DE INCAPACIDADES | C19: 44545 | D19: =TEXT(C19,"yyyy") -> 2021 | E19: 21 | F19: NOMINA NOVASOFT | H19: 000000001 | I19: GASTOS REEMBOLSABLES | J19: 163561 | K19: 0 | L19: =+J19-K19 -> 163561 | M19: 1 | N19: 800130907 | O19: SALUD TOTAL S.A. EPS ARS | P19: 10030400 | Q19: OPERADORES | T19: 0 | U19: CONTABLE | V19: N | W19: 000000001 | X19: 0 | Y19: TACOSITI | Z19: Feb 8 2022 5:24PM | AA19: frmCON6093 | AB19: DESKTOP-5900GRN | AC19: TAMBIENTAL | AD19: Feb 8 2022 5:24PM | AF19: =YEAR(C19) -> 2021 | AG19: =TEXT(C19,"mmm") -> dic | AH19: SALUD TOTAL S.A. EPS ARS | AI19: #N/A
A20: 138020001 | B20: REINTEGRO DE INCAPACIDADES | C20: 44545 | D20: =TEXT(C20,"yyyy") -> 2021 | E20: 21 | F20: NOMINA NOVASOFT | H20: 000000001 | I20: GASTOS REEMBOLSABLES | J20: 363410 | K20: 0 | L20: =+J20-K20 -> 363410 | M20: 1 | N20: 800251440 | O20: E.P.S. SANITAS S.A. | P20: 10030400 | Q20: OPERADORES | T20: 0 | U20: CONTABLE | V20: N | W20: 000000001 | X20: 0 | Y20: TACOSITI | Z20: Feb 8 2022 5:24PM | AA20: frmCON6093 | AB20: DESKTOP-5900GRN | AC20: TAMBIENTAL | AD20: Feb 8 2022 5:24PM | AF20: =YEAR(C20) -> 2021 | AG20: =TEXT(C20,"mmm") -> dic | AH20: E.P.S. SANITAS S.A. | AI20: #N/A
A21: 138020001 | B21: REINTEGRO DE INCAPACIDADES | C21: 44545 | D21: =TEXT(C21,"yyyy") -> 2021 | E21: 21 | F21: NOMINA NOVASOFT | H21: 000000001 | I21: GASTOS REEMBOLSABLES | J21: 60568 | K21: 0 | L21: =+J21-K21 -> 60568 | M21: 1 | N21: 800251440 | O21: E.P.S. SANITAS S.A. | P21: 10030400 | Q21: OPERADORES | T21: 0 | U21: CONTABLE | V21: N | W21: 000000001 | X21: 0 | Y21: TACOSITI | Z21: Feb 8 2022 5:24PM | AA21: frmCON6093 | AB21: DESKTOP-5900GRN | AC21: TAMBIENTAL | AD21: Feb 8 2022 5:24PM | AF21: =YEAR(C21) -> 2021 | AG21: =TEXT(C21,"mmm") -> dic | AH21: E.P.S. SANITAS S.A. | AI21: #N/A
A22: 138020001 | B22: REINTEGRO DE INCAPACIDADES | C22: 44545 | D22: =TEXT(C22,"yyyy") -> 2021 | E22: 21 | F22: NOMINA NOVASOFT | H22: 000000001 | I22: GASTOS REEMBOLSABLES | J22: 30284 | K22: 0 | L22: =+J22-K22 -> 30284 | M22: 1 | N22: 800251440 | O22: E.P.S. SANITAS S.A. | P22: 10030400 | Q22: OPERADORES | T22: 0 | U22: CONTABLE | V22: N | W22: 000000001 | X22: 0 | Y22: TACOSITI | Z22: Feb 8 2022 5:24PM | AA22: frmCON6093 | AB22: DESKTOP-5900GRN | AC22: TAMBIENTAL | AD22: Feb 8 2022 5:24PM | AF22: =YEAR(C22) -> 2021 | AG22: =TEXT(C22,"mmm") -> dic | AH22: E.P.S. SANITAS S.A. | AI22: #N/A
A23: 138020001 | B23: REINTEGRO DE INCAPACIDADES | C23: 44545 | D23: =TEXT(C23,"yyyy") -> 2021 | E23: 21 | F23: NOMINA NOVASOFT | H23: 000000001 | I23: GASTOS REEMBOLSABLES | J23: 31088 | K23: 0 | L23: =+J23-K23 -> 31088 | M23: 1 | N23: 806008394 | O23: ASOCIACION MUTUAL SER EMPRESA SOLIDARIA | P23: 10030400 | Q23: OPERADORES | T23: 0 | U23: CONTABLE | V23: N | W23: 000000001 | X23: 0 | Y23: TACOSITI | Z23: Feb 8 2022 5:24PM | AA23: frmCON6093 | AB23: DESKTOP-5900GRN | AC23: TAMBIENTAL | AD23: Feb 8 2022 5:24PM | AF23: =YEAR(C23) -> 2021 | AG23: =TEXT(C23,"mmm") -> dic | AH23: ASOCIACION MUTUAL SER EMPRESA SOLIDARIA | AI23: #N/A
... A25: 138020001 | B25: REINTEGRO DE INCAPACIDADES | C25: 44545 | D25: =TEXT(C25,"yyyy") -> 2021 | E25: 21 | F25: NOMINA NOVASOFT | H25: 000000001 | I25: GASTOS REEMBOLSABLES | J25: 513641 | K25: 0 | L25: =+J25-K25 -> 513641 | M25: 1 | N25: 900156264 | O25: NUEVA EMPRESA PROMOTORA DE SALUD | P25: 10030400 | Q25: OPERADORES | T25: 0 | U25: CONTABLE | V25: N | W25: 000000001 | X25: 0 | Y25: TACOSITI | Z25: Feb 8 2022 5:24PM | AA25: frmCON6093 | AB25: DESKTOP-5900GRN | AC25: TAMBIENTAL | AD25: Feb 8 2022 5:24PM | AF25: =YEAR(C25) -> 2021 | AG25: =TEXT(C25,"mmm") -> dic | AH25: NUEVA EMPRESA PROMOTORA DE SALUD | AI25: #N/A
A26: 138020001 | B26: REINTEGRO DE INCAPACIDADES | C26: 44553 | D26: =TEXT(C26,"yyyy") -> 2021 | E26: 15 | F26: CONSIGNACIONES BANCO | H26: 000000003 | I26: SALUD TOTAL S.A. EPS ARS:REINTEGRO INCAPACIDAD SALUD TOTAL000000003 | J26: 0 | K26: 885682 | L26: =+J26-K26 -> -885682 | M26: 1 | N26: 800130907 | O26: SALUD TOTAL S.A. EPS ARS | T26: 0 | U26: CONTABLE | V26: N | W26: 000000003 | X26: 0 | Y26: TACOTESO | Z26: Ene 14 2022 3:48PM | AA26: frmBAN607 | AB26: DESKTOP-O60S49G | AC26: TAMBIENTAL | AD26: Ene 14 2022 3:48PM | AF26: =YEAR(C26) -> 2021 | AG26: =TEXT(C26,"mmm") -> dic | AH26: SALUD TOTAL S.A. EPS ARS | AI26: #N/A
A27: 138020001 | B27: REINTEGRO DE INCAPACIDADES | C27: 44553 | D27: =TEXT(C27,"yyyy") -> 2021 | E27: 15 | F27: CONSIGNACIONES BANCO | H27: 000000004 | I27: SALUD TOTAL S.A. EPS ARS:REINTEGRO INCAPACIDAD SALUD TOTAL000000004 | J27: 0 | K27: 274266 | L27: =+J27-K27 -> -274266 | M27: 1 | N27: 800130907 | O27: SALUD TOTAL S.A. EPS ARS | T27: 0 | U27: CONTABLE | V27: N | W27: 000000004 | X27: 0 | Y27: TACOTESO | Z27: Ene 14 2022 3:51PM | AA27: frmBAN607 | AB27: DESKTOP-O60S49G | AC27: TAMBIENTAL | AD27: Ene 14 2022 3:51PM | AF27: =YEAR(C27) -> 2021 | AG27: =TEXT(C27,"mmm") -> dic | AH27: SALUD TOTAL S.A. EPS ARS | AI27: #N/A
A28: 138020001 | B28: REINTEGRO DE INCAPACIDADES | C28: 44553 | D28: =TEXT(C28,"yyyy") -> 2021 | E28: 15 | F28: CONSIGNACIONES BANCO | H28: 000000005 | I28: E.P.S. FAMISANAR LTDA. CAFAM COLSUBSIDIO:REINTEGRO INCAPACIDAD FAMISANAR000000005 | J28: 0 | K28: 97173 | L28: =+J28-K28 -> -97173 | M28: 1 | N28: 830003564 | O28: E.P.S. FAMISANAR LTDA. CAFAM COLSUBSIDIO | T28: 0 | U28: CONTABLE | V28: N | W28: 000000005 | X28: 0 | Y28: TACOTESO | Z28: Ene 14 2022 3:58PM | AA28: frmBAN607 | AB28: DESKTOP-O60S49G | AC28: TAMBIENTAL | AD28: Ene 14 2022 3:58PM | AF28: =YEAR(C28) -> 2021 | AG28: =TEXT(C28,"mmm") -> dic | AH28: E.P.S. FAMISANAR LTDA. CAFAM COLSUBSIDIO | AI28: #N/A
A29: 138020001 | B29: REINTEGRO DE INCAPACIDADES | C29: 44553 | D29: =TEXT(C29,"yyyy") -> 2021 | E29: 15 | F29: CONSIGNACIONES BANCO | H29: 000000006 | I29: EPS SURA COMPAÑIA SURAMERICANA SERVICIOS DE SALUD:REINTEGRO INCAPACIDAD SURAMERICANA000000006 | J29: 0 | K29: 97524 | L29: =+J29-K29 -> -97524 | M29: 1 | N29: 800088702 | O29: EPS SURA COMPAÑIA SURAMERICANA SERVICIOS DE SALUD | T29: 0 | U29: CONTABLE | V29: N | W29: 000000006 | X29: 0 | Y29: TACOTESO | Z29: Ene 14 2022 4:37PM | AA29: frmBAN607 | AB29: DESKTOP-O60S49G | AC29: TAMBIENTAL | AD29: Ene 14 2022 4:37PM | AF29: =YEAR(C29) -> 2021 | AG29: =TEXT(C29,"mmm") -> dic | AH29: EPS SURA COMPAÑIA SURAMERICANA SERVICIOS DE SALUD | AI29: #N/A
A30: 138020001 | B30: REINTEGRO DE INCAPACIDADES | C30: 44554 | D30: =TEXT(C30,"yyyy") -> 2021 | E30: 15 | F30: CONSIGNACIONES BANCO | H30: 000000015 | I30: ASOCIACION MUTUAL SER EMPRESA SOLIDARIA:Reintegro incapacidad Mutual SER000000015 | J30: 0 | K30: 31572 | L30: =+J30-K30 -> -31572 | M30: 1 | N30: 806008394 | O30: ASOCIACION MUTUAL SER EMPRESA SOLIDARIA | T30: 0 | U30: CONTABLE | V30: N | W30: 000000015 | X30: 0 | Y30: TACOTESO | Z30: Feb 15 2022 2:10PM | AA30: frmBAN607 | AB30: DESKTOP-O60S49G | AC30: TAMBIENTAL | AD30: Feb 15 2022 2:10PM | AF30: =YEAR(C30) -> 2021 | AG30: =TEXT(C30,"mmm") -> dic | AH30: ASOCIACION MUTUAL SER EMPRESA SOLIDARIA | AI30: #N/A
A31: 138020001 | B31: REINTEGRO DE INCAPACIDADES | C31: 44559 | D31: =TEXT(C31,"yyyy") -> 2021 | E31: 15 | F31: CONSIGNACIONES BANCO | H31: 000000001 | I31: SALUD TOTAL S.A. EPS ARS:Reintegro incapacidad Salud Total000000001 | J31: 0 | K31: 133255 | L31: =+J31-K31 -> -133255 | M31: 1 | N31: 800130907 | O31: SALUD TOTAL S.A. EPS ARS | T31: 0 | U31: CONTABLE | V31: N | W31: 000000001 | X31: 0 | Y31: TACOTESO | Z31: Ene 14 2022 2:07PM | AA31: frmBAN607 | AB31: DESKTOP-O60S49G | AC31: TAMBIENTAL | AD31: Ene 14 2022 2:07PM | AF31: =YEAR(C31) -> 2021 | AG31: =TEXT(C31,"mmm") -> dic | AH31: SALUD TOTAL S.A. EPS ARS | AI31: #N/A
A32: 138020001 | B32: REINTEGRO DE INCAPACIDADES | C32: 44561 | D32: =TEXT(C32,"yyyy") -> 2021 | E32: 21 | F32: NOMINA NOVASOFT | H32: 000000001 | I32: GASTOS REEMBOLSABLES | J32: 278990 | K32: 0 | L32: =+J32-K32 -> 278990 | M32: 1 | N32: 800256161 | O32: ARP SURA | P32: 10020200 | Q32: EJECUCIÓN | T32: 0 | U32: CONTABLE | V32: N | W32: 000000001 | X32: 0 | Y32: TACOSITI | Z32: Feb 8 2022 5:24PM | AA32: frmCON6093 | AB32: DESKTOP-5900GRN | AC32: TAMBIENTAL | AD32: Feb 8 2022 5:24PM | AF32: =YEAR(C32) -> 2021 | AG32: =TEXT(C32,"mmm") -> dic | AH32: ARP SURA | AI32: #N/A
A33: 138020001 | B33: REINTEGRO DE INCAPACIDADES | C33: 44561 | D33: =TEXT(C33,"yyyy") -> 2021 | E33: 21 | F33: NOMINA NOVASOFT | H33: 000000001 | I33: GASTOS REEMBOLSABLES | J33: 33082 | K33: 0 | L33: =+J33-K33 -> 33082 | M33: 1 | N33: 800088702 | O33: EPS SURA COMPAÑIA SURAMERICANA SERVICIOS DE SALUD | P33: 10030400 | Q33: OPERADORES | T33: 0 | U33: CONTABLE | V33: N | W33: 000000001 | X33: 0 | Y33: TACOSITI | Z33: Feb 8 2022 5:24PM | AA33: frmCON6093 | AB33: DESKTOP-5900GRN | AC33: TAMBIENTAL | AD33: Feb 8 2022 5:24PM | AF33: =YEAR(C33) -> 2021 | AG33: =TEXT(C33,"mmm") -> dic | AH33: EPS SURA COMPAÑIA SURAMERICANA SERVICIOS DE SALUD | AI33: #N/A
A34: 138020001 | B34: REINTEGRO DE INCAPACIDADES | C34: 44561 | D34: =TEXT(C34,"yyyy") -> 2021 | E34: 21 | F34: NOMINA NOVASOFT | H34: 000000001 | I34: GASTOS REEMBOLSABLES | J34: 68499 | K34: 0 | L34: =+J34-K34 -> 68499 | M34: 1 | N34: 800088702 | O34: EPS SURA COMPAÑIA SURAMERICANA SERVICIOS DE SALUD | P34: 10030400 | Q34: OPERADORES | T34: 0 | U34: CONTABLE | V34: N | W34: 000000001 | X34: 0 | Y34: TACOSITI | Z34: Feb 8 2022 5:24PM | AA34: frmCON6093 | AB34: DESKTOP-5900GRN | AC34: TAMBIENTAL | AD34: Feb 8 2022 5:24PM | AF34: =YEAR(C34) -> 2021 | AG34: =TEXT(C34,"mmm") -> dic | AH34: EPS SURA COMPAÑIA SURAMERICANA SERVICIOS DE SALUD | AI34: #N/A
A35: 138020001 | B35: REINTEGRO DE INCAPACIDADES | C35: 44561 | D35: =TEXT(C35,"yyyy") -> 2021 | E35: 21 | F35: NOMINA NOVASOFT | H35: 000000001 | I35: GASTOS REEMBOLSABLES | J35: 484547 | K35: 0 | L35: =+J35-K35 -> 484547 | M35: 1 | N35: 800130907 | O35: SALUD TOTAL S.A. EPS ARS | P35: 10030400 | Q35: OPERADORES | T35: 0 | U35: CONTABLE | V35: N | W35: 000000001 | X35: 0 | Y35: TACOSITI | Z35: Feb 8 2022 5:24PM | AA35: frmCON6093 | AB35: DESKTOP-5900GRN | AC35: TAMBIENTAL | AD35: Feb 8 2022 5:24PM | AF35: =YEAR(C35) -> 2021 | AG35: =TEXT(C35,"mmm") -> dic | AH35: SALUD TOTAL S.A. EPS ARS | AI35: #N/A
A36: 138020001 | B36: REINTEGRO DE INCAPACIDADES | C36: 44561 | D36: =TEXT(C36,"yyyy") -> 2021 | E36: 21 | F36: NOMINA NOVASOFT | H36: 000000001 | I36: GASTOS REEMBOLSABLES | J36: 30881 | K36: 0 | L36: =+J36-K36 -> 30881 | M36: 1 | N36: 800130907 | O36: SALUD TOTAL S.A. EPS ARS | P36: 10030400 | Q36: OPERADORES | T36: 0 | U36: CONTABLE | V36: N | W36: 000000001 | X36: 0 | Y36: TACOSITI | Z36: Feb 8 2022 5:24PM | AA36: frmCON6093 | AB36: DESKTOP-5900GRN | AC36: TAMBIENTAL | AD36: Feb 8 2022 5:24PM | AF36: =YEAR(C36) -> 2021 | AG36: =TEXT(C36,"mmm") -> dic | AH36: SALUD TOTAL S.A. EPS ARS | AI36: #N/A
A37: 138020001 | B37: REINTEGRO DE INCAPACIDADES | C37: 44561 | D37: =TEXT(C37,"yyyy") -> 2021 | E37: 21 | F37: NOMINA NOVASOFT | H37: 000000001 | I37: GASTOS REEMBOLSABLES | J37: 102302 | K37: 0 | L37: =+J37-K37 -> 102302 | M37: 1 | N37: 800130907 | O37: SALUD TOTAL S.A. EPS ARS | P37: 10030400 | Q37: OPERADORES | T37: 0 | U37: CONTABLE | V37: N | W37: 000000001 | X37: 0 | Y37: TACOSITI | Z37: Feb 8 2022 5:24PM | AA37: frmCON6093 | AB37: DESKTOP-5900GRN | AC37: TAMBIENTAL | AD37: Feb 8 2022 5:24PM | AF37: =YEAR(C37) -> 2021 | AG37: =TEXT(C37,"mmm") -> dic | AH37: SALUD TOTAL S.A. EPS ARS | AI37: #N/A
A38: 138020001 | B38: REINTEGRO DE INCAPACIDADES | C38: 44561 | D38: =TEXT(C38,"yyyy") -> 2021 | E38: 21 | F38: NOMINA NOVASOFT | H38: 000000001 | I38: GASTOS REEMBOLSABLES | J38: 98137 | K38: 0 | L38: =+J38-K38 -> 98137 | M38: 1 | N38: 800130907 | O38: SALUD TOTAL S.A. EPS ARS | P38: 10030400 | Q38: OPERADORES | T38: 0 | U38: CONTABLE | V38: N | W38: 000000001 | X38: 0 | Y38: TACOSITI | Z38: Feb 8 2022 5:24PM | AA38: frmCON6093 | AB38: DESKTOP-5900GRN | AC38: TAMBIENTAL | AD38: Feb 8 2022 5:24PM | AF38: =YEAR(C38) -> 2021 | AG38: =TEXT(C38,"mmm") -> dic | AH38: SALUD TOTAL S.A. EPS ARS | AI38: #N/A
A39: 138020001 | B39: REINTEGRO DE INCAPACIDADES | C39: 44561 | D39: =TEXT(C39,"yyyy") -> 2021 | E39: 21 | F39: NOMINA NOVASOFT | H39: 000000001 | I39: GASTOS REEMBOLSABLES | J39: 34357 | K39: 0 | L39: =+J39-K39 -> 34357 | M39: 1 | N39: 800130907 | O39: SALUD TOTAL S.A. EPS ARS | P39: 10030400 | Q39: OPERADORES | T39: 0 | U39: CONTABLE | V39: N | W39: 000000001 | X39: 0 | Y39: TACOSITI | Z39: Feb 8 2022 5:24PM | AA39: frmCON6093 | AB39: DESKTOP-5900GRN | AC39: TAMBIENTAL | AD39: Feb 8 2022 5:24PM | AF39: =YEAR(C39) -> 2021 | AG39: =TEXT(C39,"mmm") -> dic | AH39: SALUD TOTAL S.A. EPS ARS | AI39: #N/A
A40: 138020001 | B40: REINTEGRO DE INCAPACIDADES | C40: 44561 | D40: =TEXT(C40,"yyyy") -> 2021 | E40: 21 | F40: NOMINA NOVASOFT | H40: 000000001 | I40: GASTOS REEMBOLSABLES | J40: 363411 | K40: 0 | L40: =+J40-K40 -> 363411 | M40: 1 | N40: 800251440 | O40: E.P.S. SANITAS S.A. | P40: 10030400 | Q40: OPERADORES | T40: 0 | U40: CONTABLE | V40: N | W40: 000000001 | X40: 0 | Y40: TACOSITI | Z40: Feb 8 2022 5:24PM | AA40: frmCON6093 | AB40: DESKTOP-5900GRN | AC40: TAMBIENTAL | AD40: Feb 8 2022 5:24PM | AF40: =YEAR(C40) -> 2021 | AG40: =TEXT(C40,"mmm") -> dic | AH40: E.P.S. SANITAS S.A. | AI40: #N/A
A41: 138020001 | B41: REINTEGRO DE INCAPACIDADES | C41: 44561 | D41: =TEXT(C41,"yyyy") -> 2021 | E41: 21 | F41: NOMINA NOVASOFT | H41: 000000001 | I41: GASTOS REEMBOLSABLES | J41: 33912 | K41: 0 | L41: =+J41-K41 -> 33912 | M41: 1 | N41: 800251440 | O41: E.P.S. SANITAS S.A. | P41: 10030400 | Q41: OPERADORES | T41: 0 | U41: CONTABLE | V41: N | W41: 000000001 | X41: 0 | Y41: TACOSITI | Z41: Feb 8 2022 5:24PM | AA41: frmCON6093 | AB41: DESKTOP-5900GRN | AC41: TAMBIENTAL | AD41: Feb 8 2022 5:24PM | AF41: =YEAR(C41) -> 2021 | AG41: =TEXT(C41,"mmm") -> dic | AH41: E.P.S. SANITAS S.A. | AI41: #N/A
A42: 138020001 | B42: REINTEGRO DE INCAPACIDADES | C42: 44561 | D42: =TEXT(C42,"yyyy") -> 2021 | E42: 21 | F42: NOMINA NOVASOFT | H42: 000000001 | I42: GASTOS REEMBOLSABLES | J42: 345056 | K42: 0 | L42: =+J42-K42 -> 345056 | M42: 1 | N42: 830003564 | O42: E.P.S. FAMISANAR LTDA. CAFAM COLSUBSIDIO | P42: 10030400 | Q42: OPERADORES | T42: 0 | U42: CONTABLE | V42: N | W42: 000000001 | X42: 0 | Y42: TACOSITI | Z42: Feb 8 2022 5:24PM | AA42: frmCON6093 | AB42: DESKTOP-5900GRN | AC42: TAMBIENTAL | AD42: Feb 8 2022 5:24PM | AF42: =YEAR(C42) -> 2021 | AG42: =TEXT(C42,"mmm") -> dic | AH42: E.P.S. FAMISANAR LTDA. CAFAM COLSUBSIDIO | AI42: #N/A
A43: 138020001 | B43: REINTEGRO DE INCAPACIDADES | C43: 44561 | D43: =TEXT(C43,"yyyy") -> 2021 | E43: 21 | F43: NOMINA NOVASOFT | H43: 000000001 | I43: GASTOS REEMBOLSABLES | J43: 32893 | K43: 0 | L43: =+J43-K43 -> 32893 | M43: 1 | N43: 900156264 | O43: NUEVA EMPRESA PROMOTORA DE SALUD | P43: 10030400 | Q43: OPERADORES | T43: 0 | U43: CONTABLE | V43: N | W43: 000000001 | X43: 0 | Y43: TACOSITI | Z43: Feb 8 2022 5:24PM | AA43: frmCON6093 | AB43: DESKTOP-5900GRN | AC43: TAMBIENTAL | AD43: Feb 8 2022 5:24PM | AF43: =YEAR(C43) -> 2021 | AG43: =TEXT(C43,"mmm") -> dic | AH43: NUEVA EMPRESA PROMOTORA DE SALUD | AI43: #N/A
... A48: 138020001 | B48: REINTEGRO DE INCAPACIDADES | C48: 44561 | D48: =TEXT(C48,"yyyy") -> 2021 | E48: 21 | F48: NOMINA NOVASOFT | H48: 000000001 | I48: GASTOS REEMBOLSABLES | J48: 32438 | K48: 0 | L48: =+J48-K48 -> 32438 | M48: 1 | N48: 800088702 | O48: EPS SURA COMPAÑIA SURAMERICANA SERVICIOS DE SALUD | P48: 10030400 | Q48: OPERADORES | T48: 0 | U48: CONTABLE | V48: N | W48: 000000001 | X48: 0 | Y48: TACOSITI | Z48: Feb 8 2022 5:24PM | AA48: frmCON6093 | AB48: DESKTOP-5900GRN | AC48: TAMBIENTAL | AD48: Feb 8 2022 5:24PM | AF48: =YEAR(C48) -> 2021 | AG48: =TEXT(C48,"mmm") -> dic | AH48: EPS SURA COMPAÑIA SURAMERICANA SERVICIOS DE SALUD | AI48: #N/A
A49: 138020001 | B49: REINTEGRO DE INCAPACIDADES | C49: 44573 | D49: =TEXT(C49,"yyyy") -> 2022 | E49: 15 | F49: CONSIGNACIONES BANCO | H49: 000000042 | I49: NUEVA EMPRESA PROMOTORA DE SALUD:REINTEGRO INCAPACIDADES000000042 | J49: 0 | K49: 398184 | L49: =+J49-K49 -> -398184 | M49: 1 | N49: 900156264 | O49: NUEVA EMPRESA PROMOTORA DE SALUD | T49: 0 | U49: CONTABLE | V49: N | W49: 000000042 | X49: 0 | Y49: TACOTESO | Z49: Feb 24 2022 6:21PM | AA49: frmBAN607 | AB49: DESKTOP-O60S49G | AC49: TAMBIENTAL | AD49: Feb 24 2022 6:21PM | AF49: =YEAR(C49) -> 2022 | AG49: =TEXT(C49,"mmm") -> ene | AH49: NUEVA EMPRESA PROMOTORA DE SALUD | AI49: #N/A
A50: 138020001 | B50: REINTEGRO DE INCAPACIDADES | C50: 44575 | D50: =TEXT(C50,"yyyy") -> 2022 | E50: 15 | F50: CONSIGNACIONES BANCO | H50: 000000036 | I50: COOSALUD ENTIDAD PROMOTORA DE SALUD S.A:REINTEGRO INCAPACIDADES000000036 | J50: 0 | K50: 29261 | L50: =+J50-K50 -> -29261 | M50: 1 | N50: 900226715 | O50: COOSALUD ENTIDAD PROMOTORA DE SALUD S.A | T50: 0 | U50: CONTABLE | V50: N | W50: 000000036 | X50: 0 | Y50: TACOTESO | Z50: Feb 24 2022 6:07PM | AA50: frmBAN607 | AB50: DESKTOP-O60S49G | AC50: TAMBIENTAL | AD50: Feb 24 2022 6:07PM | AF50: =YEAR(C50) -> 2022 | AG50: =TEXT(C50,"mmm") -> ene | AH50: COOSALUD ENTIDAD PROMOTORA DE SALUD S.A | AI50: #N/A
A51: 138020001 | B51: REINTEGRO DE INCAPACIDADES | C51: 44575 | D51: =TEXT(C51,"yyyy") -> 2022 | E51: 15 | F51: CONSIGNACIONES BANCO | H51: 000000037 | I51: COOSALUD ENTIDAD PROMOTORA DE SALUD S.A:REINTEGRO INCAPACIDADES000000037 | J51: 0 | K51: 30285 | L51: =+J51-K51 -> -30285 | M51: 1 | N51: 900226715 | O51: COOSALUD ENTIDAD PROMOTORA DE SALUD S.A | T51: 0 | U51: CONTABLE | V51: N | W51: 000000037 | X51: 0 | Y51: TACOTESO | Z51: Feb 24 2022 6:08PM | AA51: frmBAN607 | AB51: DESKTOP-O60S49G | AC51: TAMBIENTAL | AD51: Feb 24 2022 6:08PM | AF51: =YEAR(C51) -> 2022 | AG51: =TEXT(C51,"mmm") -> ene | AH51: COOSALUD ENTIDAD PROMOTORA DE SALUD S.A | AI51: #N/A
A52: 138020001 | B52: REINTEGRO DE INCAPACIDADES | C52: 44575 | D52: =TEXT(C52,"yyyy") -> 2022 | E52: 15 | F52: CONSIGNACIONES BANCO | H52: 000000038 | I52: COOSALUD ENTIDAD PROMOTORA DE SALUD S.A:REINTEGRO INCAPACIDADES000000038 | J52: 0 | K52: 30285 | L52: =+J52-K52 -> -30285 | M52: 1 | N52: 900226715 | O52: COOSALUD ENTIDAD PROMOTORA DE SALUD S.A | T52: 0 | U52: CONTABLE | V52: N | W52: 000000038 | X52: 0 | Y52: TACOTESO | Z52: Feb 24 2022 6:11PM | AA52: frmBAN607 | AB52: DESKTOP-O60S49G | AC52: TAMBIENTAL | AD52: Feb 24 2022 6:11PM | AF52: =YEAR(C52) -> 2022 | AG52: =TEXT(C52,"mmm") -> ene | AH52: COOSALUD ENTIDAD PROMOTORA DE SALUD S.A | AI52: #N/A
A53: 138020001 | B53: REINTEGRO DE INCAPACIDADES | C53: 44575 | D53: =TEXT(C53,"yyyy") -> 2022 | E53: 15 | F53: CONSIGNACIONES BANCO | H53: 000000039 | I53: COOSALUD ENTIDAD PROMOTORA DE SALUD S.A:REINTEGRO INCAPACIDADES000000039 | J53: 0 | K53: 31032 | L53: =+J53-K53 -> -31032 | M53: 1 | N53: 900226715 | O53: COOSALUD ENTIDAD PROMOTORA DE SALUD S.A | T53: 0 | U53: CONTABLE | V53: N | W53: 000000039 | X53: 0 | Y53: TACOTESO | Z53: Feb 24 2022 6:12PM | AA53: frmBAN607 | AB53: DESKTOP-O60S49G | AC53: TAMBIENTAL | AD53: Feb 24 2022 6:12PM | AF53: =YEAR(C53) -> 2022 | AG53: =TEXT(C53,"mmm") -> ene | AH53: COOSALUD ENTIDAD PROMOTORA DE SALUD S.A | AI53: #N/A
A54: 138020001 | B54: REINTEGRO DE INCAPACIDADES | C54: 44575 | D54: =TEXT(C54,"yyyy") -> 2022 | E54: 15 | F54: CONSIGNACIONES BANCO | H54: 000000040 | I54: COOSALUD ENTIDAD PROMOTORA DE SALUD S.A:REINTEGRO INCAPACIDADES000000040 | J54: 0 | K54: 30285 | L54: =+J54-K54 -> -30285 | M54: 1 | N54: 900226715 | O54: COOSALUD ENTIDAD PROMOTORA DE SALUD S.A | T54: 0 | U54: CONTABLE | V54: N | W54: 000000040 | X54: 0 | Y54: TACOTESO | Z54: Feb 24 2022 6:17PM | AA54: frmBAN607 | AB54: DESKTOP-O60S49G | AC54: TAMBIENTAL | AD54: Feb 24 2022 6:17PM | AF54: =YEAR(C54) -> 2022 | AG54: =TEXT(C54,"mmm") -> ene | AH54: COOSALUD ENTIDAD PROMOTORA DE SALUD S.A | AI54: #N/A
A55: 138020001 | B55: REINTEGRO DE INCAPACIDADES | C55: 44575 | D55: =TEXT(C55,"yyyy") -> 2022 | E55: 15 | F55: CONSIGNACIONES BANCO | H55: 000000041 | I55: COOSALUD ENTIDAD PROMOTORA DE SALUD S.A:REINTEGRO INCAPACIDADES000000041 | J55: 0 | K55: 173891 | L55: =+J55-K55 -> -173891 | M55: 1 | N55: 900226715 | O55: COOSALUD ENTIDAD PROMOTORA DE SALUD S.A | T55: 0 | U55: CONTABLE | V55: N | W55: 000000041 | X55: 0 | Y55: TACOTESO | Z55: Feb 24 2022 6:20PM | AA55: frmBAN607 | AB55: DESKTOP-O60S49G | AC55: TAMBIENTAL | AD55: Feb 24 2022 6:20PM | AF55: =YEAR(C55) -> 2022 | AG55: =TEXT(C55,"mmm") -> ene | AH55: COOSALUD ENTIDAD PROMOTORA DE SALUD S.A | AI55: #N/A
A56: 138020001 | B56: REINTEGRO DE INCAPACIDADES | C56: 44576 | D56: =TEXT(C56,"yyyy") -> 2022 | E56: 21 | F56: NOMINA NOVASOFT | H56: 000000004 | I56: GASTOS REEMBOLSABLES | J56: 33334 | K56: 0 | L56: =+J56-K56 -> 33334 | M56: 1 | N56: 1128045753 | O56: ROJAS BUSTOS ESEIZA DEL CARMEN | P56: 10030200 | Q56: COORDINACIÓN DE OPERACIONES | T56: 0 | U56: CONTABLE | V56: N | W56: 000000004 | X56: 0 | Y56: TAAUXCON | Z56: Mar 10 2022 6:41PM | AA56: frmCON6093 | AB56: LAPTOP-18GI5NJH | AC56: TAMBIENTAL | AD56: Mar 10 2022 6:41PM | AF56: =YEAR(C56) -> 2022 | AG56: =TEXT(C56,"mmm") -> ene | AH56: SALUD TOTAL S.A. EPS ARS | AI56: SURA E.P.S.
A57: 138020001 | B57: REINTEGRO DE INCAPACIDADES | C57: 44576 | D57: =TEXT(C57,"yyyy") -> 2022 | E57: 21 | F57: NOMINA NOVASOFT | H57: 000000004 | I57: GASTOS REEMBOLSABLES | J57: 270801 | K57: 0 | L57: =+J57-K57 -> 270801 | M57: 1 | N57: 72073849 | O57: DORIAN RODRIGUEZ OSPINO | P57: 10030400 | Q57: OPERADORES | T57: 0 | U57: CONTABLE | V57: N | W57: 000000004 | X57: 0 | Y57: TAAUXCON | Z57: Mar 10 2022 6:41PM | AA57: frmCON6093 | AB57: LAPTOP-18GI5NJH | AC57: TAMBIENTAL | AD57: Mar 10 2022 6:41PM | AF57: =YEAR(C57) -> 2022 | AG57: =TEXT(C57,"mmm") -> ene | AH57: SALUD TOTAL S.A. EPS ARS | AI57: SURA E.P.S.
A58: 138020001 | B58: REINTEGRO DE INCAPACIDADES | C58: 44576 | D58: =TEXT(C58,"yyyy") -> 2022 | E58: 21 | F58: NOMINA NOVASOFT | H58: 000000004 | I58: GASTOS REEMBOLSABLES | J58: 33632 | K58: 0 | L58: =+J58-K58 -> 33632 | M58: 1 | N58: 73143163 | O58: JUAN CARLOS CABRERA TORRES | P58: 10030400 | Q58: OPERADORES | T58: 0 | U58: CONTABLE | V58: N | W58: 000000004 | X58: 0 | Y58: TAAUXCON | Z58: Mar 10 2022 6:41PM | AA58: frmCON6093 | AB58: LAPTOP-18GI5NJH | AC58: TAMBIENTAL | AD58: Mar 10 2022 6:41PM | AF58: =YEAR(C58) -> 2022 | AG58: =TEXT(C58,"mmm") -> ene | AH58: EPS SURA COMPAÑIA SURAMERICANA SERVICIOS DE SALUD | AI58: SURA E.P.S.
A59: 138020001 | B59: REINTEGRO DE INCAPACIDADES | C59: 44576 | D59: =TEXT(C59,"yyyy") -> 2022 | E59: 21 | F59: NOMINA NOVASOFT | H59: 000000004 | I59: GASTOS REEMBOLSABLES | J59: 100000 | K59: 0 | L59: =+J59-K59 -> 100000 | M59: 1 | N59: 73202722 | O59: JESUS JAVIER BELTRAN OLIVELLA | P59: 10030400 | Q59: OPERADORES | T59: 0 | U59: CONTABLE | V59: N | W59: 000000004 | X59: 0 | Y59: TAAUXCON | Z59: Mar 10 2022 6:41PM | AA59: frmCON6093 | AB59: LAPTOP-18GI5NJH | AC59: TAMBIENTAL | AD59: Mar 10 2022 6:41PM | AF59: =YEAR(C59) -> 2022 | AG59: =TEXT(C59,"mmm") -> ene | AH59: SALUD TOTAL S.A. EPS ARS | AI59: SURA E.P.S.
A60: 138020001 | B60: REINTEGRO DE INCAPACIDADES | C60: 44576 | D60: =TEXT(C60,"yyyy") -> 2022 | E60: 21 | F60: NOMINA NOVASOFT | H60: 000000004 | I60: GASTOS REEMBOLSABLES | J60: 35814 | K60: 0 | L60: =+J60-K60 -> 35814 | M60: 1 | N60: 7918997 | O60: MOISES CASTILLA GUTIERREZ | P60: 10030400 | Q60: OPERADORES | T60: 0 | U60: CONTABLE | V60: N | W60: 000000004 | X60: 0 | Y60: TAAUXCON | Z60: Mar 10 2022 6:41PM | AA60: frmCON6093 | AB60: LAPTOP-18GI5NJH | AC60: TAMBIENTAL | AD60: Mar 10 2022 6:41PM | AF60: =YEAR(C60) -> 2022 | AG60: =TEXT(C60,"mmm") -> ene | AH60: SALUD TOTAL S.A. EPS ARS | AI60: SURA E.P.S.
A61: 138020001 | B61: REINTEGRO DE INCAPACIDADES | C61: 44576 | D61: =TEXT(C61,"yyyy") -> 2022 | E61: 21 | F61: NOMINA NOVASOFT | H61: 000000004 | I61: GASTOS REEMBOLSABLES | J61: 33334 | K61: 0 | L61: =+J61-K61 -> 33334 | M61: 1 | N61: 9288712 | O61: RAFAEL DE JESUS PUELLO HUETO | P61: 10030400 | Q61: OPERADORES | T61: 0 | U61: CONTABLE | V61: N | W61: 000000004 | X61: 0 | Y61: TAAUXCON | Z61: Mar 10 2022 6:41PM | AA61: frmCON6093 | AB61: LAPTOP-18GI5NJH | AC61: TAMBIENTAL | AD61: Mar 10 2022 6:41PM | AF61: =YEAR(C61) -> 2022 | AG61: =TEXT(C61,"mmm") -> ene | AH61: SALUD TOTAL S.A. EPS ARS | AI61: SURA E.P.S.
A62: 138020001 | B62: REINTEGRO DE INCAPACIDADES | C62: 44576 | D62: =TEXT(C62,"yyyy") -> 2022 | E62: 21 | F62: NOMINA NOVASOFT | H62: 000000004 | I62: GASTOS REEMBOLSABLES | J62: 33334 | K62: 0 | L62: =+J62-K62 -> 33334 | M62: 1 | N62: 1002059942 | O62: WILSON RAFAEL SIMANCAS MARTINEZ | P62: 10030400 | Q62: OPERADORES | T62: 0 | U62: CONTABLE | V62: N | W62: 000000004 | X62: 0 | Y62: TAAUXCON | Z62: Mar 10 2022 6:41PM | AA62: frmCON6093 | AB62: LAPTOP-18GI5NJH | AC62: TAMBIENTAL | AD62: Mar 10 2022 6:41PM | AF62: =YEAR(C62) -> 2022 | AG62: =TEXT(C62,"mmm") -> ene | AH62: COOSALUD ENTIDAD PROMOTORA DE SALUD S.A | AI62: SALUD TOTAL E.P.S.
A63: 138020001 | B63: REINTEGRO DE INCAPACIDADES | C63: 44576 | D63: =TEXT(C63,"yyyy") -> 2022 | E63: 21 | F63: NOMINA NOVASOFT | H63: 000000004 | I63: GASTOS REEMBOLSABLES | J63: 500000 | K63: 0 | L63: =+J63-K63 -> 500000 | M63: 1 | N63: 1047370459 | O63: JOSE AUGUSTO ARZUZA MARRUGO | P63: 10030400 | Q63: OPERADORES | T63: 0 | U63: CONTABLE | V63: N | W63: 000000004 | X63: 0 | Y63: TAAUXCON | Z63: Mar 10 2022 6:41PM | AA63: frmCON6093 | AB63: LAPTOP-18GI5NJH | AC63: TAMBIENTAL | AD63: Mar 10 2022 6:41PM | AF63: =YEAR(C63) -> 2022 | AG63: =TEXT(C63,"mmm") -> ene | AH63: COOSALUD ENTIDAD PROMOTORA DE SALUD S.A | AI63: SALUD TOTAL E.P.S.
A64: 138020001 | B64: REINTEGRO DE INCAPACIDADES | C64: 44576 | D64: =TEXT(C64,"yyyy") -> 2022 | E64: 21 | F64: NOMINA NOVASOFT | H64: 000000004 | I64: GASTOS REEMBOLSABLES | J64: 37832 | K64: 0 | L64: =+J64-K64 -> 37832 | M64: 1 | N64: 1047364807 | O64: ALEJANDRO LUIS PEREZ PEDROZA | P64: 10030400 | Q64: OPERADORES | T64: 0 | U64: CONTABLE | V64: N | W64: 000000004 | X64: 0 | Y64: TAAUXCON | Z64: Mar 10 2022 6:41PM | AA64: frmCON6093 | AB64: LAPTOP-18GI5NJH | AC64: TAMBIENTAL | AD64: Mar 10 2022 6:41PM | AF64: =YEAR(C64) -> 2022 | AG64: =TEXT(C64,"mmm") -> ene | AH64: COOSALUD ENTIDAD PROMOTORA DE SALUD S.A | AI64: SANITAS E.P.S
A65: 138020001 | B65: REINTEGRO DE INCAPACIDADES | C65: 44576 | D65: =TEXT(C65,"yyyy") -> 2022 | E65: 21 | F65: NOMINA NOVASOFT | H65: 000000004 | I65: GASTOS REEMBOLSABLES | J65: 35677 | K65: 0 | L65: =+J65-K65 -> 35677 | M65: 1 | N65: 1049532983 | O65: PEDRO MANUEL MUÑIZ PADILLA | P65: 10030400 | Q65: OPERADORES | T65: 0 | U65: CONTABLE | V65: N | W65: 000000004 | X65: 0 | Y65: TAAUXCON | Z65: Mar 10 2022 6:41PM | AA65: frmCON6093 | AB65: LAPTOP-18GI5NJH | AC65: TAMBIENTAL | AD65: Mar 10 2022 6:41PM | AF65: =YEAR(C65) -> 2022 | AG65: =TEXT(C65,"mmm") -> ene | AH65: COOSALUD ENTIDAD PROMOTORA DE SALUD S.A | AI65: COOSALUD ESS EPS -S
A66: 138020001 | B66: REINTEGRO DE INCAPACIDADES | C66: 44576 | D66: =TEXT(C66,"yyyy") -> 2022 | E66: 21 | F66: NOMINA NOVASOFT | H66: 000000004 | I66: GASTOS REEMBOLSABLES | J66: 33856 | K66: 0 | L66: =+J66-K66 -> 33856 | M66: 1 | N66: 1137220216 | O66: TONNY JAYR ESTREMOR SALCEDO | P66: 10030400 | Q66: OPERADORES | T66: 0 | U66: CONTABLE | V66: N | W66: 000000004 | X66: 0 | Y66: TAAUXCON | Z66: Mar 10 2022 6:41PM | AA66: frmCON6093 | AB66: LAPTOP-18GI5NJH | AC66: TAMBIENTAL | AD66: Mar 10 2022 6:41PM | AF66: =YEAR(C66) -> 2022 | AG66: =TEXT(C66,"mmm") -> ene | AH66: COOSALUD ENTIDAD PROMOTORA DE SALUD S.A | AI66: SANITAS E.P.S
A67: 138020001 | B67: REINTEGRO DE INCAPACIDADES | C67: 44576 | D67: =TEXT(C67,"yyyy") -> 2022 | E67: 21 | F67: NOMINA NOVASOFT | H67: 000000004 | I67: GASTOS REEMBOLSABLES | J67: 500000 | K67: 0 | L67: =+J67-K67 -> 500000 | M67: 1 | N67: 73103777 | O67: RAMON CORREA GARCIA | P67: 10030400 | Q67: OPERADORES | T67: 0 | U67: CONTABLE | V67: N | W67: 000000004 | X67: 0 | Y67: TAAUXCON | Z67: Mar 10 2022 6:41PM | AA67: frmCON6093 | AB67: LAPTOP-18GI5NJH | AC67: TAMBIENTAL | AD67: Mar 10 2022 6:41PM | AF67: =YEAR(C67) -> 2022 | AG67: =TEXT(C67,"mmm") -> ene | AH67: SALUD TOTAL S.A. EPS ARS | AI67: SANITAS E.P.S
... A81: 138020001 | B81: REINTEGRO DE INCAPACIDADES | C81: 44576 | D81: =TEXT(C81,"yyyy") -> 2022 | E81: 21 | F81: NOMINA NOVASOFT | H81: 000000004 | I81: GASTOS REEMBOLSABLES | J81: 233334 | K81: 0 | L81: =+J81-K81 -> 233334 | M81: 1 | N81: 1047495774 | O81: LUVIS STELLA ZARZA REYES | P81: 10050400 | Q81: SALUD OCUPACIONAL | T81: 0 | U81: CONTABLE | V81: N | W81: 000000004 | X81: 0 | Y81: TAAUXCON | Z81: Mar 10 2022 6:41PM | AA81: frmCON6093 | AB81: LAPTOP-18GI5NJH | AC81: TAMBIENTAL | AD81: Mar 10 2022 6:41PM | AF81: =YEAR(C81) -> 2022 | AG81: =TEXT(C81,"mmm") -> ene | AH81: BANCOLOMBIA | AI81: SALUD TOTAL E.P.S.
A82: 138020001 | B82: REINTEGRO DE INCAPACIDADES | C82: 44581 | D82: =TEXT(C82,"yyyy") -> 2022 | E82: 15 | F82: CONSIGNACIONES BANCO | H82: 000000033 | I82: SALUD TOTAL S.A. EPS ARS:REINTEGRO INCAPACIDADES000000033 | J82: 0 | K82: 31475 | L82: =+J82-K82 -> -31475 | M82: 1 | N82: 800130907 | O82: SALUD TOTAL S.A. EPS ARS | T82: 0 | U82: CONTABLE | V82: N | W82: 000000033 | X82: 0 | Y82: TACOTESO | Z82: Feb 24 2022 6:04PM | AA82: frmBAN607 | AB82: DESKTOP-O60S49G | AC82: TAMBIENTAL | AD82: Feb 24 2022 6:04PM | AF82: =YEAR(C82) -> 2022 | AG82: =TEXT(C82,"mmm") -> ene | AH82: BANCOLOMBIA | AI82: #N/A
A83: 138020001 | B83: REINTEGRO DE INCAPACIDADES | C83: 44581 | D83: =TEXT(C83,"yyyy") -> 2022 | E83: 15 | F83: CONSIGNACIONES BANCO | H83: 000000034 | I83: SALUD TOTAL S.A. EPS ARS:REINTEGRO INCAPACIDADES000000034 | J83: 0 | K83: 423976 | L83: =+J83-K83 -> -423976 | M83: 1 | N83: 800130907 | O83: SALUD TOTAL S.A. EPS ARS | T83: 0 | U83: CONTABLE | V83: N | W83: 000000034 | X83: 0 | Y83: TACOTESO | Z83: Feb 24 2022 6:05PM | AA83: frmBAN607 | AB83: DESKTOP-O60S49G | AC83: TAMBIENTAL | AD83: Feb 24 2022 6:05PM | AF83: =YEAR(C83) -> 2022 | AG83: =TEXT(C83,"mmm") -> ene | AH83: BANCOLOMBIA | AI83: #N/A
A84: 138020001 | B84: REINTEGRO DE INCAPACIDADES | C84: 44581 | D84: =TEXT(C84,"yyyy") -> 2022 | E84: 15 | F84: CONSIGNACIONES BANCO | H84: 000000035 | I84: EPS SURA COMPAÑIA SURAMERICANA SERVICIOS DE SALUD:REINTEGRO INCAPACIDADES000000035 | J84: 0 | K84: 30284 | L84: =+J84-K84 -> -30284 | M84: 1 | N84: 800088702 | O84: EPS SURA COMPAÑIA SURAMERICANA SERVICIOS DE SALUD | T84: 0 | U84: CONTABLE | V84: N | W84: 000000035 | X84: 0 | Y84: TACOTESO | Z84: Feb 24 2022 6:06PM | AA84: frmBAN607 | AB84: DESKTOP-O60S49G | AC84: TAMBIENTAL | AD84: Feb 24 2022 6:06PM | AF84: =YEAR(C84) -> 2022 | AG84: =TEXT(C84,"mmm") -> ene | AH84: EPS SURA COMPAÑIA SURAMERICANA SERVICIOS DE SALUD | AI84: #N/A
A85: 138020001 | B85: REINTEGRO DE INCAPACIDADES | C85: 44585 | D85: =TEXT(C85,"yyyy") -> 2022 | E85: 15 | F85: CONSIGNACIONES BANCO | H85: 000000025 | I85: SALUD TOTAL S.A. EPS ARS:REINTEGRO INCAPACIDADES000000025 | J85: 0 | K85: 33623 | L85: =+J85-K85 -> -33623 | M85: 1 | N85: 800130907 | O85: SALUD TOTAL S.A. EPS ARS | T85: 0 | U85: CONTABLE | V85: N | W85: 000000025 | X85: 0 | Y85: TACOTESO | Z85: Feb 24 2022 5:52PM | AA85: frmBAN607 | AB85: DESKTOP-O60S49G | AC85: TAMBIENTAL | AD85: Feb 24 2022 5:52PM | AF85: =YEAR(C85) -> 2022 | AG85: =TEXT(C85,"mmm") -> ene | AH85: SALUD TOTAL S.A. EPS ARS | AI85: #N/A
A86: 138020001 | B86: REINTEGRO DE INCAPACIDADES | C86: 44585 | D86: =TEXT(C86,"yyyy") -> 2022 | E86: 15 | F86: CONSIGNACIONES BANCO | H86: 000000026 | I86: SALUD TOTAL S.A. EPS ARS:REINTEGRO INCAPACIDADES000000026 | J86: 0 | K86: 87781 | L86: =+J86-K86 -> -87781 | M86: 1 | N86: 800130907 | O86: SALUD TOTAL S.A. EPS ARS | T86: 0 | U86: CONTABLE | V86: N | W86: 000000026 | X86: 0 | Y86: TACOTESO | Z86: Feb 24 2022 5:55PM | AA86: frmBAN607 | AB86: DESKTOP-O60S49G | AC86: TAMBIENTAL | AD86: Feb 24 2022 5:55PM | AF86: =YEAR(C86) -> 2022 | AG86: =TEXT(C86,"mmm") -> ene | AH86: SALUD TOTAL S.A. EPS ARS | AI86: #N/A
A87: 138020001 | B87: REINTEGRO DE INCAPACIDADES | C87: 44585 | D87: =TEXT(C87,"yyyy") -> 2022 | E87: 15 | F87: CONSIGNACIONES BANCO | H87: 000000027 | I87: SALUD TOTAL S.A. EPS ARS:REINTEGRO INCAPACIDADES000000027 | J87: 0 | K87: 29261 | L87: =+J87-K87 -> -29261 | M87: 1 | N87: 800130907 | O87: SALUD TOTAL S.A. EPS ARS | T87: 0 | U87: CONTABLE | V87: N | W87: 000000027 | X87: 0 | Y87: TACOTESO | Z87: Feb 24 2022 5:56PM | AA87: frmBAN607 | AB87: DESKTOP-O60S49G | AC87: TAMBIENTAL | AD87: Feb 24 2022 5:56PM | AF87: =YEAR(C87) -> 2022 | AG87: =TEXT(C87,"mmm") -> ene | AH87: ASOCIACION MUTUAL SER EMPRESA SOLIDARIA | AI87: #N/A
A88: 138020001 | B88: REINTEGRO DE INCAPACIDADES | C88: 44585 | D88: =TEXT(C88,"yyyy") -> 2022 | E88: 15 | F88: CONSIGNACIONES BANCO | H88: 000000028 | I88: COOSALUD ENTIDAD PROMOTORA DE SALUD S.A:REINTEGRO INCAPACIDADES000000028 | J88: 0 | K88: 36615 | L88: =+J88-K88 -> -36615 | M88: 1 | N88: 900226715 | O88: COOSALUD ENTIDAD PROMOTORA DE SALUD S.A | T88: 0 | U88: CONTABLE | V88: N | W88: 000000028 | X88: 0 | Y88: TACOTESO | Z88: Feb 24 2022 5:57PM | AA88: frmBAN607 | AB88: DESKTOP-O60S49G | AC88: TAMBIENTAL | AD88: Feb 24 2022 5:57PM | AF88: =YEAR(C88) -> 2022 | AG88: =TEXT(C88,"mmm") -> ene | AH88: SALUD TOTAL S.A. EPS ARS | AI88: #N/A
A89: 138020001 | B89: REINTEGRO DE INCAPACIDADES | C89: 44585 | D89: =TEXT(C89,"yyyy") -> 2022 | E89: 15 | F89: CONSIGNACIONES BANCO | H89: 000000029 | I89: COOSALUD ENTIDAD PROMOTORA DE SALUD S.A:REINTEGRO INCAPACIDADES000000029 | J89: 0 | K89: 29261 | L89: =+J89-K89 -> -29261 | M89: 1 | N89: 900226715 | O89: COOSALUD ENTIDAD PROMOTORA DE SALUD S.A | T89: 0 | U89: CONTABLE | V89: N | W89: 000000029 | X89: 0 | Y89: TACOTESO | Z89: Feb 24 2022 5:59PM | AA89: frmBAN607 | AB89: DESKTOP-O60S49G | AC89: TAMBIENTAL | AD89: Feb 24 2022 5:59PM | AF89: =YEAR(C89) -> 2022 | AG89: =TEXT(C89,"mmm") -> ene | AH89: NUEVA EMPRESA PROMOTORA DE SALUD | AI89: #N/A
A90: 138020001 | B90: REINTEGRO DE INCAPACIDADES | C90: 44585 | D90: =TEXT(C90,"yyyy") -> 2022 | E90: 15 | F90: CONSIGNACIONES BANCO | H90: 000000030 | I90: COOSALUD ENTIDAD PROMOTORA DE SALUD S.A:REINTEGRO INCAPACIDADES000000030 | J90: 0 | K90: 175561 | L90: =+J90-K90 -> -175561 | M90: 1 | N90: 900226715 | O90: COOSALUD ENTIDAD PROMOTORA DE SALUD S.A | T90: 0 | U90: CONTABLE | V90: N | W90: 000000030 | X90: 0 | Y90: TACOTESO | Z90: Feb 24 2022 6:00PM | AA90: frmBAN607 | AB90: DESKTOP-O60S49G | AC90: TAMBIENTAL | AD90: Feb 24 2022 6:00PM | AF90: =YEAR(C90) -> 2022 | AG90: =TEXT(C90,"mmm") -> ene | AH90: E.P.S. FAMISANAR LTDA. CAFAM COLSUBSIDIO | AI90: #N/A
A91: 138020001 | B91: REINTEGRO DE INCAPACIDADES | C91: 44585 | D91: =TEXT(C91,"yyyy") -> 2022 | E91: 15 | F91: CONSIGNACIONES BANCO | H91: 000000031 | I91: COOSALUD ENTIDAD PROMOTORA DE SALUD S.A:REINTEGRO INCAPACIDADES000000031 | J91: 0 | K91: 46895 | L91: =+J91-K91 -> -46895 | M91: 1 | N91: 900226715 | O91: COOSALUD ENTIDAD PROMOTORA DE SALUD S.A | T91: 0 | U91: CONTABLE | V91: N | W91: 000000031 | X91: 0 | Y91: TACOTESO | Z91: Feb 24 2022 6:01PM | AA91: frmBAN607 | AB91: DESKTOP-O60S49G | AC91: TAMBIENTAL | AD91: Feb 24 2022 6:01PM | AF91: =YEAR(C91) -> 2022 | AG91: =TEXT(C91,"mmm") -> ene | AH91: SALUD TOTAL S.A. EPS ARS | AI91: #N/A
A92: 138020001 | B92: REINTEGRO DE INCAPACIDADES | C92: 44585 | D92: =TEXT(C92,"yyyy") -> 2022 | E92: 15 | F92: CONSIGNACIONES BANCO | H92: 000000032 | I92: COOSALUD ENTIDAD PROMOTORA DE SALUD S.A:REINTEGRO INCAPACIDADES000000032 | J92: 0 | K92: 34280 | L92: =+J92-K92 -> -34280 | M92: 1 | N92: 900226715 | O92: COOSALUD ENTIDAD PROMOTORA DE SALUD S.A | T92: 0 | U92: CONTABLE | V92: N | W92: 000000032 | X92: 0 | Y92: TACOTESO | Z92: Feb 24 2022 6:03PM | AA92: frmBAN607 | AB92: DESKTOP-O60S49G | AC92: TAMBIENTAL | AD92: Feb 24 2022 6:03PM | AF92: =YEAR(C92) -> 2022 | AG92: =TEXT(C92,"mmm") -> ene | AH92: SALUD TOTAL S.A. EPS ARS | AI92: #N/A
A93: 138020001 | B93: REINTEGRO DE INCAPACIDADES | C93: 44586 | D93: =TEXT(C93,"yyyy") -> 2022 | E93: 15 | F93: CONSIGNACIONES BANCO | H93: 000000024 | I93: SALUD TOTAL S.A. EPS ARS:REINTEGRO INCAPACIDADES000000024 | J93: 0 | K93: 371086 | L93: =+J93-K93 -> -371086 | M93: 1 | N93: 800130907 | O93: SALUD TOTAL S.A. EPS ARS | T93: 0 | U93: CONTABLE | V93: N | W93: 000000024 | X93: 0 | Y93: TACOTESO | Z93: Feb 24 2022 5:50PM | AA93: frmBAN607 | AB93: DESKTOP-O60S49G | AC93: TAMBIENTAL | AD93: Feb 24 2022 5:50PM | AF93: =YEAR(C93) -> 2022 | AG93: =TEXT(C93,"mmm") -> ene | AH93: EPS SURA COMPAÑIA SURAMERICANA SERVICIOS DE SALUD | AI93: #N/A
A94: 138020001 | B94: REINTEGRO DE INCAPACIDADES | C94: 44588 | D94: =TEXT(C94,"yyyy") -> 2022 | E94: 15 | F94: CONSIGNACIONES BANCO | H94: 000000023 | I94: SALUD TOTAL S.A. EPS ARS:REINTEGRO INCAPACIDADES000000023 | J94: 0 | K94: 969509 | L94: =+J94-K94 -> -969509 | M94: 1 | N94: 800130907 | O94: SALUD TOTAL S.A. EPS ARS | T94: 0 | U94: CONTABLE | V94: N | W94: 000000023 | X94: 0 | Y94: TACOTESO | Z94: Feb 24 2022 5:49PM | AA94: frmBAN607 | AB94: DESKTOP-O60S49G | AC94: TAMBIENTAL | AD94: Feb 24 2022 5:49PM | AF94: =YEAR(C94) -> 2022 | AG94: =TEXT(C94,"mmm") -> ene | AH94: NUEVA EMPRESA PROMOTORA DE SALUD | AI94: #N/A
A95: 138020001 | B95: REINTEGRO DE INCAPACIDADES | C95: 44592 | D95: =TEXT(C95,"yyyy") -> 2022 | E95: 21 | F95: NOMINA NOVASOFT | H95: 000000005 | I95: GASTOS REEMBOLSABLES | J95: 306355 | K95: 0 | L95: =+J95-K95 -> 306355 | M95: 1 | N95: 1047447036 | O95: LAURA ESPITALETA NARVAEZ | P95: 10000100 | Q95: JURIDICA | T95: 0 | U95: CONTABLE | V95: N | W95: 000000005 | X95: 0 | Y95: TAAUXCON | Z95: Mar 10 2022 6:45PM | AA95: frmCON6093 | AB95: LAPTOP-18GI5NJH | AC95: TAMBIENTAL | AD95: Mar 10 2022 6:45PM | AF95: =YEAR(C95) -> 2022 | AG95: =TEXT(C95,"mmm") -> ene | AH95: ASOCIACION MUTUAL SER EMPRESA SOLIDARIA | AI95: ARL SURA
A96: 138020001 | B96: REINTEGRO DE INCAPACIDADES | C96: 44592 | D96: =TEXT(C96,"yyyy") -> 2022 | E96: 21 | F96: NOMINA NOVASOFT | H96: 000000005 | I96: GASTOS REEMBOLSABLES | J96: 270801 | K96: 0 | L96: =+J96-K96 -> 270801 | M96: 1 | N96: 72073849 | O96: DORIAN RODRIGUEZ OSPINO | P96: 10030400 | Q96: OPERADORES | T96: 0 | U96: CONTABLE | V96: N | W96: 000000005 | X96: 0 | Y96: TAAUXCON | Z96: Mar 10 2022 6:45PM | AA96: frmCON6093 | AB96: LAPTOP-18GI5NJH | AC96: TAMBIENTAL | AD96: Mar 10 2022 6:45PM | AF96: =YEAR(C96) -> 2022 | AG96: =TEXT(C96,"mmm") -> ene | AH96: SALUD TOTAL S.A. EPS ARS | AI96: SURA E.P.S.
A97: 138020001 | B97: REINTEGRO DE INCAPACIDADES | C97: 44592 | D97: =TEXT(C97,"yyyy") -> 2022 | E97: 21 | F97: NOMINA NOVASOFT | H97: 000000005 | I97: GASTOS REEMBOLSABLES | J97: 33334 | K97: 0 | L97: =+J97-K97 -> 33334 | M97: 1 | N97: 73130242 | O97: RAYMUNDO SANJUAN MERCADO | P97: 10030400 | Q97: OPERADORES | T97: 0 | U97: CONTABLE | V97: N | W97: 000000005 | X97: 0 | Y97: TAAUXCON | Z97: Mar 10 2022 6:45PM | AA97: frmCON6093 | AB97: LAPTOP-18GI5NJH | AC97: TAMBIENTAL | AD97: Mar 10 2022 6:45PM | AF97: =YEAR(C97) -> 2022 | AG97: =TEXT(C97,"mmm") -> ene | AH97: E.P.S. FAMISANAR LTDA. CAFAM COLSUBSIDIO | AI97: SURA E.P.S.
A98: 138020001 | B98: REINTEGRO DE INCAPACIDADES | C98: 44592 | D98: =TEXT(C98,"yyyy") -> 2022 | E98: 21 | F98: NOMINA NOVASOFT | H98: 000000005 | I98: GASTOS REEMBOLSABLES | J98: 166667 | K98: 0 | L98: =+J98-K98 -> 166667 | M98: 1 | N98: 1047370459 | O98: JOSE AUGUSTO ARZUZA MARRUGO | P98: 10030400 | Q98: OPERADORES | T98: 0 | U98: CONTABLE | V98: N | W98: 000000005 | X98: 0 | Y98: TAAUXCON | Z98: Mar 10 2022 6:45PM | AA98: frmCON6093 | AB98: LAPTOP-18GI5NJH | AC98: TAMBIENTAL | AD98: Mar 10 2022 6:45PM | AF98: =YEAR(C98) -> 2022 | AG98: =TEXT(C98,"mmm") -> ene | AH98: E.P.S. FAMISANAR LTDA. CAFAM COLSUBSIDIO | AI98: SALUD TOTAL E.P.S.
A99: 138020001 | B99: REINTEGRO DE INCAPACIDADES | C99: 44592 | D99: =TEXT(C99,"yyyy") -> 2022 | E99: 21 | F99: NOMINA NOVASOFT | H99: 000000005 | I99: GASTOS REEMBOLSABLES | J99: 33334 | K99: 0 | L99: =+J99-K99 -> 33334 | M99: 1 | N99: 73121602 | O99: ELKIN YOUSEF CHAR NEGRETE | P99: 10030400 | Q99: OPERADORES | T99: 0 | U99: CONTABLE | V99: N | W99: 000000005 | X99: 0 | Y99: TAAUXCON | Z99: Mar 10 2022 6:45PM | AA99: frmCON6093 | AB99: LAPTOP-18GI5NJH | AC99: TAMBIENTAL | AD99: Mar 10 2022 6:45PM | AF99: =YEAR(C99) -> 2022 | AG99: =TEXT(C99,"mmm") -> ene | AH99: SALUD TOTAL S.A. EPS ARS | AI99: SALUD TOTAL E.P.S.
A100: 138020001 | B100: REINTEGRO DE INCAPACIDADES | C100: 44592 | D100: =TEXT(C100,"yyyy") -> 2022 | E100: 21 | F100: NOMINA NOVASOFT | H100: 000000005 | I100: GASTOS REEMBOLSABLES | J100: 101621 | K100: 0 | L100: =+J100-K100 -> 101621 | M100: 1 | N100: 73186816 | O100: JAMER GUSTAVO BENITEZ CHICA | P100: 10030400 | Q100: OPERADORES | T100: 0 | U100: CONTABLE | V100: N | W100: 000000005 | X100: 0 | Y100: TAAUXCON | Z100: Mar 10 2022 6:45PM | AA100: frmCON6093 | AB100: LAPTOP-18GI5NJH | AC100: TAMBIENTAL | AD100: Mar 10 2022 6:45PM | AF100: =YEAR(C100) -> 2022 | AG100: =TEXT(C100,"mmm") -> ene | AH100: NUEVA EMPRESA PROMOTORA DE SALUD | AI100: SALUD TOTAL E.P.S.
A101: 138020001 | B101: REINTEGRO DE INCAPACIDADES | C101: 44592 | D101: =TEXT(C101,"yyyy") -> 2022 | E101: 21 | F101: NOMINA NOVASOFT | H101: 000000005 | I101: GASTOS REEMBOLSABLES | J101: 33476 | K101: 0 | L101: =+J101-K101 -> 33476 | M101: 1 | N101: 73575088 | O101: WILLIAN EMILIO TIRADO SILVA | P101: 10030400 | Q101: OPERADORES | T101: 0 | U101: CONTABLE | V101: N | W101: 000000005 | X101: 0 | Y101: TAAUXCON | Z101: Mar 10 2022 6:45PM | AA101: frmCON6093 | AB101: LAPTOP-18GI5NJH | AC101: TAMBIENTAL | AD101: Mar 10 2022 6:45PM | AF101: =YEAR(C101) -> 2022 | AG101: =TEXT(C101,"mmm") -> ene | AH101: SALUD TOTAL S.A. EPS ARS | AI101: SALUD TOTAL E.P.S.
A102: 138020001 | B102: REINTEGRO DE INCAPACIDADES | C102: 44592 | D102: =TEXT(C102,"yyyy") -> 2022 | E102: 21 | F102: NOMINA NOVASOFT | H102: 000000005 | I102: GASTOS REEMBOLSABLES | J102: 33334 | K102: 0 | L102: =+J102-K102 -> 33334 | M102: 1 | N102: 9186477 | O102: AVILA JHONATAN ALZUZAR DE | P102: 10030400 | Q102: OPERADORES | T102: 0 | U102: CONTABLE | V102: N | W102: 000000005 | X102: 0 | Y102: TAAUXCON | Z102: Mar 10 2022 6:45PM | AA102: frmCON6093 | AB102: LAPTOP-18GI5NJH | AC102: TAMBIENTAL | AD102: Mar 10 2022 6:45PM | AF102: =YEAR(C102) -> 2022 | AG102: =TEXT(C102,"mmm") -> ene | AH102: E.P.S. FAMISANAR LTDA. CAFAM COLSUBSIDIO | AI102: SALUD TOTAL E.P.S.
A103: 138020001 | B103: REINTEGRO DE INCAPACIDADES | C103: 44592 | D103: =TEXT(C103,"yyyy") -> 2022 | E103: 21 | F103: NOMINA NOVASOFT | H103: 000000005 | I103: GASTOS REEMBOLSABLES | J103: 249742 | K103: 0 | L103: =+J103-K103 -> 249742 | M103: 1 | N103: 1049532983 | O103: PEDRO MANUEL MUÑIZ PADILLA | P103: 10030400 | Q103: OPERADORES | T103: 0 | U103: CONTABLE | V103: N | W103: 000000005 | X103: 0 | Y103: TAAUXCON | Z103: Mar 10 2022 6:45PM | AA103: frmCON6093 | AB103: LAPTOP-18GI5NJH | AC103: TAMBIENTAL | AD103: Mar 10 2022 6:45PM | AF103: =YEAR(C103) -> 2022 | AG103: =TEXT(C103,"mmm") -> ene | AH103: E.P.S. FAMISANAR LTDA. CAFAM COLSUBSIDIO | AI103: COOSALUD ESS EPS -S
A104: 138020001 | B104: REINTEGRO DE INCAPACIDADES | C104: 44592 | D104: =TEXT(C104,"yyyy") -> 2022 | E104: 21 | F104: NOMINA NOVASOFT | H104: 000000005 | I104: GASTOS REEMBOLSABLES | J104: 266668 | K104: 0 | L104: =+J104-K104 -> 266668 | M104: 1 | N104: 73103777 | O104: RAMON CORREA GARCIA | P104: 10030400 | Q104: OPERADORES | T104: 0 | U104: CONTABLE | V104: N | W104: 000000005 | X104: 0 | Y104: TAAUXCON | Z104: Mar 10 2022 6:45PM | AA104: frmCON6093 | AB104: LAPTOP-18GI5NJH | AC104: TAMBIENTAL | AD104: Mar 10 2022 6:45PM | AF104: =YEAR(C104) -> 2022 | AG104: =TEXT(C104,"mmm") -> ene | AH104: ASOCIACION MUTUAL SER EMPRESA SOLIDARIA | AI104: SANITAS E.P.S
A105: 138020001 | B105: REINTEGRO DE INCAPACIDADES | C105: 44592 | D105: =TEXT(C105,"yyyy") -> 2022 | E105: 21 | F105: NOMINA NOVASOFT | H105: 000000005 | I105: GASTOS REEMBOLSABLES | J105: 35019 | K105: 0 | L105: =+J105-K105 -> 35019 | M105: 1 | N105: 92031290 | O105: JORGE DAVID BOLAÑO VILLAMIL | P105: 10030400 | Q105: OPERADORES | T105: 0 | U105: CONTABLE | V105: N | W105: 000000005 | X105: 0 | Y105: TAAUXCON | Z105: Mar 10 2022 6:45PM | AA105: frmCON6093 | AB105: LAPTOP-18GI5NJH | AC105: TAMBIENTAL | AD105: Mar 10 2022 6:45PM | AF105: =YEAR(C105) -> 2022 | AG105: =TEXT(C105,"mmm") -> ene | AH105: SALUD TOTAL S.A. EPS ARS | AI105: COOMEVA E.P.S
A106: 138020001 | B106: REINTEGRO DE INCAPACIDADES | C106: 44592 | D106: =TEXT(C106,"yyyy") -> 2022 | E106: 21 | F106: NOMINA NOVASOFT | H106: 000000005 | I106: GASTOS REEMBOLSABLES | J106: 327939 | K106: 0 | L106: =+J106-K106 -> 327939 | M106: 1 | N106: 10885706 | O106: RAFAEL ENRIQUE CUELLO LORA | P106: 10030400 | Q106: OPERADORES | T106: 0 | U106: CONTABLE | V106: N | W106: 000000005 | X106: 0 | Y106: TAAUXCON | Z106: Mar 10 2022 6:45PM | AA106: frmCON6093 | AB106: LAPTOP-18GI5NJH | AC106: TAMBIENTAL | AD106: Mar 10 2022 6:45PM | AF106: =YEAR(C106) -> 2022 | AG106: =TEXT(C106,"mmm") -> ene | AH106: NUEVA EMPRESA PROMOTORA DE SALUD | AI106: COOMEVA E.P.S
... A109: 138020001 | B109: REINTEGRO DE INCAPACIDADES | C109: 44592 | D109: =TEXT(C109,"yyyy") -> 2022 | E109: 21 | F109: NOMINA NOVASOFT | H109: 000000005 | I109: GASTOS REEMBOLSABLES | J109: 103074 | K109: 0 | L109: =+J109-K109 -> 103074 | M109: 1 | N109: 12595533 | O109: LUIS ALFONSO MEDINA OCHOA | P109: 10030400 | Q109: OPERADORES | T109: 0 | U109: CONTABLE | V109: N | W109: 000000005 | X109: 0 | Y109: TAAUXCON | Z109: Mar 10 2022 6:45PM | AA109: frmCON6093 | AB109: LAPTOP-18GI5NJH | AC109: TAMBIENTAL | AD109: Mar 10 2022 6:45PM | AF109: =YEAR(C109) -> 2022 | AG109: =TEXT(C109,"mmm") -> ene | AH109: EPS SURA COMPAÑIA SURAMERICANA SERVICIOS DE SALUD | AI109: NUEVA E.P.S
A110: 138020001 | B110: REINTEGRO DE INCAPACIDADES | C110: 44595 | D110: =TEXT(C110,"yyyy") -> 2022 | E110: 15 | F110: CONSIGNACIONES BANCO | H110: 000000056 | I110: EPS SURA COMPAÑIA SURAMERICANA SERVICIOS DE SALUD:Reintegro incapacidad000000056 | J110: 0 | K110: 306602 | L110: =+J110-K110 -> -306602 | M110: 1 | N110: 800088702 | O110: EPS SURA COMPAÑIA SURAMERICANA SERVICIOS DE SALUD | T110: 0 | U110: CONTABLE | V110: N | W110: 000000056 | X110: 0 | Y110: TACOTESO | Z110: Mar 17 2022 5:13PM | AA110: frmBAN607 | AB110: DESKTOP-O60S49G | AC110: TAMBIENTAL | AD110: Mar 17 2022 5:13PM | AF110: =YEAR(C110) -> 2022 | AG110: =TEXT(C110,"mmm") -> feb | AH110: NUEVA EMPRESA PROMOTORA DE SALUD | AI110: #N/A
A111: 138020001 | B111: REINTEGRO DE INCAPACIDADES | C111: 44601 | D111: =TEXT(C111,"yyyy") -> 2022 | E111: 15 | F111: CONSIGNACIONES BANCO | H111: 000000054 | I111: NUEVA EMPRESA PROMOTORA DE SALUD:Reintegro incapacidad000000054 | J111: 0 | K111: 33804 | L111: =+J111-K111 -> -33804 | M111: 1 | N111: 900156264 | O111: NUEVA EMPRESA PROMOTORA DE SALUD | T111: 0 | U111: CONTABLE | V111: N | W111: 000000054 | X111: 0 | Y111: TACOTESO | Z111: Mar 17 2022 5:10PM | AA111: frmBAN607 | AB111: DESKTOP-O60S49G | AC111: TAMBIENTAL | AD111: Mar 17 2022 5:10PM | AF111: =YEAR(C111) -> 2022 | AG111: =TEXT(C111,"mmm") -> feb | AH111: NUEVA EMPRESA PROMOTORA DE SALUD | AI111: #N/A
A112: 138020001 | B112: REINTEGRO DE INCAPACIDADES | C112: 44601 | D112: =TEXT(C112,"yyyy") -> 2022 | E112: 15 | F112: CONSIGNACIONES BANCO | H112: 000000055 | I112: NUEVA EMPRESA PROMOTORA DE SALUD:Reintegro incapacidad000000055 | J112: 0 | K112: 1346338 | L112: =+J112-K112 -> -1346338 | M112: 1 | N112: 900156264 | O112: NUEVA EMPRESA PROMOTORA DE SALUD | T112: 0 | U112: CONTABLE | V112: N | W112: 000000055 | X112: 0 | Y112: TACOTESO | Z112: Mar 17 2022 5:11PM | AA112: frmBAN607 | AB112: DESKTOP-O60S49G | AC112: TAMBIENTAL | AD112: Mar 17 2022 5:11PM | AF112: =YEAR(C112) -> 2022 | AG112: =TEXT(C112,"mmm") -> feb | AH112: EPS SURA COMPAÑIA SURAMERICANA SERVICIOS DE SALUD | AI112: #N/A
A113: 138020001 | B113: REINTEGRO DE INCAPACIDADES | C113: 44607 | D113: =TEXT(C113,"yyyy") -> 2022 | E113: 15 | F113: CONSIGNACIONES BANCO | H113: 000000051 | I113: EPS SURA COMPAÑIA SURAMERICANA SERVICIOS DE SALUD:Reintegro incapacidad000000051 | J113: 0 | K113: 100000 | L113: =+J113-K113 -> -100000 | M113: 1 | N113: 800088702 | O113: EPS SURA COMPAÑIA SURAMERICANA SERVICIOS DE SALUD | T113: 0 | U113: CONTABLE | V113: N | W113: 000000051 | X113: 0 | Y113: TACOTESO | Z113: Mar 17 2022 5:06PM | AA113: frmBAN607 | AB113: DESKTOP-O60S49G | AC113: TAMBIENTAL | AD113: Mar 17 2022 5:06PM | AF113: =YEAR(C113) -> 2022 | AG113: =TEXT(C113,"mmm") -> feb | AH113: E.P.S. FAMISANAR LTDA. CAFAM COLSUBSIDIO | AI113: #N/A
A114: 138020001 | B114: REINTEGRO DE INCAPACIDADES | C114: 44607 | D114: =TEXT(C114,"yyyy") -> 2022 | E114: 15 | F114: CONSIGNACIONES BANCO | H114: 000000052 | I114: COOSALUD ENTIDAD PROMOTORA DE SALUD S.A:Reintegro incapacidad000000052 | J114: 0 | K114: 31974 | L114: =+J114-K114 -> -31974 | M114: 1 | N114: 900226715 | O114: COOSALUD ENTIDAD PROMOTORA DE SALUD S.A | T114: 0 | U114: CONTABLE | V114: N | W114: 000000052 | X114: 0 | Y114: TACOTESO | Z114: Mar 17 2022 5:07PM | AA114: frmBAN607 | AB114: DESKTOP-O60S49G | AC114: TAMBIENTAL | AD114: Mar 17 2022 5:07PM | AF114: =YEAR(C114) -> 2022 | AG114: =TEXT(C114,"mmm") -> feb | AH114: SALUD TOTAL S.A. EPS ARS | AI114: #N/A
A115: 138020001 | B115: REINTEGRO DE INCAPACIDADES | C115: 44607 | D115: =TEXT(C115,"yyyy") -> 2022 | E115: 15 | F115: CONSIGNACIONES BANCO | H115: 000000053 | I115: COOSALUD ENTIDAD PROMOTORA DE SALUD S.A:Reintegro incapacidad000000053 | J115: 0 | K115: 32439 | L115: =+J115-K115 -> -32439 | M115: 1 | N115: 900226715 | O115: COOSALUD ENTIDAD PROMOTORA DE SALUD S.A | T115: 0 | U115: CONTABLE | V115: N | W115: 000000053 | X115: 0 | Y115: TACOTESO | Z115: Mar 17 2022 5:08PM | AA115: frmBAN607 | AB115: DESKTOP-O60S49G | AC115: TAMBIENTAL | AD115: Mar 17 2022 5:08PM | AF115: =YEAR(C115) -> 2022 | AG115: =TEXT(C115,"mmm") -> feb | AH115: EPS SURA COMPAÑIA SURAMERICANA SERVICIOS DE SALUD | AI115: #N/A
A116: 138020001 | B116: REINTEGRO DE INCAPACIDADES | C116: 44617 | D116: =TEXT(C116,"yyyy") -> 2022 | E116: 15 | F116: CONSIGNACIONES BANCO | H116: 000000050 | I116: COOSALUD ENTIDAD PROMOTORA DE SALUD S.A:Reintegro incapacidad000000050 | J116: 0 | K116: 411927 | L116: =+J116-K116 -> -411927 | M116: 1 | N116: 900226715 | O116: COOSALUD ENTIDAD PROMOTORA DE SALUD S.A | T116: 0 | U116: CONTABLE | V116: N | W116: 000000050 | X116: 0 | Y116: TACOTESO | Z116: Mar 17 2022 5:04PM | AA116: frmBAN607 | AB116: DESKTOP-O60S49G | AC116: TAMBIENTAL | AD116: Mar 17 2022 5:04PM | AF116: =YEAR(C116) -> 2022 | AG116: =TEXT(C116,"mmm") -> feb | AH116: SALUD TOTAL S.A. EPS ARS | AI116: #N/A
A117: 138020001 | B117: REINTEGRO DE INCAPACIDADES | C117: 44620 | D117: =TEXT(C117,"yyyy") -> 2022 | E117: 15 | F117: CONSIGNACIONES BANCO | H117: 000000049 | I117: COOSALUD ENTIDAD PROMOTORA DE SALUD S.A:Reintegro incapacidad000000049 | J117: 0 | K117: 151422 | L117: =+J117-K117 -> -151422 | M117: 1 | N117: 900226715 | O117: COOSALUD ENTIDAD PROMOTORA DE SALUD S.A | T117: 0 | U117: CONTABLE | V117: N | W117: 000000049 | X117: 0 | Y117: TACOTESO | Z117: Mar 17 2022 5:03PM | AA117: frmBAN607 | AB117: DESKTOP-O60S49G | AC117: TAMBIENTAL | AD117: Mar 17 2022 5:03PM | AF117: =YEAR(C117) -> 2022 | AG117: =TEXT(C117,"mmm") -> feb | AH117: COOSALUD ENTIDAD PROMOTORA DE SALUD S.A | AI117: #N/A
A118: 138020001 | B118: REINTEGRO DE INCAPACIDADES | C118: 44620 | D118: =TEXT(C118,"yyyy") -> 2022 | E118: 21 | F118: NOMINA NOVASOFT | H118: 000000006 | I118: GASTOS REEMBOLSABLES | J118: 33334 | K118: 0 | L118: =+J118-K118 -> 33334 | M118: 1 | N118: 73202722 | O118: JESUS JAVIER BELTRAN OLIVELLA | P118: 10030400 | Q118: OPERADORES | T118: 0 | U118: CONTABLE | V118: N | W118: 000000006 | X118: 0 | Y118: TACOSITI | Z118: Mar 25 2022 6:22PM | AA118: frmCON6093 | AB118: DESKTOP-5900GRN | AC118: TAMBIENTAL | AD118: Mar 25 2022 6:22PM | AF118: =YEAR(C118) -> 2022 | AG118: =TEXT(C118,"mmm") -> feb | AH118: E.P.S. FAMISANAR LTDA. CAFAM COLSUBSIDIO | AI118: SURA E.P.S.
A119: 138020001 | B119: REINTEGRO DE INCAPACIDADES | C119: 44620 | D119: =TEXT(C119,"yyyy") -> 2022 | E119: 21 | F119: NOMINA NOVASOFT | H119: 000000006 | I119: GASTOS REEMBOLSABLES | J119: 500000 | K119: 0 | L119: =+J119-K119 -> 500000 | M119: 1 | N119: 1047370459 | O119: JOSE AUGUSTO ARZUZA MARRUGO | P119: 10030400 | Q119: OPERADORES | T119: 0 | U119: CONTABLE | V119: N | W119: 000000006 | X119: 0 | Y119: TACOSITI | Z119: Mar 25 2022 6:22PM | AA119: frmCON6093 | AB119: DESKTOP-5900GRN | AC119: TAMBIENTAL | AD119: Mar 25 2022 6:22PM | AF119: =YEAR(C119) -> 2022 | AG119: =TEXT(C119,"mmm") -> feb | AH119: SALUD TOTAL S.A. EPS ARS | AI119: SALUD TOTAL E.P.S.
A120: 138020001 | B120: REINTEGRO DE INCAPACIDADES | C120: 44620 | D120: =TEXT(C120,"yyyy") -> 2022 | E120: 21 | F120: NOMINA NOVASOFT | H120: 000000006 | I120: GASTOS REEMBOLSABLES | J120: 34963 | K120: 0 | L120: =+J120-K120 -> 34963 | M120: 1 | N120: 73106822 | O120: DECHAMPS MORALES MANUEL CARMELO | P120: 10030400 | Q120: OPERADORES | T120: 0 | U120: CONTABLE | V120: N | W120: 000000006 | X120: 0 | Y120: TACOSITI | Z120: Mar 25 2022 6:22PM | AA120: frmCON6093 | AB120: DESKTOP-5900GRN | AC120: TAMBIENTAL | AD120: Mar 25 2022 6:22PM | AF120: =YEAR(C120) -> 2022 | AG120: =TEXT(C120,"mmm") -> feb | AH120: SALUD TOTAL S.A. EPS ARS | AI120: SALUD TOTAL E.P.S.
A121: 138020001 | B121: REINTEGRO DE INCAPACIDADES | C121: 44620 | D121: =TEXT(C121,"yyyy") -> 2022 | E121: 21 | F121: NOMINA NOVASOFT | H121: 000000006 | I121: GASTOS REEMBOLSABLES | J121: 33334 | K121: 0 | L121: =+J121-K121 -> 33334 | M121: 1 | N121: 73121602 | O121: ELKIN YOUSEF CHAR NEGRETE | P121: 10030400 | Q121: OPERADORES | T121: 0 | U121: CONTABLE | V121: N | W121: 000000006 | X121: 0 | Y121: TACOSITI | Z121: Mar 25 2022 6:22PM | AA121: frmCON6093 | AB121: DESKTOP-5900GRN | AC121: TAMBIENTAL | AD121: Mar 25 2022 6:22PM | AF121: =YEAR(C121) -> 2022 | AG121: =TEXT(C121,"mmm") -> feb | AH121: SALUD TOTAL S.A. EPS ARS | AI121: SALUD TOTAL E.P.S.
...

Sheet BD 2021 - 2026
A1: SUBSISTEMA DE CONTABILIDAD
A2: TRANSAMBIENTAL S.A.S.
A3: CONSULTA DE MOVIMIENTO POR FUENTES A 24.MAR./2026
A4: PERIODO COMPRENDIDO ENTRE 01.ENE./2021 Y 28.FEB./2026 | I4: =SUBTOTAL(9,I7:I10000) -> 13425056 | J4: =SUBTOTAL(9,J7:J10000) -> 10261364 | K4: =+I4-J4 -> 3163692
A6: Codigo Cuenta | B6: Nombre Cuenta | C6: Fecha Documento | D6: Fuente | E6: Nombre Fuente | F6: Prefijo Documento | G6: Numero Documento | H6: Detalle del Registro | I6: Valor Debito | J6: Valor Credito | K6: Tipo Anexo | L6: Id.Tercero | M6: Nombre Tercero | N6: Codigo Costo | O6: Nombre Costo | P6: Codigo Retencion | Q6: Concepto Retencion | R6: Base Retencion | S6: Tipo Libro | T6: Asiento Cierre | U6: Documento Referencia | V6: Numero Cheque | W6: Codigo Operacion | X6: Fecha Operacion | Y6: Programa | Z6: Estacion | AA6: Empresa | AB6: Fecha Version | AC6: Estado Reg.
A7: 138020001 | B7: REINTEGRO DE INCAPACIDADES | C7: 44530 | D7: 99 | E7: SALDOS INICIALES | G7: 000000001 | H7: REINTEGRO DE INCAPACIDADES | I7: 38623261 | J7: 0 | K7: 1 | L7: 900771273 | M7: TRANSAMBIENTAL | R7: 0 | S7: CONTABLE | T7: N | U7: 000000001 | V7: 0 | W7: TACOSITI | X7: Feb 8 2022 4:17AM | Y7: frmCON6093 | Z7: DESKTOP-5900GRN | AA7: TAMBIENTAL | AB7: Feb 8 2022 4:17AM
A8: 138020001 | B8: REINTEGRO DE INCAPACIDADES | C8: 44532 | D8: 15 | E8: CONSIGNACIONES BANCO | G8: 000000010 | H8: EPS SURA COMPAÑIA SURAMERICANA SERVICIOS DE SALUD:REINTEGRO INCAPACIDAD SURAMERICANA000000010 | I8: 0 | J8: 262479 | K8: 1 | L8: 800088702 | M8: EPS SURA COMPAÑIA SURAMERICANA SERVICIOS DE SALUD | R8: 0 | S8: CONTABLE | T8: N | U8: 000000010 | V8: 0 | W8: TACOTESO | X8: Ene 14 2022 5:20PM | Y8: frmBAN607 | Z8: DESKTOP-O60S49G | AA8: TAMBIENTAL | AB8: Ene 14 2022 5:20PM
A9: 138020001 | B9: REINTEGRO DE INCAPACIDADES | C9: 44532 | D9: 15 | E9: CONSIGNACIONES BANCO | G9: 000000011 | H9: SALUD TOTAL S.A. EPS ARS:REINTEGRO INCAPACIDAD SALUD TOTAL000000011 | I9: 0 | J9: 428175 | K9: 1 | L9: 800130907 | M9: SALUD TOTAL S.A. EPS ARS | R9: 0 | S9: CONTABLE | T9: N | U9: 000000011 | V9: 0 | W9: TACOTESO | X9: Ene 14 2022 5:27PM | Y9: frmBAN607 | Z9: DESKTOP-O60S49G | AA9: TAMBIENTAL | AB9: Ene 14 2022 5:27PM
A10: 138020001 | B10: REINTEGRO DE INCAPACIDADES | C10: 44540 | D10: 15 | E10: CONSIGNACIONES BANCO | G10: 000000007 | H10: SALUD TOTAL S.A. EPS ARS:REINTEGRO INCAPACIDAD SALUD TOTAL000000007 | I10: 0 | J10: 1535787 | K10: 1 | L10: 800130907 | M10: SALUD TOTAL S.A. EPS ARS | R10: 0 | S10: CONTABLE | T10: N | U10: 000000007 | V10: 0 | W10: TACOTESO | X10: Ene 14 2022 4:39PM | Y10: frmBAN607 | Z10: DESKTOP-O60S49G | AA10: TAMBIENTAL | AB10: Ene 14 2022 4:39PM
A11: 138020001 | B11: REINTEGRO DE INCAPACIDADES | C11: 44540 | D11: 15 | E11: CONSIGNACIONES BANCO | G11: 000000008 | H11: NUEVA EMPRESA PROMOTORA DE SALUD:REINTEGRO INCAPACIDAD NUEVA EPS000000008 | I11: 0 | J11: 195079 | K11: 1 | L11: 900156264 | M11: NUEVA EMPRESA PROMOTORA DE SALUD | R11: 0 | S11: CONTABLE | T11: N | U11: 000000008 | V11: 0 | W11: TACOTESO | X11: Ene 14 2022 4:41PM | Y11: frmBAN607 | Z11: DESKTOP-O60S49G | AA11: TAMBIENTAL | AB11: Ene 14 2022 4:41PM
A12: 138020001 | B12: REINTEGRO DE INCAPACIDADES | C12: 44545 | D12: 21 | E12: NOMINA NOVASOFT | G12: 000000001 | H12: GASTOS REEMBOLSABLES | I12: 42866 | J12: 0 | K12: 1 | L12: 800088702 | M12: EPS SURA COMPAÑIA SURAMERICANA SERVICIOS DE SALUD | N12: 10010200 | O12: COMPRAS Y ABASTESIMIENTO | R12: 0 | S12: CONTABLE | T12: N | U12: 000000001 | V12: 0 | W12: TACOSITI | X12: Feb 8 2022 5:24PM | Y12: frmCON6093 | Z12: DESKTOP-5900GRN | AA12: TAMBIENTAL | AB12: Feb 8 2022 5:24PM
A13: 138020001 | B13: REINTEGRO DE INCAPACIDADES | C13: 44545 | D13: 21 | E13: NOMINA NOVASOFT | G13: 000000001 | H13: GASTOS REEMBOLSABLES | I13: 30284 | J13: 0 | K13: 1 | L13: 800088702 | M13: EPS SURA COMPAÑIA SURAMERICANA SERVICIOS DE SALUD | N13: 10020200 | O13: EJECUCIÓN | R13: 0 | S13: CONTABLE | T13: N | U13: 000000001 | V13: 0 | W13: TACOSITI | X13: Feb 8 2022 5:24PM | Y13: frmCON6093 | Z13: DESKTOP-5900GRN | AA13: TAMBIENTAL | AB13: Feb 8 2022 5:24PM
A14: 138020001 | B14: REINTEGRO DE INCAPACIDADES | C14: 44545 | D14: 21 | E14: NOMINA NOVASOFT | G14: 000000001 | H14: GASTOS REEMBOLSABLES | I14: 77628 | J14: 0 | K14: 1 | L14: 800256161 | M14: ARP SURA | N14: 10020200 | O14: EJECUCIÓN | R14: 0 | S14: CONTABLE | T14: N | U14: 000000001 | V14: 0 | W14: TACOSITI | X14: Feb 8 2022 5:24PM | Y14: frmCON6093 | Z14: DESKTOP-5900GRN | AA14: TAMBIENTAL | AB14: Feb 8 2022 5:24PM
A15: 138020001 | B15: REINTEGRO DE INCAPACIDADES | C15: 44545 | D15: 21 | E15: NOMINA NOVASOFT | G15: 000000001 | H15: GASTOS REEMBOLSABLES | I15: 60568 | J15: 0 | K15: 1 | L15: 800130907 | M15: SALUD TOTAL S.A. EPS ARS | N15: 10030200 | O15: COORDINACIÓN DE OPERACIONES | R15: 0 | S15: CONTABLE | T15: N | U15: 000000001 | V15: 0 | W15: TACOSITI | X15: Feb 8 2022 5:24PM | Y15: frmCON6093 | Z15: DESKTOP-5900GRN | AA15: TAMBIENTAL | AB15: Feb 8 2022 5:24PM
A16: 138020001 | B16: REINTEGRO DE INCAPACIDADES | C16: 44545 | D16: 21 | E16: NOMINA NOVASOFT | G16: 000000001 | H16: GASTOS REEMBOLSABLES | I16: 67244 | J16: 0 | K16: 1 | L16: 800088702 | M16: EPS SURA COMPAÑIA SURAMERICANA SERVICIOS DE SALUD | N16: 10030400 | O16: OPERADORES | R16: 0 | S16: CONTABLE | T16: N | U16: 000000001 | V16: 0 | W16: TACOSITI | X16: Feb 8 2022 5:24PM | Y16: frmCON6093 | Z16: DESKTOP-5900GRN | AA16: TAMBIENTAL | AB16: Feb 8 2022 5:24PM
A17: 138020001 | B17: REINTEGRO DE INCAPACIDADES | C17: 44545 | D17: 21 | E17: NOMINA NOVASOFT | G17: 000000001 | H17: GASTOS REEMBOLSABLES | I17: 454263 | J17: 0 | K17: 1 | L17: 800130907 | M17: SALUD TOTAL S.A. EPS ARS | N17: 10030400 | O17: OPERADORES | R17: 0 | S17: CONTABLE | T17: N | U17: 000000001 | V17: 0 | W17: TACOSITI | X17: Feb 8 2022 5:24PM | Y17: frmCON6093 | Z17: DESKTOP-5900GRN | AA17: TAMBIENTAL | AB17: Feb 8 2022 5:24PM
A18: 138020001 | B18: REINTEGRO DE INCAPACIDADES | C18: 44545 | D18: 21 | E18: NOMINA NOVASOFT | G18: 000000001 | H18: GASTOS REEMBOLSABLES | I18: 32965 | J18: 0 | K18: 1 | L18: 800130907 | M18: SALUD TOTAL S.A. EPS ARS | N18: 10030400 | O18: OPERADORES | R18: 0 | S18: CONTABLE | T18: N | U18: 000000001 | V18: 0 | W18: TACOSITI | X18: Feb 8 2022 5:24PM | Y18: frmCON6093 | Z18: DESKTOP-5900GRN | AA18: TAMBIENTAL | AB18: Feb 8 2022 5:24PM
A19: 138020001 | B19: REINTEGRO DE INCAPACIDADES | C19: 44545 | D19: 21 | E19: NOMINA NOVASOFT | G19: 000000001 | H19: GASTOS REEMBOLSABLES | I19: 163561 | J19: 0 | K19: 1 | L19: 800130907 | M19: SALUD TOTAL S.A. EPS ARS | N19: 10030400 | O19: OPERADORES | R19: 0 | S19: CONTABLE | T19: N | U19: 000000001 | V19: 0 | W19: TACOSITI | X19: Feb 8 2022 5:24PM | Y19: frmCON6093 | Z19: DESKTOP-5900GRN | AA19: TAMBIENTAL | AB19: Feb 8 2022 5:24PM
A20: 138020001 | B20: REINTEGRO DE INCAPACIDADES | C20: 44545 | D20: 21 | E20: NOMINA NOVASOFT | G20: 000000001 | H20: GASTOS REEMBOLSABLES | I20: 363410 | J20: 0 | K20: 1 | L20: 800251440 | M20: E.P.S. SANITAS S.A. | N20: 10030400 | O20: OPERADORES | R20: 0 | S20: CONTABLE | T20: N | U20: 000000001 | V20: 0 | W20: TACOSITI | X20: Feb 8 2022 5:24PM | Y20: frmCON6093 | Z20: DESKTOP-5900GRN | AA20: TAMBIENTAL | AB20: Feb 8 2022 5:24PM
A21: 138020001 | B21: REINTEGRO DE INCAPACIDADES | C21: 44545 | D21: 21 | E21: NOMINA NOVASOFT | G21: 000000001 | H21: GASTOS REEMBOLSABLES | I21: 60568 | J21: 0 | K21: 1 | L21: 800251440 | M21: E.P.S. SANITAS S.A. | N21: 10030400 | O21: OPERADORES | R21: 0 | S21: CONTABLE | T21: N | U21: 000000001 | V21: 0 | W21: TACOSITI | X21: Feb 8 2022 5:24PM | Y21: frmCON6093 | Z21: DESKTOP-5900GRN | AA21: TAMBIENTAL | AB21: Feb 8 2022 5:24PM
A22: 138020001 | B22: REINTEGRO DE INCAPACIDADES | C22: 44545 | D22: 21 | E22: NOMINA NOVASOFT | G22: 000000001 | H22: GASTOS REEMBOLSABLES | I22: 30284 | J22: 0 | K22: 1 | L22: 800251440 | M22: E.P.S. SANITAS S.A. | N22: 10030400 | O22: OPERADORES | R22: 0 | S22: CONTABLE | T22: N | U22: 000000001 | V22: 0 | W22: TACOSITI | X22: Feb 8 2022 5:24PM | Y22: frmCON6093 | Z22: DESKTOP-5900GRN | AA22: TAMBIENTAL | AB22: Feb 8 2022 5:24PM
A23: 138020001 | B23: REINTEGRO DE INCAPACIDADES | C23: 44545 | D23: 21 | E23: NOMINA NOVASOFT | G23: 000000001 | H23: GASTOS REEMBOLSABLES | I23: 31088 | J23: 0 | K23: 1 | L23: 806008394 | M23: ASOCIACION MUTUAL SER EMPRESA SOLIDARIA | N23: 10030400 | O23: OPERADORES | R23: 0 | S23: CONTABLE | T23: N | U23: 000000001 | V23: 0 | W23: TACOSITI | X23: Feb 8 2022 5:24PM | Y23: frmCON6093 | Z23: DESKTOP-5900GRN | AA23: TAMBIENTAL | AB23: Feb 8 2022 5:24PM
... A25: 138020001 | B25: REINTEGRO DE INCAPACIDADES | C25: 44545 | D25: 21 | E25: NOMINA NOVASOFT | G25: 000000001 | H25: GASTOS REEMBOLSABLES | I25: 513641 | J25: 0 | K25: 1 | L25: 900156264 | M25: NUEVA EMPRESA PROMOTORA DE SALUD | N25: 10030400 | O25: OPERADORES | R25: 0 | S25: CONTABLE | T25: N | U25: 000000001 | V25: 0 | W25: TACOSITI | X25: Feb 8 2022 5:24PM | Y25: frmCON6093 | Z25: DESKTOP-5900GRN | AA25: TAMBIENTAL | AB25: Feb 8 2022 5:24PM
A26: 138020001 | B26: REINTEGRO DE INCAPACIDADES | C26: 44553 | D26: 15 | E26: CONSIGNACIONES BANCO | G26: 000000003 | H26: SALUD TOTAL S.A. EPS ARS:REINTEGRO INCAPACIDAD SALUD TOTAL000000003 | I26: 0 | J26: 885682 | K26: 1 | L26: 800130907 | M26: SALUD TOTAL S.A. EPS ARS | R26: 0 | S26: CONTABLE | T26: N | U26: 000000003 | V26: 0 | W26: TACOTESO | X26: Ene 14 2022 3:48PM | Y26: frmBAN607 | Z26: DESKTOP-O60S49G | AA26: TAMBIENTAL | AB26: Ene 14 2022 3:48PM
A27: 138020001 | B27: REINTEGRO DE INCAPACIDADES | C27: 44553 | D27: 15 | E27: CONSIGNACIONES BANCO | G27: 000000004 | H27: SALUD TOTAL S.A. EPS ARS:REINTEGRO INCAPACIDAD SALUD TOTAL000000004 | I27: 0 | J27: 274266 | K27: 1 | L27: 800130907 | M27: SALUD TOTAL S.A. EPS ARS | R27: 0 | S27: CONTABLE | T27: N | U27: 000000004 | V27: 0 | W27: TACOTESO | X27: Ene 14 2022 3:51PM | Y27: frmBAN607 | Z27: DESKTOP-O60S49G | AA27: TAMBIENTAL | AB27: Ene 14 2022 3:51PM
A28: 138020001 | B28: REINTEGRO DE INCAPACIDADES | C28: 44553 | D28: 15 | E28: CONSIGNACIONES BANCO | G28: 000000005 | H28: E.P.S. FAMISANAR LTDA. CAFAM COLSUBSIDIO:REINTEGRO INCAPACIDAD FAMISANAR000000005 | I28: 0 | J28: 97173 | K28: 1 | L28: 830003564 | M28: E.P.S. FAMISANAR LTDA. CAFAM COLSUBSIDIO | R28: 0 | S28: CONTABLE | T28: N | U28: 000000005 | V28: 0 | W28: TACOTESO | X28: Ene 14 2022 3:58PM | Y28: frmBAN607 | Z28: DESKTOP-O60S49G | AA28: TAMBIENTAL | AB28: Ene 14 2022 3:58PM
A29: 138020001 | B29: REINTEGRO DE INCAPACIDADES | C29: 44553 | D29: 15 | E29: CONSIGNACIONES BANCO | G29: 000000006 | H29: EPS SURA COMPAÑIA SURAMERICANA SERVICIOS DE SALUD:REINTEGRO INCAPACIDAD SURAMERICANA000000006 | I29: 0 | J29: 97524 | K29: 1 | L29: 800088702 | M29: EPS SURA COMPAÑIA SURAMERICANA SERVICIOS DE SALUD | R29: 0 | S29: CONTABLE | T29: N | U29: 000000006 | V29: 0 | W29: TACOTESO | X29: Ene 14 2022 4:37PM | Y29: frmBAN607 | Z29: DESKTOP-O60S49G | AA29: TAMBIENTAL | AB29: Ene 14 2022 4:37PM
A30: 138020001 | B30: REINTEGRO DE INCAPACIDADES | C30: 44554 | D30: 15 | E30: CONSIGNACIONES BANCO | G30: 000000015 | H30: ASOCIACION MUTUAL SER EMPRESA SOLIDARIA:Reintegro incapacidad Mutual SER000000015 | I30: 0 | J30: 31572 | K30: 1 | L30: 806008394 | M30: ASOCIACION MUTUAL SER EMPRESA SOLIDARIA | R30: 0 | S30: CONTABLE | T30: N | U30: 000000015 | V30: 0 | W30: TACOTESO | X30: Feb 15 2022 2:10PM | Y30: frmBAN607 | Z30: DESKTOP-O60S49G | AA30: TAMBIENTAL | AB30: Feb 15 2022 2:10PM
A31: 138020001 | B31: REINTEGRO DE INCAPACIDADES | C31: 44559 | D31: 15 | E31: CONSIGNACIONES BANCO | G31: 000000001 | H31: SALUD TOTAL S.A. EPS ARS:Reintegro incapacidad Salud Total000000001 | I31: 0 | J31: 133255 | K31: 1 | L31: 800130907 | M31: SALUD TOTAL S.A. EPS ARS | R31: 0 | S31: CONTABLE | T31: N | U31: 000000001 | V31: 0 | W31: TACOTESO | X31: Ene 14 2022 2:07PM | Y31: frmBAN607 | Z31: DESKTOP-O60S49G | AA31: TAMBIENTAL | AB31: Ene 14 2022 2:07PM
A32: 138020001 | B32: REINTEGRO DE INCAPACIDADES | C32: 44561 | D32: 21 | E32: NOMINA NOVASOFT | G32: 000000001 | H32: GASTOS REEMBOLSABLES | I32: 278990 | J32: 0 | K32: 1 | L32: 800256161 | M32: ARP SURA | N32: 10020200 | O32: EJECUCIÓN | R32: 0 | S32: CONTABLE | T32: N | U32: 000000001 | V32: 0 | W32: TACOSITI | X32: Feb 8 2022 5:24PM | Y32: frmCON6093 | Z32: DESKTOP-5900GRN | AA32: TAMBIENTAL | AB32: Feb 8 2022 5:24PM
A33: 138020001 | B33: REINTEGRO DE INCAPACIDADES | C33: 44561 | D33: 21 | E33: NOMINA NOVASOFT | G33: 000000001 | H33: GASTOS REEMBOLSABLES | I33: 33082 | J33: 0 | K33: 1 | L33: 800088702 | M33: EPS SURA COMPAÑIA SURAMERICANA SERVICIOS DE SALUD | N33: 10030400 | O33: OPERADORES | R33: 0 | S33: CONTABLE | T33: N | U33: 000000001 | V33: 0 | W33: TACOSITI | X33: Feb 8 2022 5:24PM | Y33: frmCON6093 | Z33: DESKTOP-5900GRN | AA33: TAMBIENTAL | AB33: Feb 8 2022 5:24PM
A34: 138020001 | B34: REINTEGRO DE INCAPACIDADES | C34: 44561 | D34: 21 | E34: NOMINA NOVASOFT | G34: 000000001 | H34: GASTOS REEMBOLSABLES | I34: 68499 | J34: 0 | K34: 1 | L34: 800088702 | M34: EPS SURA COMPAÑIA SURAMERICANA SERVICIOS DE SALUD | N34: 10030400 | O34: OPERADORES | R34: 0 | S34: CONTABLE | T34: N | U34: 000000001 | V34: 0 | W34: TACOSITI | X34: Feb 8 2022 5:24PM | Y34: frmCON6093 | Z34: DESKTOP-5900GRN | AA34: TAMBIENTAL | AB34: Feb 8 2022 5:24PM
A35: 138020001 | B35: REINTEGRO DE INCAPACIDADES | C35: 44561 | D35: 21 | E35: NOMINA NOVASOFT | G35: 000000001 | H35: GASTOS REEMBOLSABLES | I35: 484547 | J35: 0 | K35: 1 | L35: 800130907 | M35: SALUD TOTAL S.A. EPS ARS | N35: 10030400 | O35: OPERADORES | R35: 0 | S35: CONTABLE | T35: N | U35: 000000001 | V35: 0 | W35: TACOSITI | X35: Feb 8 2022 5:24PM | Y35: frmCON6093 | Z35: DESKTOP-5900GRN | AA35: TAMBIENTAL | AB35: Feb 8 2022 5:24PM
A36: 138020001 | B36: REINTEGRO DE INCAPACIDADES | C36: 44561 | D36: 21 | E36: NOMINA NOVASOFT | G36: 000000001 | H36: GASTOS REEMBOLSABLES | I36: 30881 | J36: 0 | K36: 1 | L36: 800130907 | M36: SALUD TOTAL S.A. EPS ARS | N36: 10030400 | O36: OPERADORES | R36: 0 | S36: CONTABLE | T36: N | U36: 000000001 | V36: 0 | W36: TACOSITI | X36: Feb 8 2022 5:24PM | Y36: frmCON6093 | Z36: DESKTOP-5900GRN | AA36: TAMBIENTAL | AB36: Feb 8 2022 5:24PM
A37: 138020001 | B37: REINTEGRO DE INCAPACIDADES | C37: 44561 | D37: 21 | E37: NOMINA NOVASOFT | G37: 000000001 | H37: GASTOS REEMBOLSABLES | I37: 102302 | J37: 0 | K37: 1 | L37: 800130907 | M37: SALUD TOTAL S.A. EPS ARS | N37: 10030400 | O37: OPERADORES | R37: 0 | S37: CONTABLE | T37: N | U37: 000000001 | V37: 0 | W37: TACOSITI | X37: Feb 8 2022 5:24PM | Y37: frmCON6093 | Z37: DESKTOP-5900GRN | AA37: TAMBIENTAL | AB37: Feb 8 2022 5:24PM
A38: 138020001 | B38: REINTEGRO DE INCAPACIDADES | C38: 44561 | D38: 21 | E38: NOMINA NOVASOFT | G38: 000000001 | H38: GASTOS REEMBOLSABLES | I38: 98137 | J38: 0 | K38: 1 | L38: 800130907 | M38: SALUD TOTAL S.A. EPS ARS | N38: 10030400 | O38: OPERADORES | R38: 0 | S38: CONTABLE | T38: N | U38: 000000001 | V38: 0 | W38: TACOSITI | X38: Feb 8 2022 5:24PM | Y38: frmCON6093 | Z38: DESKTOP-5900GRN | AA38: TAMBIENTAL | AB38: Feb 8 2022 5:24PM
A39: 138020001 | B39: REINTEGRO DE INCAPACIDADES | C39: 44561 | D39: 21 | E39: NOMINA NOVASOFT | G39: 000000001 | H39: GASTOS REEMBOLSABLES | I39: 34357 | J39: 0 | K39: 1 | L39: 800130907 | M39: SALUD TOTAL S.A. EPS ARS | N39: 10030400 | O39: OPERADORES | R39: 0 | S39: CONTABLE | T39: N | U39: 000000001 | V39: 0 | W39: TACOSITI | X39: Feb 8 2022 5:24PM | Y39: frmCON6093 | Z39: DESKTOP-5900GRN | AA39: TAMBIENTAL | AB39: Feb 8 2022 5:24PM
A40: 138020001 | B40: REINTEGRO DE INCAPACIDADES | C40: 44561 | D40: 21 | E40: NOMINA NOVASOFT | G40: 000000001 | H40: GASTOS REEMBOLSABLES | I40: 363411 | J40: 0 | K40: 1 | L40: 800251440 | M40: E.P.S. SANITAS S.A. | N40: 10030400 | O40: OPERADORES | R40: 0 | S40: CONTABLE | T40: N | U40: 000000001 | V40: 0 | W40: TACOSITI | X40: Feb 8 2022 5:24PM | Y40: frmCON6093 | Z40: DESKTOP-5900GRN | AA40: TAMBIENTAL | AB40: Feb 8 2022 5:24PM
A41: 138020001 | B41: REINTEGRO DE INCAPACIDADES | C41: 44561 | D41: 21 | E41: NOMINA NOVASOFT | G41: 000000001 | H41: GASTOS REEMBOLSABLES | I41: 33912 | J41: 0 | K41: 1 | L41: 800251440 | M41: E.P.S. SANITAS S.A. | N41: 10030400 | O41: OPERADORES | R41: 0 | S41: CONTABLE | T41: N | U41: 000000001 | V41: 0 | W41: TACOSITI | X41: Feb 8 2022 5:24PM | Y41: frmCON6093 | Z41: DESKTOP-5900GRN | AA41: TAMBIENTAL | AB41: Feb 8 2022 5:24PM
A42: 138020001 | B42: REINTEGRO DE INCAPACIDADES | C42: 44561 | D42: 21 | E42: NOMINA NOVASOFT | G42: 000000001 | H42: GASTOS REEMBOLSABLES | I42: 345056 | J42: 0 | K42: 1 | L42: 830003564 | M42: E.P.S. FAMISANAR LTDA. CAFAM COLSUBSIDIO | N42: 10030400 | O42: OPERADORES | R42: 0 | S42: CONTABLE | T42: N | U42: 000000001 | V42: 0 | W42: TACOSITI | X42: Feb 8 2022 5:24PM | Y42: frmCON6093 | Z42: DESKTOP-5900GRN | AA42: TAMBIENTAL | AB42: Feb 8 2022 5:24PM
A43: 138020001 | B43: REINTEGRO DE INCAPACIDADES | C43: 44561 | D43: 21 | E43: NOMINA NOVASOFT | G43: 000000001 | H43: GASTOS REEMBOLSABLES | I43: 32893 | J43: 0 | K43: 1 | L43: 900156264 | M43: NUEVA EMPRESA PROMOTORA DE SALUD | N43: 10030400 | O43: OPERADORES | R43: 0 | S43: CONTABLE | T43: N | U43: 000000001 | V43: 0 | W43: TACOSITI | X43: Feb 8 2022 5:24PM | Y43: frmCON6093 | Z43: DESKTOP-5900GRN | AA43: TAMBIENTAL | AB43: Feb 8 2022 5:24PM
... A48: 138020001 | B48: REINTEGRO DE INCAPACIDADES | C48: 44561 | D48: 21 | E48: NOMINA NOVASOFT | G48: 000000001 | H48: GASTOS REEMBOLSABLES | I48: 32438 | J48: 0 | K48: 1 | L48: 800088702 | M48: EPS SURA COMPAÑIA SURAMERICANA SERVICIOS DE SALUD | N48: 10030400 | O48: OPERADORES | R48: 0 | S48: CONTABLE | T48: N | U48: 000000001 | V48: 0 | W48: TACOSITI | X48: Feb 8 2022 5:24PM | Y48: frmCON6093 | Z48: DESKTOP-5900GRN | AA48: TAMBIENTAL | AB48: Feb 8 2022 5:24PM
A49: 138020001 | B49: REINTEGRO DE INCAPACIDADES | C49: 44561 | D49: 24 | E49: ASIENTOS DE CONTABILIDAD | G49: 000000048 | H49: REINTEGRO DE INCAPACIDADES | I49: 0 | J49: 0.01 | K49: 1 | L49: 900771273 | M49: TRANSAMBIENTAL | R49: 0 | S49: CONTABLE | T49: N | U49: 000000048 | V49: 0 | W49: TAAUXAREA | X49: Feb 25 2022 5:38PM | Y49: frmCON200 | Z49: PRACTICANTEFA | AA49: TAMBIENTAL | AB49: Mar 31 2022 5:14PM
A50: 138020001 | B50: REINTEGRO DE INCAPACIDADES | C50: 44573 | D50: 15 | E50: CONSIGNACIONES BANCO | G50: 000000042 | H50: NUEVA EMPRESA PROMOTORA DE SALUD:REINTEGRO INCAPACIDADES000000042 | I50: 0 | J50: 398184 | K50: 1 | L50: 900156264 | M50: NUEVA EMPRESA PROMOTORA DE SALUD | R50: 0 | S50: CONTABLE | T50: N | U50: 000000042 | V50: 0 | W50: TACOTESO | X50: Feb 24 2022 6:21PM | Y50: frmBAN607 | Z50: DESKTOP-O60S49G | AA50: TAMBIENTAL | AB50: Feb 24 2022 6:21PM
A51: 138020001 | B51: REINTEGRO DE INCAPACIDADES | C51: 44575 | D51: 15 | E51: CONSIGNACIONES BANCO | G51: 000000036 | H51: COOSALUD ENTIDAD PROMOTORA DE SALUD S.A:REINTEGRO INCAPACIDADES000000036 | I51: 0 | J51: 29261 | K51: 1 | L51: 900226715 | M51: COOSALUD ENTIDAD PROMOTORA DE SALUD S.A | R51: 0 | S51: CONTABLE | T51: N | U51: 000000036 | V51: 0 | W51: TACOTESO | X51: Feb 24 2022 6:07PM | Y51: frmBAN607 | Z51: DESKTOP-O60S49G | AA51: TAMBIENTAL | AB51: Feb 24 2022 6:07PM
A52: 138020001 | B52: REINTEGRO DE INCAPACIDADES | C52: 44575 | D52: 15 | E52: CONSIGNACIONES BANCO | G52: 000000037 | H52: COOSALUD ENTIDAD PROMOTORA DE SALUD S.A:REINTEGRO INCAPACIDADES000000037 | I52: 0 | J52: 30285 | K52: 1 | L52: 900226715 | M52: COOSALUD ENTIDAD PROMOTORA DE SALUD S.A | R52: 0 | S52: CONTABLE | T52: N | U52: 000000037 | V52: 0 | W52: TACOTESO | X52: Feb 24 2022 6:08PM | Y52: frmBAN607 | Z52: DESKTOP-O60S49G | AA52: TAMBIENTAL | AB52: Feb 24 2022 6:08PM
A53: 138020001 | B53: REINTEGRO DE INCAPACIDADES | C53: 44575 | D53: 15 | E53: CONSIGNACIONES BANCO | G53: 000000038 | H53: COOSALUD ENTIDAD PROMOTORA DE SALUD S.A:REINTEGRO INCAPACIDADES000000038 | I53: 0 | J53: 30285 | K53: 1 | L53: 900226715 | M53: COOSALUD ENTIDAD PROMOTORA DE SALUD S.A | R53: 0 | S53: CONTABLE | T53: N | U53: 000000038 | V53: 0 | W53: TACOTESO | X53: Feb 24 2022 6:11PM | Y53: frmBAN607 | Z53: DESKTOP-O60S49G | AA53: TAMBIENTAL | AB53: Feb 24 2022 6:11PM
A54: 138020001 | B54: REINTEGRO DE INCAPACIDADES | C54: 44575 | D54: 15 | E54: CONSIGNACIONES BANCO | G54: 000000039 | H54: COOSALUD ENTIDAD PROMOTORA DE SALUD S.A:REINTEGRO INCAPACIDADES000000039 | I54: 0 | J54: 31032 | K54: 1 | L54: 900226715 | M54: COOSALUD ENTIDAD PROMOTORA DE SALUD S.A | R54: 0 | S54: CONTABLE | T54: N | U54: 000000039 | V54: 0 | W54: TACOTESO | X54: Feb 24 2022 6:12PM | Y54: frmBAN607 | Z54: DESKTOP-O60S49G | AA54: TAMBIENTAL | AB54: Feb 24 2022 6:12PM
A55: 138020001 | B55: REINTEGRO DE INCAPACIDADES | C55: 44575 | D55: 15 | E55: CONSIGNACIONES BANCO | G55: 000000040 | H55: COOSALUD ENTIDAD PROMOTORA DE SALUD S.A:REINTEGRO INCAPACIDADES000000040 | I55: 0 | J55: 30285 | K55: 1 | L55: 900226715 | M55: COOSALUD ENTIDAD PROMOTORA DE SALUD S.A | R55: 0 | S55: CONTABLE | T55: N | U55: 000000040 | V55: 0 | W55: TACOTESO | X55: Feb 24 2022 6:17PM | Y55: frmBAN607 | Z55: DESKTOP-O60S49G | AA55: TAMBIENTAL | AB55: Feb 24 2022 6:17PM
A56: 138020001 | B56: REINTEGRO DE INCAPACIDADES | C56: 44575 | D56: 15 | E56: CONSIGNACIONES BANCO | G56: 000000041 | H56: COOSALUD ENTIDAD PROMOTORA DE SALUD S.A:REINTEGRO INCAPACIDADES000000041 | I56: 0 | J56: 173891 | K56: 1 | L56: 900226715 | M56: COOSALUD ENTIDAD PROMOTORA DE SALUD S.A | R56: 0 | S56: CONTABLE | T56: N | U56: 000000041 | V56: 0 | W56: TACOTESO | X56: Feb 24 2022 6:20PM | Y56: frmBAN607 | Z56: DESKTOP-O60S49G | AA56: TAMBIENTAL | AB56: Feb 24 2022 6:20PM
A57: 138020001 | B57: REINTEGRO DE INCAPACIDADES | C57: 44576 | D57: 21 | E57: NOMINA NOVASOFT | G57: 000000004 | H57: GASTOS REEMBOLSABLES | I57: 33334 | J57: 0 | K57: 1 | L57: 1128045753 | M57: ROJAS BUSTOS ESEIZA DEL CARMEN | N57: 10030200 | O57: COORDINACIÓN DE OPERACIONES | R57: 0 | S57: CONTABLE | T57: N | U57: 000000004 | V57: 0 | W57: TAAUXCON | X57: Mar 10 2022 6:41PM | Y57: frmCON6093 | Z57: LAPTOP-18GI5NJH | AA57: TAMBIENTAL | AB57: Mar 10 2022 6:41PM
A58: 138020001 | B58: REINTEGRO DE INCAPACIDADES | C58: 44576 | D58: 21 | E58: NOMINA NOVASOFT | G58: 000000004 | H58: GASTOS REEMBOLSABLES | I58: 270801 | J58: 0 | K58: 1 | L58: 72073849 | M58: DORIAN RODRIGUEZ OSPINO | N58: 10030400 | O58: OPERADORES | R58: 0 | S58: CONTABLE | T58: N | U58: 000000004 | V58: 0 | W58: TAAUXCON | X58: Mar 10 2022 6:41PM | Y58: frmCON6093 | Z58: LAPTOP-18GI5NJH | AA58: TAMBIENTAL | AB58: Mar 10 2022 6:41PM
A59: 138020001 | B59: REINTEGRO DE INCAPACIDADES | C59: 44576 | D59: 21 | E59: NOMINA NOVASOFT | G59: 000000004 | H59: GASTOS REEMBOLSABLES | I59: 33632 | J59: 0 | K59: 1 | L59: 73143163 | M59: JUAN CARLOS CABRERA TORRES | N59: 10030400 | O59: OPERADORES | R59: 0 | S59: CONTABLE | T59: N | U59: 000000004 | V59: 0 | W59: TAAUXCON | X59: Mar 10 2022 6:41PM | Y59: frmCON6093 | Z59: LAPTOP-18GI5NJH | AA59: TAMBIENTAL | AB59: Mar 10 2022 6:41PM
A60: 138020001 | B60: REINTEGRO DE INCAPACIDADES | C60: 44576 | D60: 21 | E60: NOMINA NOVASOFT | G60: 000000004 | H60: GASTOS REEMBOLSABLES | I60: 100000 | J60: 0 | K60: 1 | L60: 73202722 | M60: JESUS JAVIER BELTRAN OLIVELLA | N60: 10030400 | O60: OPERADORES | R60: 0 | S60: CONTABLE | T60: N | U60: 000000004 | V60: 0 | W60: TAAUXCON | X60: Mar 10 2022 6:41PM | Y60: frmCON6093 | Z60: LAPTOP-18GI5NJH | AA60: TAMBIENTAL | AB60: Mar 10 2022 6:41PM
A61: 138020001 | B61: REINTEGRO DE INCAPACIDADES | C61: 44576 | D61: 21 | E61: NOMINA NOVASOFT | G61: 000000004 | H61: GASTOS REEMBOLSABLES | I61: 35814 | J61: 0 | K61: 1 | L61: 7918997 | M61: MOISES CASTILLA GUTIERREZ | N61: 10030400 | O61: OPERADORES | R61: 0 | S61: CONTABLE | T61: N | U61: 000000004 | V61: 0 | W61: TAAUXCON | X61: Mar 10 2022 6:41PM | Y61: frmCON6093 | Z61: LAPTOP-18GI5NJH | AA61: TAMBIENTAL | AB61: Mar 10 2022 6:41PM
A62: 138020001 | B62: REINTEGRO DE INCAPACIDADES | C62: 44576 | D62: 21 | E62: NOMINA NOVASOFT | G62: 000000004 | H62: GASTOS REEMBOLSABLES | I62: 33334 | J62: 0 | K62: 1 | L62: 9288712 | M62: RAFAEL DE JESUS PUELLO HUETO | N62: 10030400 | O62: OPERADORES | R62: 0 | S62: CONTABLE | T62: N | U62: 000000004 | V62: 0 | W62: TAAUXCON | X62: Mar 10 2022 6:41PM | Y62: frmCON6093 | Z62: LAPTOP-18GI5NJH | AA62: TAMBIENTAL | AB62: Mar 10 2022 6:41PM
A63: 138020001 | B63: REINTEGRO DE INCAPACIDADES | C63: 44576 | D63: 21 | E63: NOMINA NOVASOFT | G63: 000000004 | H63: GASTOS REEMBOLSABLES | I63: 33334 | J63: 0 | K63: 1 | L63: 1002059942 | M63: WILSON RAFAEL SIMANCAS MARTINEZ | N63: 10030400 | O63: OPERADORES | R63: 0 | S63: CONTABLE | T63: N | U63: 000000004 | V63: 0 | W63: TAAUXCON | X63: Mar 10 2022 6:41PM | Y63: frmCON6093 | Z63: LAPTOP-18GI5NJH | AA63: TAMBIENTAL | AB63: Mar 10 2022 6:41PM
A64: 138020001 | B64: REINTEGRO DE INCAPACIDADES | C64: 44576 | D64: 21 | E64: NOMINA NOVASOFT | G64: 000000004 | H64: GASTOS REEMBOLSABLES | I64: 500000 | J64: 0 | K64: 1 | L64: 1047370459 | M64: JOSE AUGUSTO ARZUZA MARRUGO | N64: 10030400 | O64: OPERADORES | R64: 0 | S64: CONTABLE | T64: N | U64: 000000004 | V64: 0 | W64: TAAUXCON | X64: Mar 10 2022 6:41PM | Y64: frmCON6093 | Z64: LAPTOP-18GI5NJH | AA64: TAMBIENTAL | AB64: Mar 10 2022 6:41PM
A65: 138020001 | B65: REINTEGRO DE INCAPACIDADES | C65: 44576 | D65: 21 | E65: NOMINA NOVASOFT | G65: 000000004 | H65: GASTOS REEMBOLSABLES | I65: 37832 | J65: 0 | K65: 1 | L65: 1047364807 | M65: ALEJANDRO LUIS PEREZ PEDROZA | N65: 10030400 | O65: OPERADORES | R65: 0 | S65: CONTABLE | T65: N | U65: 000000004 | V65: 0 | W65: TAAUXCON | X65: Mar 10 2022 6:41PM | Y65: frmCON6093 | Z65: LAPTOP-18GI5NJH | AA65: TAMBIENTAL | AB65: Mar 10 2022 6:41PM
A66: 138020001 | B66: REINTEGRO DE INCAPACIDADES | C66: 44576 | D66: 21 | E66: NOMINA NOVASOFT | G66: 000000004 | H66: GASTOS REEMBOLSABLES | I66: 35677 | J66: 0 | K66: 1 | L66: 1049532983 | M66: PEDRO MANUEL MUÑIZ PADILLA | N66: 10030400 | O66: OPERADORES | R66: 0 | S66: CONTABLE | T66: N | U66: 000000004 | V66: 0 | W66: TAAUXCON | X66: Mar 10 2022 6:41PM | Y66: frmCON6093 | Z66: LAPTOP-18GI5NJH | AA66: TAMBIENTAL | AB66: Mar 10 2022 6:41PM
A67: 138020001 | B67: REINTEGRO DE INCAPACIDADES | C67: 44576 | D67: 21 | E67: NOMINA NOVASOFT | G67: 000000004 | H67: GASTOS REEMBOLSABLES | I67: 33856 | J67: 0 | K67: 1 | L67: 1137220216 | M67: TONNY JAYR ESTREMOR SALCEDO | N67: 10030400 | O67: OPERADORES | R67: 0 | S67: CONTABLE | T67: N | U67: 000000004 | V67: 0 | W67: TAAUXCON | X67: Mar 10 2022 6:41PM | Y67: frmCON6093 | Z67: LAPTOP-18GI5NJH | AA67: TAMBIENTAL | AB67: Mar 10 2022 6:41PM
A68: 138020001 | B68: REINTEGRO DE INCAPACIDADES | C68: 44576 | D68: 21 | E68: NOMINA NOVASOFT | G68: 000000004 | H68: GASTOS REEMBOLSABLES | I68: 500000 | J68: 0 | K68: 1 | L68: 73103777 | M68: RAMON CORREA GARCIA | N68: 10030400 | O68: OPERADORES | R68: 0 | S68: CONTABLE | T68: N | U68: 000000004 | V68: 0 | W68: TAAUXCON | X68: Mar 10 2022 6:41PM | Y68: frmCON6093 | Z68: LAPTOP-18GI5NJH | AA68: TAMBIENTAL | AB68: Mar 10 2022 6:41PM
... A82: 138020001 | B82: REINTEGRO DE INCAPACIDADES | C82: 44576 | D82: 21 | E82: NOMINA NOVASOFT | G82: 000000004 | H82: GASTOS REEMBOLSABLES | I82: 233334 | J82: 0 | K82: 1 | L82: 1047495774 | M82: LUVIS STELLA ZARZA REYES | N82: 10050400 | O82: SALUD OCUPACIONAL | R82: 0 | S82: CONTABLE | T82: N | U82: 000000004 | V82: 0 | W82: TAAUXCON | X82: Mar 10 2022 6:41PM | Y82: frmCON6093 | Z82: LAPTOP-18GI5NJH | AA82: TAMBIENTAL | AB82: Mar 10 2022 6:41PM
A83: 138020001 | B83: REINTEGRO DE INCAPACIDADES | C83: 44581 | D83: 15 | E83: CONSIGNACIONES BANCO | G83: 000000033 | H83: SALUD TOTAL S.A. EPS ARS:REINTEGRO INCAPACIDADES000000033 | I83: 0 | J83: 31475 | K83: 1 | L83: 800130907 | M83: SALUD TOTAL S.A. EPS ARS | R83: 0 | S83: CONTABLE | T83: N | U83: 000000033 | V83: 0 | W83: TACOTESO | X83: Feb 24 2022 6:04PM | Y83: frmBAN607 | Z83: DESKTOP-O60S49G | AA83: TAMBIENTAL | AB83: Feb 24 2022 6:04PM
A84: 138020001 | B84: REINTEGRO DE INCAPACIDADES | C84: 44581 | D84: 15 | E84: CONSIGNACIONES BANCO | G84: 000000034 | H84: SALUD TOTAL S.A. EPS ARS:REINTEGRO INCAPACIDADES000000034 | I84: 0 | J84: 423976 | K84: 1 | L84: 800130907 | M84: SALUD TOTAL S.A. EPS ARS | R84: 0 | S84: CONTABLE | T84: N | U84: 000000034 | V84: 0 | W84: TACOTESO | X84: Feb 24 2022 6:05PM | Y84: frmBAN607 | Z84: DESKTOP-O60S49G | AA84: TAMBIENTAL | AB84: Feb 24 2022 6:05PM
A85: 138020001 | B85: REINTEGRO DE INCAPACIDADES | C85: 44581 | D85: 15 | E85: CONSIGNACIONES BANCO | G85: 000000035 | H85: EPS SURA COMPAÑIA SURAMERICANA SERVICIOS DE SALUD:REINTEGRO INCAPACIDADES000000035 | I85: 0 | J85: 30284 | K85: 1 | L85: 800088702 | M85: EPS SURA COMPAÑIA SURAMERICANA SERVICIOS DE SALUD | R85: 0 | S85: CONTABLE | T85: N | U85: 000000035 | V85: 0 | W85: TACOTESO | X85: Feb 24 2022 6:06PM | Y85: frmBAN607 | Z85: DESKTOP-O60S49G | AA85: TAMBIENTAL | AB85: Feb 24 2022 6:06PM
A86: 138020001 | B86: REINTEGRO DE INCAPACIDADES | C86: 44585 | D86: 15 | E86: CONSIGNACIONES BANCO | G86: 000000025 | H86: SALUD TOTAL S.A. EPS ARS:REINTEGRO INCAPACIDADES000000025 | I86: 0 | J86: 33623 | K86: 1 | L86: 800130907 | M86: SALUD TOTAL S.A. EPS ARS | R86: 0 | S86: CONTABLE | T86: N | U86: 000000025 | V86: 0 | W86: TACOTESO | X86: Feb 24 2022 5:52PM | Y86: frmBAN607 | Z86: DESKTOP-O60S49G | AA86: TAMBIENTAL | AB86: Feb 24 2022 5:52PM
A87: 138020001 | B87: REINTEGRO DE INCAPACIDADES | C87: 44585 | D87: 15 | E87: CONSIGNACIONES BANCO | G87: 000000026 | H87: SALUD TOTAL S.A. EPS ARS:REINTEGRO INCAPACIDADES000000026 | I87: 0 | J87: 87781 | K87: 1 | L87: 800130907 | M87: SALUD TOTAL S.A. EPS ARS | R87: 0 | S87: CONTABLE | T87: N | U87: 000000026 | V87: 0 | W87: TACOTESO | X87: Feb 24 2022 5:55PM | Y87: frmBAN607 | Z87: DESKTOP-O60S49G | AA87: TAMBIENTAL | AB87: Feb 24 2022 5:55PM
A88: 138020001 | B88: REINTEGRO DE INCAPACIDADES | C88: 44585 | D88: 15 | E88: CONSIGNACIONES BANCO | G88: 000000027 | H88: SALUD TOTAL S.A. EPS ARS:REINTEGRO INCAPACIDADES000000027 | I88: 0 | J88: 29261 | K88: 1 | L88: 800130907 | M88: SALUD TOTAL S.A. EPS ARS | R88: 0 | S88: CONTABLE | T88: N | U88: 000000027 | V88: 0 | W88: TACOTESO | X88: Feb 24 2022 5:56PM | Y88: frmBAN607 | Z88: DESKTOP-O60S49G | AA88: TAMBIENTAL | AB88: Feb 24 2022 5:56PM
A89: 138020001 | B89: REINTEGRO DE INCAPACIDADES | C89: 44585 | D89: 15 | E89: CONSIGNACIONES BANCO | G89: 000000028 | H89: COOSALUD ENTIDAD PROMOTORA DE SALUD S.A:REINTEGRO INCAPACIDADES000000028 | I89: 0 | J89: 36615 | K89: 1 | L89: 900226715 | M89: COOSALUD ENTIDAD PROMOTORA DE SALUD S.A | R89: 0 | S89: CONTABLE | T89: N | U89: 000000028 | V89: 0 | W89: TACOTESO | X89: Feb 24 2022 5:57PM | Y89: frmBAN607 | Z89: DESKTOP-O60S49G | AA89: TAMBIENTAL | AB89: Feb 24 2022 5:57PM
A90: 138020001 | B90: REINTEGRO DE INCAPACIDADES | C90: 44585 | D90: 15 | E90: CONSIGNACIONES BANCO | G90: 000000029 | H90: COOSALUD ENTIDAD PROMOTORA DE SALUD S.A:REINTEGRO INCAPACIDADES000000029 | I90: 0 | J90: 29261 | K90: 1 | L90: 900226715 | M90: COOSALUD ENTIDAD PROMOTORA DE SALUD S.A | R90: 0 | S90: CONTABLE | T90: N | U90: 000000029 | V90: 0 | W90: TACOTESO | X90: Feb 24 2022 5:59PM | Y90: frmBAN607 | Z90: DESKTOP-O60S49G | AA90: TAMBIENTAL | AB90: Feb 24 2022 5:59PM
A91: 138020001 | B91: REINTEGRO DE INCAPACIDADES | C91: 44585 | D91: 15 | E91: CONSIGNACIONES BANCO | G91: 000000030 | H91: COOSALUD ENTIDAD PROMOTORA DE SALUD S.A:REINTEGRO INCAPACIDADES000000030 | I91: 0 | J91: 175561 | K91: 1 | L91: 900226715 | M91: COOSALUD ENTIDAD PROMOTORA DE SALUD S.A | R91: 0 | S91: CONTABLE | T91: N | U91: 000000030 | V91: 0 | W91: TACOTESO | X91: Feb 24 2022 6:00PM | Y91: frmBAN607 | Z91: DESKTOP-O60S49G | AA91: TAMBIENTAL | AB91: Feb 24 2022 6:00PM
A92: 138020001 | B92: REINTEGRO DE INCAPACIDADES | C92: 44585 | D92: 15 | E92: CONSIGNACIONES BANCO | G92: 000000031 | H92: COOSALUD ENTIDAD PROMOTORA DE SALUD S.A:REINTEGRO INCAPACIDADES000000031 | I92: 0 | J92: 46895 | K92: 1 | L92: 900226715 | M92: COOSALUD ENTIDAD PROMOTORA DE SALUD S.A | R92: 0 | S92: CONTABLE | T92: N | U92: 000000031 | V92: 0 | W92: TACOTESO | X92: Feb 24 2022 6:01PM | Y92: frmBAN607 | Z92: DESKTOP-O60S49G | AA92: TAMBIENTAL | AB92: Feb 24 2022 6:01PM
A93: 138020001 | B93: REINTEGRO DE INCAPACIDADES | C93: 44585 | D93: 15 | E93: CONSIGNACIONES BANCO | G93: 000000032 | H93: COOSALUD ENTIDAD PROMOTORA DE SALUD S.A:REINTEGRO INCAPACIDADES000000032 | I93: 0 | J93: 34280 | K93: 1 | L93: 900226715 | M93: COOSALUD ENTIDAD PROMOTORA DE SALUD S.A | R93: 0 | S93: CONTABLE | T93: N | U93: 000000032 | V93: 0 | W93: TACOTESO | X93: Feb 24 2022 6:03PM | Y93: frmBAN607 | Z93: DESKTOP-O60S49G | AA93: TAMBIENTAL | AB93: Feb 24 2022 6:03PM
A94: 138020001 | B94: REINTEGRO DE INCAPACIDADES | C94: 44586 | D94: 15 | E94: CONSIGNACIONES BANCO | G94: 000000024 | H94: SALUD TOTAL S.A. EPS ARS:REINTEGRO INCAPACIDADES000000024 | I94: 0 | J94: 371086 | K94: 1 | L94: 800130907 | M94: SALUD TOTAL S.A. EPS ARS | R94: 0 | S94: CONTABLE | T94: N | U94: 000000024 | V94: 0 | W94: TACOTESO | X94: Feb 24 2022 5:50PM | Y94: frmBAN607 | Z94: DESKTOP-O60S49G | AA94: TAMBIENTAL | AB94: Feb 24 2022 5:50PM
A95: 138020001 | B95: REINTEGRO DE INCAPACIDADES | C95: 44588 | D95: 15 | E95: CONSIGNACIONES BANCO | G95: 000000023 | H95: SALUD TOTAL S.A. EPS ARS:REINTEGRO INCAPACIDADES000000023 | I95: 0 | J95: 969509 | K95: 1 | L95: 800130907 | M95: SALUD TOTAL S.A. EPS ARS | R95: 0 | S95: CONTABLE | T95: N | U95: 000000023 | V95: 0 | W95: TACOTESO | X95: Feb 24 2022 5:49PM | Y95: frmBAN607 | Z95: DESKTOP-O60S49G | AA95: TAMBIENTAL | AB95: Feb 24 2022 5:49PM
A96: 138020001 | B96: REINTEGRO DE INCAPACIDADES | C96: 44592 | D96: 21 | E96: NOMINA NOVASOFT | G96: 000000005 | H96: GASTOS REEMBOLSABLES | I96: 306355 | J96: 0 | K96: 1 | L96: 1047447036 | M96: LAURA ESPITALETA NARVAEZ | N96: 10000100 | O96: JURIDICA | R96: 0 | S96: CONTABLE | T96: N | U96: 000000005 | V96: 0 | W96: TAAUXCON | X96: Mar 10 2022 6:45PM | Y96: frmCON6093 | Z96: LAPTOP-18GI5NJH | AA96: TAMBIENTAL | AB96: Mar 10 2022 6:45PM
A97: 138020001 | B97: REINTEGRO DE INCAPACIDADES | C97: 44592 | D97: 21 | E97: NOMINA NOVASOFT | G97: 000000005 | H97: GASTOS REEMBOLSABLES | I97: 270801 | J97: 0 | K97: 1 | L97: 72073849 | M97: DORIAN RODRIGUEZ OSPINO | N97: 10030400 | O97: OPERADORES | R97: 0 | S97: CONTABLE | T97: N | U97: 000000005 | V97: 0 | W97: TAAUXCON | X97: Mar 10 2022 6:45PM | Y97: frmCON6093 | Z97: LAPTOP-18GI5NJH | AA97: TAMBIENTAL | AB97: Mar 10 2022 6:45PM
A98: 138020001 | B98: REINTEGRO DE INCAPACIDADES | C98: 44592 | D98: 21 | E98: NOMINA NOVASOFT | G98: 000000005 | H98: GASTOS REEMBOLSABLES | I98: 33334 | J98: 0 | K98: 1 | L98: 73130242 | M98: RAYMUNDO SANJUAN MERCADO | N98: 10030400 | O98: OPERADORES | R98: 0 | S98: CONTABLE | T98: N | U98: 000000005 | V98: 0 | W98: TAAUXCON | X98: Mar 10 2022 6:45PM | Y98: frmCON6093 | Z98: LAPTOP-18GI5NJH | AA98: TAMBIENTAL | AB98: Mar 10 2022 6:45PM
A99: 138020001 | B99: REINTEGRO DE INCAPACIDADES | C99: 44592 | D99: 21 | E99: NOMINA NOVASOFT | G99: 000000005 | H99: GASTOS REEMBOLSABLES | I99: 166667 | J99: 0 | K99: 1 | L99: 1047370459 | M99: JOSE AUGUSTO ARZUZA MARRUGO | N99: 10030400 | O99: OPERADORES | R99: 0 | S99: CONTABLE | T99: N | U99: 000000005 | V99: 0 | W99: TAAUXCON | X99: Mar 10 2022 6:45PM | Y99: frmCON6093 | Z99: LAPTOP-18GI5NJH | AA99: TAMBIENTAL | AB99: Mar 10 2022 6:45PM
A100: 138020001 | B100: REINTEGRO DE INCAPACIDADES | C100: 44592 | D100: 21 | E100: NOMINA NOVASOFT | G100: 000000005 | H100: GASTOS REEMBOLSABLES | I100: 33334 | J100: 0 | K100: 1 | L100: 73121602 | M100: ELKIN YOUSEF CHAR NEGRETE | N100: 10030400 | O100: OPERADORES | R100: 0 | S100: CONTABLE | T100: N | U100: 000000005 | V100: 0 | W100: TAAUXCON | X100: Mar 10 2022 6:45PM | Y100: frmCON6093 | Z100: LAPTOP-18GI5NJH | AA100: TAMBIENTAL | AB100: Mar 10 2022 6:45PM
A101: 138020001 | B101: REINTEGRO DE INCAPACIDADES | C101: 44592 | D101: 21 | E101: NOMINA NOVASOFT | G101: 000000005 | H101: GASTOS REEMBOLSABLES | I101: 101621 | J101: 0 | K101: 1 | L101: 73186816 | M101: JAMER GUSTAVO BENITEZ CHICA | N101: 10030400 | O101: OPERADORES | R101: 0 | S101: CONTABLE | T101: N | U101: 000000005 | V101: 0 | W101: TAAUXCON | X101: Mar 10 2022 6:45PM | Y101: frmCON6093 | Z101: LAPTOP-18GI5NJH | AA101: TAMBIENTAL | AB101: Mar 10 2022 6:45PM
A102: 138020001 | B102: REINTEGRO DE INCAPACIDADES | C102: 44592 | D102: 21 | E102: NOMINA NOVASOFT | G102: 000000005 | H102: GASTOS REEMBOLSABLES | I102: 33476 | J102: 0 | K102: 1 | L102: 73575088 | M102: WILLIAN EMILIO TIRADO SILVA | N102: 10030400 | O102: OPERADORES | R102: 0 | S102: CONTABLE | T102: N | U102: 000000005 | V102: 0 | W102: TAAUXCON | X102: Mar 10 2022 6:45PM | Y102: frmCON6093 | Z102: LAPTOP-18GI5NJH | AA102: TAMBIENTAL | AB102: Mar 10 2022 6:45PM
A103: 138020001 | B103: REINTEGRO DE INCAPACIDADES | C103: 44592 | D103: 21 | E103: NOMINA NOVASOFT | G103: 000000005 | H103: GASTOS REEMBOLSABLES | I103: 33334 | J103: 0 | K103: 1 | L103: 9186477 | M103: AVILA JHONATAN ALZUZAR DE | N103: 10030400 | O103: OPERADORES | R103: 0 | S103: CONTABLE | T103: N | U103: 000000005 | V103: 0 | W103: TAAUXCON | X103: Mar 10 2022 6:45PM | Y103: frmCON6093 | Z103: LAPTOP-18GI5NJH | AA103: TAMBIENTAL | AB103: Mar 10 2022 6:45PM
A104: 138020001 | B104: REINTEGRO DE INCAPACIDADES | C104: 44592 | D104: 21 | E104: NOMINA NOVASOFT | G104: 000000005 | H104: GASTOS REEMBOLSABLES | I104: 249742 | J104: 0 | K104: 1 | L104: 1049532983 | M104: PEDRO MANUEL MUÑIZ PADILLA | N104: 10030400 | O104: OPERADORES | R104: 0 | S104: CONTABLE | T104: N | U104: 000000005 | V104: 0 | W104: TAAUXCON | X104: Mar 10 2022 6:45PM | Y104: frmCON6093 | Z104: LAPTOP-18GI5NJH | AA104: TAMBIENTAL | AB104: Mar 10 2022 6:45PM
A105: 138020001 | B105: REINTEGRO DE INCAPACIDADES | C105: 44592 | D105: 21 | E105: NOMINA NOVASOFT | G105: 000000005 | H105: GASTOS REEMBOLSABLES | I105: 266668 | J105: 0 | K105: 1 | L105: 73103777 | M105: RAMON CORREA GARCIA | N105: 10030400 | O105: OPERADORES | R105: 0 | S105: CONTABLE | T105: N | U105: 000000005 | V105: 0 | W105: TAAUXCON | X105: Mar 10 2022 6:45PM | Y105: frmCON6093 | Z105: LAPTOP-18GI5NJH | AA105: TAMBIENTAL | AB105: Mar 10 2022 6:45PM
A106: 138020001 | B106: REINTEGRO DE INCAPACIDADES | C106: 44592 | D106: 21 | E106: NOMINA NOVASOFT | G106: 000000005 | H106: GASTOS REEMBOLSABLES | I106: 35019 | J106: 0 | K106: 1 | L106: 92031290 | M106: JORGE DAVID BOLAÑO VILLAMIL | N106: 10030400 | O106: OPERADORES | R106: 0 | S106: CONTABLE | T106: N | U106: 000000005 | V106: 0 | W106: TAAUXCON | X106: Mar 10 2022 6:45PM | Y106: frmCON6093 | Z106: LAPTOP-18GI5NJH | AA106: TAMBIENTAL | AB106: Mar 10 2022 6:45PM
A107: 138020001 | B107: REINTEGRO DE INCAPACIDADES | C107: 44592 | D107: 21 | E107: NOMINA NOVASOFT | G107: 000000005 | H107: GASTOS REEMBOLSABLES | I107: 327939 | J107: 0 | K107: 1 | L107: 10885706 | M107: RAFAEL ENRIQUE CUELLO LORA | N107: 10030400 | O107: OPERADORES | R107: 0 | S107: CONTABLE | T107: N | U107: 000000005 | V107: 0 | W107: TAAUXCON | X107: Mar 10 2022 6:45PM | Y107: frmCON6093 | Z107: LAPTOP-18GI5NJH | AA107: TAMBIENTAL | AB107: Mar 10 2022 6:45PM
... A110: 138020001 | B110: REINTEGRO DE INCAPACIDADES | C110: 44592 | D110: 21 | E110: NOMINA NOVASOFT | G110: 000000005 | H110: GASTOS REEMBOLSABLES | I110: 103074 | J110: 0 | K110: 1 | L110: 12595533 | M110: LUIS ALFONSO MEDINA OCHOA | N110: 10030400 | O110: OPERADORES | R110: 0 | S110: CONTABLE | T110: N | U110: 000000005 | V110: 0 | W110: TAAUXCON | X110: Mar 10 2022 6:45PM | Y110: frmCON6093 | Z110: LAPTOP-18GI5NJH | AA110: TAMBIENTAL | AB110: Mar 10 2022 6:45PM
A111: 138020001 | B111: REINTEGRO DE INCAPACIDADES | C111: 44595 | D111: 15 | E111: CONSIGNACIONES BANCO | G111: 000000056 | H111: EPS SURA COMPAÑIA SURAMERICANA SERVICIOS DE SALUD:Reintegro incapacidad000000056 | I111: 0 | J111: 306602 | K111: 1 | L111: 800088702 | M111: EPS SURA COMPAÑIA SURAMERICANA SERVICIOS DE SALUD | R111: 0 | S111: CONTABLE | T111: N | U111: 000000056 | V111: 0 | W111: TACOTESO | X111: Mar 17 2022 5:13PM | Y111: frmBAN607 | Z111: DESKTOP-O60S49G | AA111: TAMBIENTAL | AB111: Mar 17 2022 5:13PM
A112: 138020001 | B112: REINTEGRO DE INCAPACIDADES | C112: 44601 | D112: 15 | E112: CONSIGNACIONES BANCO | G112: 000000054 | H112: NUEVA EMPRESA PROMOTORA DE SALUD:Reintegro incapacidad000000054 | I112: 0 | J112: 33804 | K112: 1 | L112: 900156264 | M112: NUEVA EMPRESA PROMOTORA DE SALUD | R112: 0 | S112: CONTABLE | T112: N | U112: 000000054 | V112: 0 | W112: TACOTESO | X112: Mar 17 2022 5:10PM | Y112: frmBAN607 | Z112: DESKTOP-O60S49G | AA112: TAMBIENTAL | AB112: Mar 17 2022 5:10PM
A113: 138020001 | B113: REINTEGRO DE INCAPACIDADES | C113: 44601 | D113: 15 | E113: CONSIGNACIONES BANCO | G113: 000000055 | H113: NUEVA EMPRESA PROMOTORA DE SALUD:Reintegro incapacidad000000055 | I113: 0 | J113: 1346338 | K113: 1 | L113: 900156264 | M113: NUEVA EMPRESA PROMOTORA DE SALUD | R113: 0 | S113: CONTABLE | T113: N | U113: 000000055 | V113: 0 | W113: TACOTESO | X113: Mar 17 2022 5:11PM | Y113: frmBAN607 | Z113: DESKTOP-O60S49G | AA113: TAMBIENTAL | AB113: Mar 17 2022 5:11PM
A114: 138020001 | B114: REINTEGRO DE INCAPACIDADES | C114: 44607 | D114: 15 | E114: CONSIGNACIONES BANCO | G114: 000000051 | H114: EPS SURA COMPAÑIA SURAMERICANA SERVICIOS DE SALUD:Reintegro incapacidad000000051 | I114: 0 | J114: 100000 | K114: 1 | L114: 800088702 | M114: EPS SURA COMPAÑIA SURAMERICANA SERVICIOS DE SALUD | R114: 0 | S114: CONTABLE | T114: N | U114: 000000051 | V114: 0 | W114: TACOTESO | X114: Mar 17 2022 5:06PM | Y114: frmBAN607 | Z114: DESKTOP-O60S49G | AA114: TAMBIENTAL | AB114: Mar 17 2022 5:06PM
A115: 138020001 | B115: REINTEGRO DE INCAPACIDADES | C115: 44607 | D115: 15 | E115: CONSIGNACIONES BANCO | G115: 000000052 | H115: COOSALUD ENTIDAD PROMOTORA DE SALUD S.A:Reintegro incapacidad000000052 | I115: 0 | J115: 31974 | K115: 1 | L115: 900226715 | M115: COOSALUD ENTIDAD PROMOTORA DE SALUD S.A | R115: 0 | S115: CONTABLE | T115: N | U115: 000000052 | V115: 0 | W115: TACOTESO | X115: Mar 17 2022 5:07PM | Y115: frmBAN607 | Z115: DESKTOP-O60S49G | AA115: TAMBIENTAL | AB115: Mar 17 2022 5:07PM
A116: 138020001 | B116: REINTEGRO DE INCAPACIDADES | C116: 44607 | D116: 15 | E116: CONSIGNACIONES BANCO | G116: 000000053 | H116: COOSALUD ENTIDAD PROMOTORA DE SALUD S.A:Reintegro incapacidad000000053 | I116: 0 | J116: 32439 | K116: 1 | L116: 900226715 | M116: COOSALUD ENTIDAD PROMOTORA DE SALUD S.A | R116: 0 | S116: CONTABLE | T116: N | U116: 000000053 | V116: 0 | W116: TACOTESO | X116: Mar 17 2022 5:08PM | Y116: frmBAN607 | Z116: DESKTOP-O60S49G | AA116: TAMBIENTAL | AB116: Mar 17 2022 5:08PM
A117: 138020001 | B117: REINTEGRO DE INCAPACIDADES | C117: 44617 | D117: 15 | E117: CONSIGNACIONES BANCO | G117: 000000050 | H117: COOSALUD ENTIDAD PROMOTORA DE SALUD S.A:Reintegro incapacidad000000050 | I117: 0 | J117: 411927 | K117: 1 | L117: 900226715 | M117: COOSALUD ENTIDAD PROMOTORA DE SALUD S.A | R117: 0 | S117: CONTABLE | T117: N | U117: 000000050 | V117: 0 | W117: TACOTESO | X117: Mar 17 2022 5:04PM | Y117: frmBAN607 | Z117: DESKTOP-O60S49G | AA117: TAMBIENTAL | AB117: Mar 17 2022 5:04PM
A118: 138020001 | B118: REINTEGRO DE INCAPACIDADES | C118: 44620 | D118: 15 | E118: CONSIGNACIONES BANCO | G118: 000000049 | H118: COOSALUD ENTIDAD PROMOTORA DE SALUD S.A:Reintegro incapacidad000000049 | I118: 0 | J118: 151422 | K118: 1 | L118: 900226715 | M118: COOSALUD ENTIDAD PROMOTORA DE SALUD S.A | R118: 0 | S118: CONTABLE | T118: N | U118: 000000049 | V118: 0 | W118: TACOTESO | X118: Mar 17 2022 5:03PM | Y118: frmBAN607 | Z118: DESKTOP-O60S49G | AA118: TAMBIENTAL | AB118: Mar 17 2022 5:03PM
A119: 138020001 | B119: REINTEGRO DE INCAPACIDADES | C119: 44620 | D119: 21 | E119: NOMINA NOVASOFT | G119: 000000006 | H119: GASTOS REEMBOLSABLES | I119: 33334 | J119: 0 | K119: 1 | L119: 73202722 | M119: JESUS JAVIER BELTRAN OLIVELLA | N119: 10030400 | O119: OPERADORES | R119: 0 | S119: CONTABLE | T119: N | U119: 000000006 | V119: 0 | W119: TACOSITI | X119: Mar 25 2022 6:22PM | Y119: frmCON6093 | Z119: DESKTOP-5900GRN | AA119: TAMBIENTAL | AB119: Mar 25 2022 6:22PM
A120: 138020001 | B120: REINTEGRO DE INCAPACIDADES | C120: 44620 | D120: 21 | E120: NOMINA NOVASOFT | G120: 000000006 | H120: GASTOS REEMBOLSABLES | I120: 500000 | J120: 0 | K120: 1 | L120: 1047370459 | M120: JOSE AUGUSTO ARZUZA MARRUGO | N120: 10030400 | O120: OPERADORES | R120: 0 | S120: CONTABLE | T120: N | U120: 000000006 | V120: 0 | W120: TACOSITI | X120: Mar 25 2022 6:22PM | Y120: frmCON6093 | Z120: DESKTOP-5900GRN | AA120: TAMBIENTAL | AB120: Mar 25 2022 6:22PM
A121: 138020001 | B121: REINTEGRO DE INCAPACIDADES | C121: 44620 | D121: 21 | E121: NOMINA NOVASOFT | G121: 000000006 | H121: GASTOS REEMBOLSABLES | I121: 34963 | J121: 0 | K121: 1 | L121: 73106822 | M121: DECHAMPS MORALES MANUEL CARMELO | N121: 10030400 | O121: OPERADORES | R121: 0 | S121: CONTABLE | T121: N | U121: 000000006 | V121: 0 | W121: TACOSITI | X121: Mar 25 2022 6:22PM | Y121: frmCON6093 | Z121: DESKTOP-5900GRN | AA121: TAMBIENTAL | AB121: Mar 25 2022 6:22PM
...

Sheet BD 2021 - 2025 (2)
A1: SUBSISTEMA DE CONTABILIDAD
A2: TRANSAMBIENTAL S.A.S.
A3: CONSULTA DE MOVIMIENTO POR FUENTES A 10.SEPT./2025
A4: PERIODO COMPRENDIDO ENTRE 01.ENE./2021 Y 31.JUL./2025 | I4: =SUBTOTAL(9,I7:I10000) -> 13913038 | J4: =SUBTOTAL(9,J7:J10000) -> 13375282 | K4: =+I4-J4 -> 537756
A6: Codigo Cuenta | B6: Nombre Cuenta | C6: Fecha Documento | D6: Fuente | E6: Nombre Fuente | F6: Prefijo Documento | G6: Numero Documento | H6: Detalle del Registro | I6: Valor Debito | J6: Valor Credito | K6: Tipo Anexo | L6: Id.Tercero | M6: Nombre Tercero | N6: Codigo Costo | O6: Nombre Costo | P6: Codigo Retencion | Q6: Concepto Retencion | R6: Base Retencion | S6: Tipo Libro | T6: Asiento Cierre | U6: Documento Referencia | V6: Numero Cheque | W6: Codigo Operacion | X6: Fecha Operacion | Y6: Programa | Z6: Estacion | AA6: Empresa | AB6: Fecha Version | AC6: Estado Reg.
A7: 138020001 | B7: REINTEGRO DE INCAPACIDADES | C7: 44530 | D7: 99 | E7: SALDOS INICIALES | G7: 000000001 | H7: REINTEGRO DE INCAPACIDADES | I7: 38623261 | J7: 0 | K7: 1 | L7: 900771273 | M7: TRANSAMBIENTAL | R7: 0 | S7: CONTABLE | T7: N | U7: 000000001 | V7: 0 | W7: TACOSITI | X7: Feb 8 2022 4:17AM | Y7: frmCON6093 | Z7: DESKTOP-5900GRN | AA7: TAMBIENTAL | AB7: Feb 8 2022 4:17AM
A8: 138020001 | B8: REINTEGRO DE INCAPACIDADES | C8: 44532 | D8: 15 | E8: CONSIGNACIONES BANCO | G8: 000000010 | H8: EPS SURA COMPAÑIA SURAMERICANA SERVICIOS DE SALUD:REINTEGRO INCAPACIDAD SURAMERICANA000000010 | I8: 0 | J8: 262479 | K8: 1 | L8: 800088702 | M8: EPS SURA COMPAÑIA SURAMERICANA SERVICIOS DE SALUD | R8: 0 | S8: CONTABLE | T8: N | U8: 000000010 | V8: 0 | W8: TACOTESO | X8: Ene 14 2022 5:20PM | Y8: frmBAN607 | Z8: DESKTOP-O60S49G | AA8: TAMBIENTAL | AB8: Ene 14 2022 5:20PM
A9: 138020001 | B9: REINTEGRO DE INCAPACIDADES | C9: 44532 | D9: 15 | E9: CONSIGNACIONES BANCO | G9: 000000011 | H9: SALUD TOTAL S.A. EPS ARS:REINTEGRO INCAPACIDAD SALUD TOTAL000000011 | I9: 0 | J9: 428175 | K9: 1 | L9: 800130907 | M9: SALUD TOTAL S.A. EPS ARS | R9: 0 | S9: CONTABLE | T9: N | U9: 000000011 | V9: 0 | W9: TACOTESO | X9: Ene 14 2022 5:27PM | Y9: frmBAN607 | Z9: DESKTOP-O60S49G | AA9: TAMBIENTAL | AB9: Ene 14 2022 5:27PM
A10: 138020001 | B10: REINTEGRO DE INCAPACIDADES | C10: 44540 | D10: 15 | E10: CONSIGNACIONES BANCO | G10: 000000007 | H10: SALUD TOTAL S.A. EPS ARS:REINTEGRO INCAPACIDAD SALUD TOTAL000000007 | I10: 0 | J10: 1535787 | K10: 1 | L10: 800130907 | M10: SALUD TOTAL S.A. EPS ARS | R10: 0 | S10: CONTABLE | T10: N | U10: 000000007 | V10: 0 | W10: TACOTESO | X10: Ene 14 2022 4:39PM | Y10: frmBAN607 | Z10: DESKTOP-O60S49G | AA10: TAMBIENTAL | AB10: Ene 14 2022 4:39PM
A11: 138020001 | B11: REINTEGRO DE INCAPACIDADES | C11: 44540 | D11: 15 | E11: CONSIGNACIONES BANCO | G11: 000000008 | H11: NUEVA EMPRESA PROMOTORA DE SALUD:REINTEGRO INCAPACIDAD NUEVA EPS000000008 | I11: 0 | J11: 195079 | K11: 1 | L11: 900156264 | M11: NUEVA EMPRESA PROMOTORA DE SALUD | R11: 0 | S11: CONTABLE | T11: N | U11: 000000008 | V11: 0 | W11: TACOTESO | X11: Ene 14 2022 4:41PM | Y11: frmBAN607 | Z11: DESKTOP-O60S49G | AA11: TAMBIENTAL | AB11: Ene 14 2022 4:41PM
A12: 138020001 | B12: REINTEGRO DE INCAPACIDADES | C12: 44545 | D12: 21 | E12: NOMINA NOVASOFT | G12: 000000001 | H12: GASTOS REEMBOLSABLES | I12: 42866 | J12: 0 | K12: 1 | L12: 800088702 | M12: EPS SURA COMPAÑIA SURAMERICANA SERVICIOS DE SALUD | N12: 10010200 | O12: COMPRAS Y ABASTESIMIENTO | R12: 0 | S12: CONTABLE | T12: N | U12: 000000001 | V12: 0 | W12: TACOSITI | X12: Feb 8 2022 5:24PM | Y12: frmCON6093 | Z12: DESKTOP-5900GRN | AA12: TAMBIENTAL | AB12: Feb 8 2022 5:24PM
A13: 138020001 | B13: REINTEGRO DE INCAPACIDADES | C13: 44545 | D13: 21 | E13: NOMINA NOVASOFT | G13: 000000001 | H13: GASTOS REEMBOLSABLES | I13: 30284 | J13: 0 | K13: 1 | L13: 800088702 | M13: EPS SURA COMPAÑIA SURAMERICANA SERVICIOS DE SALUD | N13: 10020200 | O13: EJECUCIÓN | R13: 0 | S13: CONTABLE | T13: N | U13: 000000001 | V13: 0 | W13: TACOSITI | X13: Feb 8 2022 5:24PM | Y13: frmCON6093 | Z13: DESKTOP-5900GRN | AA13: TAMBIENTAL | AB13: Feb 8 2022 5:24PM
A14: 138020001 | B14: REINTEGRO DE INCAPACIDADES | C14: 44545 | D14: 21 | E14: NOMINA NOVASOFT | G14: 000000001 | H14: GASTOS REEMBOLSABLES | I14: 77628 | J14: 0 | K14: 1 | L14: 800256161 | M14: ARP SURA | N14: 10020200 | O14: EJECUCIÓN | R14: 0 | S14: CONTABLE | T14: N | U14: 000000001 | V14: 0 | W14: TACOSITI | X14: Feb 8 2022 5:24PM | Y14: frmCON6093 | Z14: DESKTOP-5900GRN | AA14: TAMBIENTAL | AB14: Feb 8 2022 5:24PM
A15: 138020001 | B15: REINTEGRO DE INCAPACIDADES | C15: 44545 | D15: 21 | E15: NOMINA NOVASOFT | G15: 000000001 | H15: GASTOS REEMBOLSABLES | I15: 60568 | J15: 0 | K15: 1 | L15: 800130907 | M15: SALUD TOTAL S.A. EPS ARS | N15: 10030200 | O15: COORDINACIÓN DE OPERACIONES | R15: 0 | S15: CONTABLE | T15: N | U15: 000000001 | V15: 0 | W15: TACOSITI | X15: Feb 8 2022 5:24PM | Y15: frmCON6093 | Z15: DESKTOP-5900GRN | AA15: TAMBIENTAL | AB15: Feb 8 2022 5:24PM
A16: 138020001 | B16: REINTEGRO DE INCAPACIDADES | C16: 44545 | D16: 21 | E16: NOMINA NOVASOFT | G16: 000000001 | H16: GASTOS REEMBOLSABLES | I16: 67244 | J16: 0 | K16: 1 | L16: 800088702 | M16: EPS SURA COMPAÑIA SURAMERICANA SERVICIOS DE SALUD | N16: 10030400 | O16: OPERADORES | R16: 0 | S16: CONTABLE | T16: N | U16: 000000001 | V16: 0 | W16: TACOSITI | X16: Feb 8 2022 5:24PM | Y16: frmCON6093 | Z16: DESKTOP-5900GRN | AA16: TAMBIENTAL | AB16: Feb 8 2022 5:24PM
A17: 138020001 | B17: REINTEGRO DE INCAPACIDADES | C17: 44545 | D17: 21 | E17: NOMINA NOVASOFT | G17: 000000001 | H17: GASTOS REEMBOLSABLES | I17: 454263 | J17: 0 | K17: 1 | L17: 800130907 | M17: SALUD TOTAL S.A. EPS ARS | N17: 10030400 | O17: OPERADORES | R17: 0 | S17: CONTABLE | T17: N | U17: 000000001 | V17: 0 | W17: TACOSITI | X17: Feb 8 2022 5:24PM | Y17: frmCON6093 | Z17: DESKTOP-5900GRN | AA17: TAMBIENTAL | AB17: Feb 8 2022 5:24PM
A18: 138020001 | B18: REINTEGRO DE INCAPACIDADES | C18: 44545 | D18: 21 | E18: NOMINA NOVASOFT | G18: 000000001 | H18: GASTOS REEMBOLSABLES | I18: 32965 | J18: 0 | K18: 1 | L18: 800130907 | M18: SALUD TOTAL S.A. EPS ARS | N18: 10030400 | O18: OPERADORES | R18: 0 | S18: CONTABLE | T18: N | U18: 000000001 | V18: 0 | W18: TACOSITI | X18: Feb 8 2022 5:24PM | Y18: frmCON6093 | Z18: DESKTOP-5900GRN | AA18: TAMBIENTAL | AB18: Feb 8 2022 5:24PM
A19: 138020001 | B19: REINTEGRO DE INCAPACIDADES | C19: 44545 | D19: 21 | E19: NOMINA NOVASOFT | G19: 000000001 | H19: GASTOS REEMBOLSABLES | I19: 163561 | J19: 0 | K19: 1 | L19: 800130907 | M19: SALUD TOTAL S.A. EPS ARS | N19: 10030400 | O19: OPERADORES | R19: 0 | S19: CONTABLE | T19: N | U19: 000000001 | V19: 0 | W19: TACOSITI | X19: Feb 8 2022 5:24PM | Y19: frmCON6093 | Z19: DESKTOP-5900GRN | AA19: TAMBIENTAL | AB19: Feb 8 2022 5:24PM
A20: 138020001 | B20: REINTEGRO DE INCAPACIDADES | C20: 44545 | D20: 21 | E20: NOMINA NOVASOFT | G20: 000000001 | H20: GASTOS REEMBOLSABLES | I20: 363410 | J20: 0 | K20: 1 | L20: 800251440 | M20: E.P.S. SANITAS S.A. | N20: 10030400 | O20: OPERADORES | R20: 0 | S20: CONTABLE | T20: N | U20: 000000001 | V20: 0 | W20: TACOSITI | X20: Feb 8 2022 5:24PM | Y20: frmCON6093 | Z20: DESKTOP-5900GRN | AA20: TAMBIENTAL | AB20: Feb 8 2022 5:24PM
A21: 138020001 | B21: REINTEGRO DE INCAPACIDADES | C21: 44545 | D21: 21 | E21: NOMINA NOVASOFT | G21: 000000001 | H21: GASTOS REEMBOLSABLES | I21: 60568 | J21: 0 | K21: 1 | L21: 800251440 | M21: E.P.S. SANITAS S.A. | N21: 10030400 | O21: OPERADORES | R21: 0 | S21: CONTABLE | T21: N | U21: 000000001 | V21: 0 | W21: TACOSITI | X21: Feb 8 2022 5:24PM | Y21: frmCON6093 | Z21: DESKTOP-5900GRN | AA21: TAMBIENTAL | AB21: Feb 8 2022 5:24PM
A22: 138020001 | B22: REINTEGRO DE INCAPACIDADES | C22: 44545 | D22: 21 | E22: NOMINA NOVASOFT | G22: 000000001 | H22: GASTOS REEMBOLSABLES | I22: 30284 | J22: 0 | K22: 1 | L22: 800251440 | M22: E.P.S. SANITAS S.A. | N22: 10030400 | O22: OPERADORES | R22: 0 | S22: CONTABLE | T22: N | U22: 000000001 | V22: 0 | W22: TACOSITI | X22: Feb 8 2022 5:24PM | Y22: frmCON6093 | Z22: DESKTOP-5900GRN | AA22: TAMBIENTAL | AB22: Feb 8 2022 5:24PM
A23: 138020001 | B23: REINTEGRO DE INCAPACIDADES | C23: 44545 | D23: 21 | E23: NOMINA NOVASOFT | G23: 000000001 | H23: GASTOS REEMBOLSABLES | I23: 31088 | J23: 0 | K23: 1 | L23: 806008394 | M23: ASOCIACION MUTUAL SER EMPRESA SOLIDARIA | N23: 10030400 | O23: OPERADORES | R23: 0 | S23: CONTABLE | T23: N | U23: 000000001 | V23: 0 | W23: TACOSITI | X23: Feb 8 2022 5:24PM | Y23: frmCON6093 | Z23: DESKTOP-5900GRN | AA23: TAMBIENTAL | AB23: Feb 8 2022 5:24PM
... A25: 138020001 | B25: REINTEGRO DE INCAPACIDADES | C25: 44545 | D25: 21 | E25: NOMINA NOVASOFT | G25: 000000001 | H25: GASTOS REEMBOLSABLES | I25: 513641 | J25: 0 | K25: 1 | L25: 900156264 | M25: NUEVA EMPRESA PROMOTORA DE SALUD | N25: 10030400 | O25: OPERADORES | R25: 0 | S25: CONTABLE | T25: N | U25: 000000001 | V25: 0 | W25: TACOSITI | X25: Feb 8 2022 5:24PM | Y25: frmCON6093 | Z25: DESKTOP-5900GRN | AA25: TAMBIENTAL | AB25: Feb 8 2022 5:24PM
A26: 138020001 | B26: REINTEGRO DE INCAPACIDADES | C26: 44553 | D26: 15 | E26: CONSIGNACIONES BANCO | G26: 000000003 | H26: SALUD TOTAL S.A. EPS ARS:REINTEGRO INCAPACIDAD SALUD TOTAL000000003 | I26: 0 | J26: 885682 | K26: 1 | L26: 800130907 | M26: SALUD TOTAL S.A. EPS ARS | R26: 0 | S26: CONTABLE | T26: N | U26: 000000003 | V26: 0 | W26: TACOTESO | X26: Ene 14 2022 3:48PM | Y26: frmBAN607 | Z26: DESKTOP-O60S49G | AA26: TAMBIENTAL | AB26: Ene 14 2022 3:48PM
A27: 138020001 | B27: REINTEGRO DE INCAPACIDADES | C27: 44553 | D27: 15 | E27: CONSIGNACIONES BANCO | G27: 000000004 | H27: SALUD TOTAL S.A. EPS ARS:REINTEGRO INCAPACIDAD SALUD TOTAL000000004 | I27: 0 | J27: 274266 | K27: 1 | L27: 800130907 | M27: SALUD TOTAL S.A. EPS ARS | R27: 0 | S27: CONTABLE | T27: N | U27: 000000004 | V27: 0 | W27: TACOTESO | X27: Ene 14 2022 3:51PM | Y27: frmBAN607 | Z27: DESKTOP-O60S49G | AA27: TAMBIENTAL | AB27: Ene 14 2022 3:51PM
A28: 138020001 | B28: REINTEGRO DE INCAPACIDADES | C28: 44553 | D28: 15 | E28: CONSIGNACIONES BANCO | G28: 000000005 | H28: E.P.S. FAMISANAR LTDA. CAFAM COLSUBSIDIO:REINTEGRO INCAPACIDAD FAMISANAR000000005 | I28: 0 | J28: 97173 | K28: 1 | L28: 830003564 | M28: E.P.S. FAMISANAR LTDA. CAFAM COLSUBSIDIO | R28: 0 | S28: CONTABLE | T28: N | U28: 000000005 | V28: 0 | W28: TACOTESO | X28: Ene 14 2022 3:58PM | Y28: frmBAN607 | Z28: DESKTOP-O60S49G | AA28: TAMBIENTAL | AB28: Ene 14 2022 3:58PM
A29: 138020001 | B29: REINTEGRO DE INCAPACIDADES | C29: 44553 | D29: 15 | E29: CONSIGNACIONES BANCO | G29: 000000006 | H29: EPS SURA COMPAÑIA SURAMERICANA SERVICIOS DE SALUD:REINTEGRO INCAPACIDAD SURAMERICANA000000006 | I29: 0 | J29: 97524 | K29: 1 | L29: 800088702 | M29: EPS SURA COMPAÑIA SURAMERICANA SERVICIOS DE SALUD | R29: 0 | S29: CONTABLE | T29: N | U29: 000000006 | V29: 0 | W29: TACOTESO | X29: Ene 14 2022 4:37PM | Y29: frmBAN607 | Z29: DESKTOP-O60S49G | AA29: TAMBIENTAL | AB29: Ene 14 2022 4:37PM
A30: 138020001 | B30: REINTEGRO DE INCAPACIDADES | C30: 44554 | D30: 15 | E30: CONSIGNACIONES BANCO | G30: 000000015 | H30: ASOCIACION MUTUAL SER EMPRESA SOLIDARIA:Reintegro incapacidad Mutual SER000000015 | I30: 0 | J30: 31572 | K30: 1 | L30: 806008394 | M30: ASOCIACION MUTUAL SER EMPRESA SOLIDARIA | R30: 0 | S30: CONTABLE | T30: N | U30: 000000015 | V30: 0 | W30: TACOTESO | X30: Feb 15 2022 2:10PM | Y30: frmBAN607 | Z30: DESKTOP-O60S49G | AA30: TAMBIENTAL | AB30: Feb 15 2022 2:10PM
A31: 138020001 | B31: REINTEGRO DE INCAPACIDADES | C31: 44559 | D31: 15 | E31: CONSIGNACIONES BANCO | G31: 000000001 | H31: SALUD TOTAL S.A. EPS ARS:Reintegro incapacidad Salud Total000000001 | I31: 0 | J31: 133255 | K31: 1 | L31: 800130907 | M31: SALUD TOTAL S.A. EPS ARS | R31: 0 | S31: CONTABLE | T31: N | U31: 000000001 | V31: 0 | W31: TACOTESO | X31: Ene 14 2022 2:07PM | Y31: frmBAN607 | Z31: DESKTOP-O60S49G | AA31: TAMBIENTAL | AB31: Ene 14 2022 2:07PM
A32: 138020001 | B32: REINTEGRO DE INCAPACIDADES | C32: 44561 | D32: 21 | E32: NOMINA NOVASOFT | G32: 000000001 | H32: GASTOS REEMBOLSABLES | I32: 278990 | J32: 0 | K32: 1 | L32: 800256161 | M32: ARP SURA | N32: 10020200 | O32: EJECUCIÓN | R32: 0 | S32: CONTABLE | T32: N | U32: 000000001 | V32: 0 | W32: TACOSITI | X32: Feb 8 2022 5:24PM | Y32: frmCON6093 | Z32: DESKTOP-5900GRN | AA32: TAMBIENTAL | AB32: Feb 8 2022 5:24PM
A33: 138020001 | B33: REINTEGRO DE INCAPACIDADES | C33: 44561 | D33: 21 | E33: NOMINA NOVASOFT | G33: 000000001 | H33: GASTOS REEMBOLSABLES | I33: 33082 | J33: 0 | K33: 1 | L33: 800088702 | M33: EPS SURA COMPAÑIA SURAMERICANA SERVICIOS DE SALUD | N33: 10030400 | O33: OPERADORES | R33: 0 | S33: CONTABLE | T33: N | U33: 000000001 | V33: 0 | W33: TACOSITI | X33: Feb 8 2022 5:24PM | Y33: frmCON6093 | Z33: DESKTOP-5900GRN | AA33: TAMBIENTAL | AB33: Feb 8 2022 5:24PM
A34: 138020001 | B34: REINTEGRO DE INCAPACIDADES | C34: 44561 | D34: 21 | E34: NOMINA NOVASOFT | G34: 000000001 | H34: GASTOS REEMBOLSABLES | I34: 68499 | J34: 0 | K34: 1 | L34: 800088702 | M34: EPS SURA COMPAÑIA SURAMERICANA SERVICIOS DE SALUD | N34: 10030400 | O34: OPERADORES | R34: 0 | S34: CONTABLE | T34: N | U34: 000000001 | V34: 0 | W34: TACOSITI | X34: Feb 8 2022 5:24PM | Y34: frmCON6093 | Z34: DESKTOP-5900GRN | AA34: TAMBIENTAL | AB34: Feb 8 2022 5:24PM
A35: 138020001 | B35: REINTEGRO DE INCAPACIDADES | C35: 44561 | D35: 21 | E35: NOMINA NOVASOFT | G35: 000000001 | H35: GASTOS REEMBOLSABLES | I35: 484547 | J35: 0 | K35: 1 | L35: 800130907 | M35: SALUD TOTAL S.A. EPS ARS | N35: 10030400 | O35: OPERADORES | R35: 0 | S35: CONTABLE | T35: N | U35: 000000001 | V35: 0 | W35: TACOSITI | X35: Feb 8 2022 5:24PM | Y35: frmCON6093 | Z35: DESKTOP-5900GRN | AA35: TAMBIENTAL | AB35: Feb 8 2022 5:24PM
A36: 138020001 | B36: REINTEGRO DE INCAPACIDADES | C36: 44561 | D36: 21 | E36: NOMINA NOVASOFT | G36: 000000001 | H36: GASTOS REEMBOLSABLES | I36: 30881 | J36: 0 | K36: 1 | L36: 800130907 | M36: SALUD TOTAL S.A. EPS ARS | N36: 10030400 | O36: OPERADORES | R36: 0 | S36: CONTABLE | T36: N | U36: 000000001 | V36: 0 | W36: TACOSITI | X36: Feb 8 2022 5:24PM | Y36: frmCON6093 | Z36: DESKTOP-5900GRN | AA36: TAMBIENTAL | AB36: Feb 8 2022 5:24PM
A37: 138020001 | B37: REINTEGRO DE INCAPACIDADES | C37: 44561 | D37: 21 | E37: NOMINA NOVASOFT | G37: 000000001 | H37: GASTOS REEMBOLSABLES | I37: 102302 | J37: 0 | K37: 1 | L37: 800130907 | M37: SALUD TOTAL S.A. EPS ARS | N37: 10030400 | O37: OPERADORES | R37: 0 | S37: CONTABLE | T37: N | U37: 000000001 | V37: 0 | W37: TACOSITI | X37: Feb 8 2022 5:24PM | Y37: frmCON6093 | Z37: DESKTOP-5900GRN | AA37: TAMBIENTAL | AB37: Feb 8 2022 5:24PM
A38: 138020001 | B38: REINTEGRO DE INCAPACIDADES | C38: 44561 | D38: 21 | E38: NOMINA NOVASOFT | G38: 000000001 | H38: GASTOS REEMBOLSABLES | I38: 98137 | J38: 0 | K38: 1 | L38: 800130907 | M38: SALUD TOTAL S.A. EPS ARS | N38: 10030400 | O38: OPERADORES | R38: 0 | S38: CONTABLE | T38: N | U38: 000000001 | V38: 0 | W38: TACOSITI | X38: Feb 8 2022 5:24PM | Y38: frmCON6093 | Z38: DESKTOP-5900GRN | AA38: TAMBIENTAL | AB38: Feb 8 2022 5:24PM
A39: 138020001 | B39: REINTEGRO DE INCAPACIDADES | C39: 44561 | D39: 21 | E39: NOMINA NOVASOFT | G39: 000000001 | H39: GASTOS REEMBOLSABLES | I39: 34357 | J39: 0 | K39: 1 | L39: 800130907 | M39: SALUD TOTAL S.A. EPS ARS | N39: 10030400 | O39: OPERADORES | R39: 0 | S39: CONTABLE | T39: N | U39: 000000001 | V39: 0 | W39: TACOSITI | X39: Feb 8 2022 5:24PM | Y39: frmCON6093 | Z39: DESKTOP-5900GRN | AA39: TAMBIENTAL | AB39: Feb 8 2022 5:24PM
A40: 138020001 | B40: REINTEGRO DE INCAPACIDADES | C40: 44561 | D40: 21 | E40: NOMINA NOVASOFT | G40: 000000001 | H40: GASTOS REEMBOLSABLES | I40: 363411 | J40: 0 | K40: 1 | L40: 800251440 | M40: E.P.S. SANITAS S.A. | N40: 10030400 | O40: OPERADORES | R40: 0 | S40: CONTABLE | T40: N | U40: 000000001 | V40: 0 | W40: TACOSITI | X40: Feb 8 2022 5:24PM | Y40: frmCON6093 | Z40: DESKTOP-5900GRN | AA40: TAMBIENTAL | AB40: Feb 8 2022 5:24PM
A41: 138020001 | B41: REINTEGRO DE INCAPACIDADES | C41: 44561 | D41: 21 | E41: NOMINA NOVASOFT | G41: 000000001 | H41: GASTOS REEMBOLSABLES | I41: 33912 | J41: 0 | K41: 1 | L41: 800251440 | M41: E.P.S. SANITAS S.A. | N41: 10030400 | O41: OPERADORES | R41: 0 | S41: CONTABLE | T41: N | U41: 000000001 | V41: 0 | W41: TACOSITI | X41: Feb 8 2022 5:24PM | Y41: frmCON6093 | Z41: DESKTOP-5900GRN | AA41: TAMBIENTAL | AB41: Feb 8 2022 5:24PM
A42: 138020001 | B42: REINTEGRO DE INCAPACIDADES | C42: 44561 | D42: 21 | E42: NOMINA NOVASOFT | G42: 000000001 | H42: GASTOS REEMBOLSABLES | I42: 345056 | J42: 0 | K42: 1 | L42: 830003564 | M42: E.P.S. FAMISANAR LTDA. CAFAM COLSUBSIDIO | N42: 10030400 | O42: OPERADORES | R42: 0 | S42: CONTABLE | T42: N | U42: 000000001 | V42: 0 | W42: TACOSITI | X42: Feb 8 2022 5:24PM | Y42: frmCON6093 | Z42: DESKTOP-5900GRN | AA42: TAMBIENTAL | AB42: Feb 8 2022 5:24PM
A43: 138020001 | B43: REINTEGRO DE INCAPACIDADES | C43: 44561 | D43: 21 | E43: NOMINA NOVASOFT | G43: 000000001 | H43: GASTOS REEMBOLSABLES | I43: 32893 | J43: 0 | K43: 1 | L43: 900156264 | M43: NUEVA EMPRESA PROMOTORA DE SALUD | N43: 10030400 | O43: OPERADORES | R43: 0 | S43: CONTABLE | T43: N | U43: 000000001 | V43: 0 | W43: TACOSITI | X43: Feb 8 2022 5:24PM | Y43: frmCON6093 | Z43: DESKTOP-5900GRN | AA43: TAMBIENTAL | AB43: Feb 8 2022 5:24PM
... A48: 138020001 | B48: REINTEGRO DE INCAPACIDADES | C48: 44561 | D48: 21 | E48: NOMINA NOVASOFT | G48: 000000001 | H48: GASTOS REEMBOLSABLES | I48: 32438 | J48: 0 | K48: 1 | L48: 800088702 | M48: EPS SURA COMPAÑIA SURAMERICANA SERVICIOS DE SALUD | N48: 10030400 | O48: OPERADORES | R48: 0 | S48: CONTABLE | T48: N | U48: 000000001 | V48: 0 | W48: TACOSITI | X48: Feb 8 2022 5:24PM | Y48: frmCON6093 | Z48: DESKTOP-5900GRN | AA48: TAMBIENTAL | AB48: Feb 8 2022 5:24PM
A49: 138020001 | B49: REINTEGRO DE INCAPACIDADES | C49: 44561 | D49: 24 | E49: ASIENTOS DE CONTABILIDAD | G49: 000000048 | H49: REINTEGRO DE INCAPACIDADES | I49: 0 | J49: 0.01 | K49: 1 | L49: 900771273 | M49: TRANSAMBIENTAL | R49: 0 | S49: CONTABLE | T49: N | U49: 000000048 | V49: 0 | W49: TAAUXAREA | X49: Feb 25 2022 5:38PM | Y49: frmCON200 | Z49: PRACTICANTEFA | AA49: TAMBIENTAL | AB49: Mar 31 2022 5:14PM
A50: 138020001 | B50: REINTEGRO DE INCAPACIDADES | C50: 44573 | D50: 15 | E50: CONSIGNACIONES BANCO | G50: 000000042 | H50: NUEVA EMPRESA PROMOTORA DE SALUD:REINTEGRO INCAPACIDADES000000042 | I50: 0 | J50: 398184 | K50: 1 | L50: 900156264 | M50: NUEVA EMPRESA PROMOTORA DE SALUD | R50: 0 | S50: CONTABLE | T50: N | U50: 000000042 | V50: 0 | W50: TACOTESO | X50: Feb 24 2022 6:21PM | Y50: frmBAN607 | Z50: DESKTOP-O60S49G | AA50: TAMBIENTAL | AB50: Feb 24 2022 6:21PM
A51: 138020001 | B51: REINTEGRO DE INCAPACIDADES | C51: 44575 | D51: 15 | E51: CONSIGNACIONES BANCO | G51: 000000036 | H51: COOSALUD ENTIDAD PROMOTORA DE SALUD S.A:REINTEGRO INCAPACIDADES000000036 | I51: 0 | J51: 29261 | K51: 1 | L51: 900226715 | M51: COOSALUD ENTIDAD PROMOTORA DE SALUD S.A | R51: 0 | S51: CONTABLE | T51: N | U51: 000000036 | V51: 0 | W51: TACOTESO | X51: Feb 24 2022 6:07PM | Y51: frmBAN607 | Z51: DESKTOP-O60S49G | AA51: TAMBIENTAL | AB51: Feb 24 2022 6:07PM
A52: 138020001 | B52: REINTEGRO DE INCAPACIDADES | C52: 44575 | D52: 15 | E52: CONSIGNACIONES BANCO | G52: 000000037 | H52: COOSALUD ENTIDAD PROMOTORA DE SALUD S.A:REINTEGRO INCAPACIDADES000000037 | I52: 0 | J52: 30285 | K52: 1 | L52: 900226715 | M52: COOSALUD ENTIDAD PROMOTORA DE SALUD S.A | R52: 0 | S52: CONTABLE | T52: N | U52: 000000037 | V52: 0 | W52: TACOTESO | X52: Feb 24 2022 6:08PM | Y52: frmBAN607 | Z52: DESKTOP-O60S49G | AA52: TAMBIENTAL | AB52: Feb 24 2022 6:08PM
A53: 138020001 | B53: REINTEGRO DE INCAPACIDADES | C53: 44575 | D53: 15 | E53: CONSIGNACIONES BANCO | G53: 000000038 | H53: COOSALUD ENTIDAD PROMOTORA DE SALUD S.A:REINTEGRO INCAPACIDADES000000038 | I53: 0 | J53: 30285 | K53: 1 | L53: 900226715 | M53: COOSALUD ENTIDAD PROMOTORA DE SALUD S.A | R53: 0 | S53: CONTABLE | T53: N | U53: 000000038 | V53: 0 | W53: TACOTESO | X53: Feb 24 2022 6:11PM | Y53: frmBAN607 | Z53: DESKTOP-O60S49G | AA53: TAMBIENTAL | AB53: Feb 24 2022 6:11PM
A54: 138020001 | B54: REINTEGRO DE INCAPACIDADES | C54: 44575 | D54: 15 | E54: CONSIGNACIONES BANCO | G54: 000000039 | H54: COOSALUD ENTIDAD PROMOTORA DE SALUD S.A:REINTEGRO INCAPACIDADES000000039 | I54: 0 | J54: 31032 | K54: 1 | L54: 900226715 | M54: COOSALUD ENTIDAD PROMOTORA DE SALUD S.A | R54: 0 | S54: CONTABLE | T54: N | U54: 000000039 | V54: 0 | W54: TACOTESO | X54: Feb 24 2022 6:12PM | Y54: frmBAN607 | Z54: DESKTOP-O60S49G | AA54: TAMBIENTAL | AB54: Feb 24 2022 6:12PM
A55: 138020001 | B55: REINTEGRO DE INCAPACIDADES | C55: 44575 | D55: 15 | E55: CONSIGNACIONES BANCO | G55: 000000040 | H55: COOSALUD ENTIDAD PROMOTORA DE SALUD S.A:REINTEGRO INCAPACIDADES000000040 | I55: 0 | J55: 30285 | K55: 1 | L55: 900226715 | M55: COOSALUD ENTIDAD PROMOTORA DE SALUD S.A | R55: 0 | S55: CONTABLE | T55: N | U55: 000000040 | V55: 0 | W55: TACOTESO | X55: Feb 24 2022 6:17PM | Y55: frmBAN607 | Z55: DESKTOP-O60S49G | AA55: TAMBIENTAL | AB55: Feb 24 2022 6:17PM
A56: 138020001 | B56: REINTEGRO DE INCAPACIDADES | C56: 44575 | D56: 15 | E56: CONSIGNACIONES BANCO | G56: 000000041 | H56: COOSALUD ENTIDAD PROMOTORA DE SALUD S.A:REINTEGRO INCAPACIDADES000000041 | I56: 0 | J56: 173891 | K56: 1 | L56: 900226715 | M56: COOSALUD ENTIDAD PROMOTORA DE SALUD S.A | R56: 0 | S56: CONTABLE | T56: N | U56: 000000041 | V56: 0 | W56: TACOTESO | X56: Feb 24 2022 6:20PM | Y56: frmBAN607 | Z56: DESKTOP-O60S49G | AA56: TAMBIENTAL | AB56: Feb 24 2022 6:20PM
A57: 138020001 | B57: REINTEGRO DE INCAPACIDADES | C57: 44576 | D57: 21 | E57: NOMINA NOVASOFT | G57: 000000004 | H57: GASTOS REEMBOLSABLES | I57: 33334 | J57: 0 | K57: 1 | L57: 1128045753 | M57: ROJAS BUSTOS ESEIZA DEL CARMEN | N57: 10030200 | O57: COORDINACIÓN DE OPERACIONES | R57: 0 | S57: CONTABLE | T57: N | U57: 000000004 | V57: 0 | W57: TAAUXCON | X57: Mar 10 2022 6:41PM | Y57: frmCON6093 | Z57: LAPTOP-18GI5NJH | AA57: TAMBIENTAL | AB57: Mar 10 2022 6:41PM
A58: 138020001 | B58: REINTEGRO DE INCAPACIDADES | C58: 44576 | D58: 21 | E58: NOMINA NOVASOFT | G58: 000000004 | H58: GASTOS REEMBOLSABLES | I58: 270801 | J58: 0 | K58: 1 | L58: 72073849 | M58: DORIAN RODRIGUEZ OSPINO | N58: 10030400 | O58: OPERADORES | R58: 0 | S58: CONTABLE | T58: N | U58: 000000004 | V58: 0 | W58: TAAUXCON | X58: Mar 10 2022 6:41PM | Y58: frmCON6093 | Z58: LAPTOP-18GI5NJH | AA58: TAMBIENTAL | AB58: Mar 10 2022 6:41PM
A59: 138020001 | B59: REINTEGRO DE INCAPACIDADES | C59: 44576 | D59: 21 | E59: NOMINA NOVASOFT | G59: 000000004 | H59: GASTOS REEMBOLSABLES | I59: 33632 | J59: 0 | K59: 1 | L59: 73143163 | M59: JUAN CARLOS CABRERA TORRES | N59: 10030400 | O59: OPERADORES | R59: 0 | S59: CONTABLE | T59: N | U59: 000000004 | V59: 0 | W59: TAAUXCON | X59: Mar 10 2022 6:41PM | Y59: frmCON6093 | Z59: LAPTOP-18GI5NJH | AA59: TAMBIENTAL | AB59: Mar 10 2022 6:41PM
A60: 138020001 | B60: REINTEGRO DE INCAPACIDADES | C60: 44576 | D60: 21 | E60: NOMINA NOVASOFT | G60: 000000004 | H60: GASTOS REEMBOLSABLES | I60: 100000 | J60: 0 | K60: 1 | L60: 73202722 | M60: JESUS JAVIER BELTRAN OLIVELLA | N60: 10030400 | O60: OPERADORES | R60: 0 | S60: CONTABLE | T60: N | U60: 000000004 | V60: 0 | W60: TAAUXCON | X60: Mar 10 2022 6:41PM | Y60: frmCON6093 | Z60: LAPTOP-18GI5NJH | AA60: TAMBIENTAL | AB60: Mar 10 2022 6:41PM
A61: 138020001 | B61: REINTEGRO DE INCAPACIDADES | C61: 44576 | D61: 21 | E61: NOMINA NOVASOFT | G61: 000000004 | H61: GASTOS REEMBOLSABLES | I61: 35814 | J61: 0 | K61: 1 | L61: 7918997 | M61: MOISES CASTILLA GUTIERREZ | N61: 10030400 | O61: OPERADORES | R61: 0 | S61: CONTABLE | T61: N | U61: 000000004 | V61: 0 | W61: TAAUXCON | X61: Mar 10 2022 6:41PM | Y61: frmCON6093 | Z61: LAPTOP-18GI5NJH | AA61: TAMBIENTAL | AB61: Mar 10 2022 6:41PM
A62: 138020001 | B62: REINTEGRO DE INCAPACIDADES | C62: 44576 | D62: 21 | E62: NOMINA NOVASOFT | G62: 000000004 | H62: GASTOS REEMBOLSABLES | I62: 33334 | J62: 0 | K62: 1 | L62: 9288712 | M62: RAFAEL DE JESUS PUELLO HUETO | N62: 10030400 | O62: OPERADORES | R62: 0 | S62: CONTABLE | T62: N | U62: 000000004 | V62: 0 | W62: TAAUXCON | X62: Mar 10 2022 6:41PM | Y62: frmCON6093 | Z62: LAPTOP-18GI5NJH | AA62: TAMBIENTAL | AB62: Mar 10 2022 6:41PM
A63: 138020001 | B63: REINTEGRO DE INCAPACIDADES | C63: 44576 | D63: 21 | E63: NOMINA NOVASOFT | G63: 000000004 | H63: GASTOS REEMBOLSABLES | I63: 33334 | J63: 0 | K63: 1 | L63: 1002059942 | M63: WILSON RAFAEL SIMANCAS MARTINEZ | N63: 10030400 | O63: OPERADORES | R63: 0 | S63: CONTABLE | T63: N | U63: 000000004 | V63: 0 | W63: TAAUXCON | X63: Mar 10 2022 6:41PM | Y63: frmCON6093 | Z63: LAPTOP-18GI5NJH | AA63: TAMBIENTAL | AB63: Mar 10 2022 6:41PM
A64: 138020001 | B64: REINTEGRO DE INCAPACIDADES | C64: 44576 | D64: 21 | E64: NOMINA NOVASOFT | G64: 000000004 | H64: GASTOS REEMBOLSABLES | I64: 500000 | J64: 0 | K64: 1 | L64: 1047370459 | M64: JOSE AUGUSTO ARZUZA MARRUGO | N64: 10030400 | O64: OPERADORES | R64: 0 | S64: CONTABLE | T64: N | U64: 000000004 | V64: 0 | W64: TAAUXCON | X64: Mar 10 2022 6:41PM | Y64: frmCON6093 | Z64: LAPTOP-18GI5NJH | AA64: TAMBIENTAL | AB64: Mar 10 2022 6:41PM
A65: 138020001 | B65: REINTEGRO DE INCAPACIDADES | C65: 44576 | D65: 21 | E65: NOMINA NOVASOFT | G65: 000000004 | H65: GASTOS REEMBOLSABLES | I65: 37832 | J65: 0 | K65: 1 | L65: 1047364807 | M65: ALEJANDRO LUIS PEREZ PEDROZA | N65: 10030400 | O65: OPERADORES | R65: 0 | S65: CONTABLE | T65: N | U65: 000000004 | V65: 0 | W65: TAAUXCON | X65: Mar 10 2022 6:41PM | Y65: frmCON6093 | Z65: LAPTOP-18GI5NJH | AA65: TAMBIENTAL | AB65: Mar 10 2022 6:41PM
A66: 138020001 | B66: REINTEGRO DE INCAPACIDADES | C66: 44576 | D66: 21 | E66: NOMINA NOVASOFT | G66: 000000004 | H66: GASTOS REEMBOLSABLES | I66: 35677 | J66: 0 | K66: 1 | L66: 1049532983 | M66: PEDRO MANUEL MUÑIZ PADILLA | N66: 10030400 | O66: OPERADORES | R66: 0 | S66: CONTABLE | T66: N | U66: 000000004 | V66: 0 | W66: TAAUXCON | X66: Mar 10 2022 6:41PM | Y66: frmCON6093 | Z66: LAPTOP-18GI5NJH | AA66: TAMBIENTAL | AB66: Mar 10 2022 6:41PM
A67: 138020001 | B67: REINTEGRO DE INCAPACIDADES | C67: 44576 | D67: 21 | E67: NOMINA NOVASOFT | G67: 000000004 | H67: GASTOS REEMBOLSABLES | I67: 33856 | J67: 0 | K67: 1 | L67: 1137220216 | M67: TONNY JAYR ESTREMOR SALCEDO | N67: 10030400 | O67: OPERADORES | R67: 0 | S67: CONTABLE | T67: N | U67: 000000004 | V67: 0 | W67: TAAUXCON | X67: Mar 10 2022 6:41PM | Y67: frmCON6093 | Z67: LAPTOP-18GI5NJH | AA67: TAMBIENTAL | AB67: Mar 10 2022 6:41PM
A68: 138020001 | B68: REINTEGRO DE INCAPACIDADES | C68: 44576 | D68: 21 | E68: NOMINA NOVASOFT | G68: 000000004 | H68: GASTOS REEMBOLSABLES | I68: 500000 | J68: 0 | K68: 1 | L68: 73103777 | M68: RAMON CORREA GARCIA | N68: 10030400 | O68: OPERADORES | R68: 0 | S68: CONTABLE | T68: N | U68: 000000004 | V68: 0 | W68: TAAUXCON | X68: Mar 10 2022 6:41PM | Y68: frmCON6093 | Z68: LAPTOP-18GI5NJH | AA68: TAMBIENTAL | AB68: Mar 10 2022 6:41PM
... A82: 138020001 | B82: REINTEGRO DE INCAPACIDADES | C82: 44576 | D82: 21 | E82: NOMINA NOVASOFT | G82: 000000004 | H82: GASTOS REEMBOLSABLES | I82: 233334 | J82: 0 | K82: 1 | L82: 1047495774 | M82: LUVIS STELLA ZARZA REYES | N82: 10050400 | O82: SALUD OCUPACIONAL | R82: 0 | S82: CONTABLE | T82: N | U82: 000000004 | V82: 0 | W82: TAAUXCON | X82: Mar 10 2022 6:41PM | Y82: frmCON6093 | Z82: LAPTOP-18GI5NJH | AA82: TAMBIENTAL | AB82: Mar 10 2022 6:41PM
A83: 138020001 | B83: REINTEGRO DE INCAPACIDADES | C83: 44581 | D83: 15 | E83: CONSIGNACIONES BANCO | G83: 000000033 | H83: SALUD TOTAL S.A. EPS ARS:REINTEGRO INCAPACIDADES000000033 | I83: 0 | J83: 31475 | K83: 1 | L83: 800130907 | M83: SALUD TOTAL S.A. EPS ARS | R83: 0 | S83: CONTABLE | T83: N | U83: 000000033 | V83: 0 | W83: TACOTESO | X83: Feb 24 2022 6:04PM | Y83: frmBAN607 | Z83: DESKTOP-O60S49G | AA83: TAMBIENTAL | AB83: Feb 24 2022 6:04PM
A84: 138020001 | B84: REINTEGRO DE INCAPACIDADES | C84: 44581 | D84: 15 | E84: CONSIGNACIONES BANCO | G84: 000000034 | H84: SALUD TOTAL S.A. EPS ARS:REINTEGRO INCAPACIDADES000000034 | I84: 0 | J84: 423976 | K84: 1 | L84: 800130907 | M84: SALUD TOTAL S.A. EPS ARS | R84: 0 | S84: CONTABLE | T84: N | U84: 000000034 | V84: 0 | W84: TACOTESO | X84: Feb 24 2022 6:05PM | Y84: frmBAN607 | Z84: DESKTOP-O60S49G | AA84: TAMBIENTAL | AB84: Feb 24 2022 6:05PM
A85: 138020001 | B85: REINTEGRO DE INCAPACIDADES | C85: 44581 | D85: 15 | E85: CONSIGNACIONES BANCO | G85: 000000035 | H85: EPS SURA COMPAÑIA SURAMERICANA SERVICIOS DE SALUD:REINTEGRO INCAPACIDADES000000035 | I85: 0 | J85: 30284 | K85: 1 | L85: 800088702 | M85: EPS SURA COMPAÑIA SURAMERICANA SERVICIOS DE SALUD | R85: 0 | S85: CONTABLE | T85: N | U85: 000000035 | V85: 0 | W85: TACOTESO | X85: Feb 24 2022 6:06PM | Y85: frmBAN607 | Z85: DESKTOP-O60S49G | AA85: TAMBIENTAL | AB85: Feb 24 2022 6:06PM
A86: 138020001 | B86: REINTEGRO DE INCAPACIDADES | C86: 44585 | D86: 15 | E86: CONSIGNACIONES BANCO | G86: 000000025 | H86: SALUD TOTAL S.A. EPS ARS:REINTEGRO INCAPACIDADES000000025 | I86: 0 | J86: 33623 | K86: 1 | L86: 800130907 | M86: SALUD TOTAL S.A. EPS ARS | R86: 0 | S86: CONTABLE | T86: N | U86: 000000025 | V86: 0 | W86: TACOTESO | X86: Feb 24 2022 5:52PM | Y86: frmBAN607 | Z86: DESKTOP-O60S49G | AA86: TAMBIENTAL | AB86: Feb 24 2022 5:52PM
A87: 138020001 | B87: REINTEGRO DE INCAPACIDADES | C87: 44585 | D87: 15 | E87: CONSIGNACIONES BANCO | G87: 000000026 | H87: SALUD TOTAL S.A. EPS ARS:REINTEGRO INCAPACIDADES000000026 | I87: 0 | J87: 87781 | K87: 1 | L87: 800130907 | M87: SALUD TOTAL S.A. EPS ARS | R87: 0 | S87: CONTABLE | T87: N | U87: 000000026 | V87: 0 | W87: TACOTESO | X87: Feb 24 2022 5:55PM | Y87: frmBAN607 | Z87: DESKTOP-O60S49G | AA87: TAMBIENTAL | AB87: Feb 24 2022 5:55PM
A88: 138020001 | B88: REINTEGRO DE INCAPACIDADES | C88: 44585 | D88: 15 | E88: CONSIGNACIONES BANCO | G88: 000000027 | H88: SALUD TOTAL S.A. EPS ARS:REINTEGRO INCAPACIDADES000000027 | I88: 0 | J88: 29261 | K88: 1 | L88: 800130907 | M88: SALUD TOTAL S.A. EPS ARS | R88: 0 | S88: CONTABLE | T88: N | U88: 000000027 | V88: 0 | W88: TACOTESO | X88: Feb 24 2022 5:56PM | Y88: frmBAN607 | Z88: DESKTOP-O60S49G | AA88: TAMBIENTAL | AB88: Feb 24 2022 5:56PM
A89: 138020001 | B89: REINTEGRO DE INCAPACIDADES | C89: 44585 | D89: 15 | E89: CONSIGNACIONES BANCO | G89: 000000028 | H89: COOSALUD ENTIDAD PROMOTORA DE SALUD S.A:REINTEGRO INCAPACIDADES000000028 | I89: 0 | J89: 36615 | K89: 1 | L89: 900226715 | M89: COOSALUD ENTIDAD PROMOTORA DE SALUD S.A | R89: 0 | S89: CONTABLE | T89: N | U89: 000000028 | V89: 0 | W89: TACOTESO | X89: Feb 24 2022 5:57PM | Y89: frmBAN607 | Z89: DESKTOP-O60S49G | AA89: TAMBIENTAL | AB89: Feb 24 2022 5:57PM
A90: 138020001 | B90: REINTEGRO DE INCAPACIDADES | C90: 44585 | D90: 15 | E90: CONSIGNACIONES BANCO | G90: 000000029 | H90: COOSALUD ENTIDAD PROMOTORA DE SALUD S.A:REINTEGRO INCAPACIDADES000000029 | I90: 0 | J90: 29261 | K90: 1 | L90: 900226715 | M90: COOSALUD ENTIDAD PROMOTORA DE SALUD S.A | R90: 0 | S90: CONTABLE | T90: N | U90: 000000029 | V90: 0 | W90: TACOTESO | X90: Feb 24 2022 5:59PM | Y90: frmBAN607 | Z90: DESKTOP-O60S49G | AA90: TAMBIENTAL | AB90: Feb 24 2022 5:59PM
